Workbook
Name الاسم: Stock_New!$A$1:$A$273

Sheet Dashboard
A1: Product Name | B1: Total Qty | C1: Cost | D1: Revenue | E1: Profit Per Unit | F1: Total Profit | G1: Last Sale Date
A2: {=UNIQUE(Sales_New!A2:A4745)} -> بوت تركي | B2: {=IF(A2:A4745="","",SUMIF(Sales_New!A:A, A2:A4745, Sales_New!C:C))} -> 6 | C2: =IF($A2="", "", IFERROR(VLOOKUP($A2, Stock_New!$A:$M, 4, FALSE), "")) -> 105 | D2: =IF($A2="", "", IFERROR(VLOOKUP($A2, Stock_New!$A:$M, 6, FALSE), "")) -> 126 | E2: =D2-C2 -> 21 | F2: =B2*D2-B2*C2 -> 126
A3: شجرة تركيب 12 ورقة | B3: 2 | C3: =IF($A3="", "", IFERROR(VLOOKUP($A3, Stock_New!$A:$M, 4, FALSE), "")) -> 95 | D3: =IF($A3="", "", IFERROR(VLOOKUP($A3, Stock_New!$A:$M, 6, FALSE), "")) -> 114 | E3: =D3-C3 -> 19 | F3: =B3*D3-B3*C3 -> 38
A4: بوكيه خزف | B4: 1 | C4: =IF($A4="", "", IFERROR(VLOOKUP($A4, Stock_New!$A:$M, 4, FALSE), "")) -> 140 | D4: =IF($A4="", "", IFERROR(VLOOKUP($A4, Stock_New!$A:$M, 6, FALSE), "")) -> 168 | E4: =D4-C4 -> 28 | F4: =B4*D4-B4*C4 -> 28
A5: فازة خزف وورد احمر صغير | B5: 4 | C5: =IF($A5="", "", IFERROR(VLOOKUP($A5, Stock_New!$A:$M, 4, FALSE), "")) -> 135 | D5: =IF($A5="", "", IFERROR(VLOOKUP($A5, Stock_New!$A:$M, 6, FALSE), "")) -> 162 | E5: =D5-C5 -> 27 | F5: =B5*D5-B5*C5 -> 108
A6: فازة خزف وبوكيه ابيض كبير | B6: 1 | C6: =IF($A6="", "", IFERROR(VLOOKUP($A6, Stock_New!$A:$M, 4, FALSE), "")) -> 185 | D6: =IF($A6="", "", IFERROR(VLOOKUP($A6, Stock_New!$A:$M, 6, FALSE), "")) -> 222 | E6: =D6-C6 -> 37 | F6: =B6*D6-B6*C6 -> 37
A7: مزرعة | B7: 53 | C7: =IF($A7="", "", IFERROR(VLOOKUP($A7, Stock_New!$A:$M, 4, FALSE), "")) -> 37 | D7: =IF($A7="", "", IFERROR(VLOOKUP($A7, Stock_New!$A:$M, 6, FALSE), "")) -> 44.4 | E7: =D7-C7 -> 7.4 | F7: =B7*D7-B7*C7 -> 392.2
A8: شجرة ورق عريض | B8: 6 | C8: =IF($A8="", "", IFERROR(VLOOKUP($A8, Stock_New!$A:$M, 4, FALSE), "")) -> 195 | D8: =IF($A8="", "", IFERROR(VLOOKUP($A8, Stock_New!$A:$M, 6, FALSE), "")) -> 234 | E8: =D8-C8 -> 39 | F8: =B8*D8-B8*C8 -> 234
A9: بوكيه ورد احمر صغير واخضر | B9: 2 | C9: =IF($A9="", "", IFERROR(VLOOKUP($A9, Stock_New!$A:$M, 4, FALSE), "")) -> 170 | D9: =IF($A9="", "", IFERROR(VLOOKUP($A9, Stock_New!$A:$M, 6, FALSE), "")) -> 204 | E9: =D9-C9 -> 34 | F9: =B9*D9-B9*C9 -> 68
A10: مج بشاليموه | B10: 5 | C10: =IF($A10="", "", IFERROR(VLOOKUP($A10, Stock_New!$A:$M, 4, FALSE), "")) -> 75 | D10: =IF($A10="", "", IFERROR(VLOOKUP($A10, Stock_New!$A:$M, 6, FALSE), "")) -> 90 | E10: =D10-C10 -> 15 | F10: =B10*D10-B10*C10 -> 75
A11: اشكال السيرفرات | B11: 9 | C11: =IF($A11="", "", IFERROR(VLOOKUP($A11, Stock_New!$A:$M, 4, FALSE), "")) -> 120 | D11: =IF($A11="", "", IFERROR(VLOOKUP($A11, Stock_New!$A:$M, 6, FALSE), "")) -> 144 | E11: =D11-C11 -> 24 | F11: =B11*D11-B11*C11 -> 216
A12: مبخرة غزالة | B12: 10 | C12: =IF($A12="", "", IFERROR(VLOOKUP($A12, Stock_New!$A:$M, 4, FALSE), "")) -> 60 | D12: =IF($A12="", "", IFERROR(VLOOKUP($A12, Stock_New!$A:$M, 6, FALSE), "")) -> 72 | E12: =D12-C12 -> 12 | F12: =B12*D12-B12*C12 -> 120
A13: بوكيه بلاستيك وورد احمر | B13: 1 | C13: =IF($A13="", "", IFERROR(VLOOKUP($A13, Stock_New!$A:$M, 4, FALSE), "")) -> 220 | D13: =IF($A13="", "", IFERROR(VLOOKUP($A13, Stock_New!$A:$M, 6, FALSE), "")) -> 264 | E13: =D13-C13 -> 44 | F13: =B13*D13-B13*C13 -> 44
A14: بوكيه بلاستيك ورد كبير | B14: 1 | C14: =IF($A14="", "", IFERROR(VLOOKUP($A14, Stock_New!$A:$M, 4, FALSE), "")) -> 175 | D14: =IF($A14="", "", IFERROR(VLOOKUP($A14, Stock_New!$A:$M, 6, FALSE), "")) -> 210 | E14: =D14-C14 -> 35 | F14: =B14*D14-B14*C14 -> 35
... A103: فازة بورسلين | B103: 8 | C103: =IF($A103="", "", IFERROR(VLOOKUP($A103, Stock_New!$A:$M, 4, FALSE), "")) -> 195 | D103: =IF($A103="", "", IFERROR(VLOOKUP($A103, Stock_New!$A:$M, 6, FALSE), "")) -> 234 | E103: =D103-C103 -> 39 | F103: =B103*D103-B103*C103 -> 312
C104: =IF($A104="", "", IFERROR(VLOOKUP($A104, Stock_New!$A:$M, 4, FALSE), "")) | D104: =IF($A104="", "", IFERROR(VLOOKUP($A104, Stock_New!$A:$M, 6, FALSE), "")) | E104: =D104-C104 -> 0 | F104: =B104*D104-B104*C104 -> 0
A105: طقم ترمص | B105: 4 | C105: =IF($A105="", "", IFERROR(VLOOKUP($A105, Stock_New!$A:$M, 4, FALSE), "")) -> 165 | D105: =IF($A105="", "", IFERROR(VLOOKUP($A105, Stock_New!$A:$M, 6, FALSE), "")) -> 198 | E105: =D105-C105 -> 33 | F105: =B105*D105-B105*C105 -> 132
A106: شوكة وسط | B106: 5 | C106: =IF($A106="", "", IFERROR(VLOOKUP($A106, Stock_New!$A:$M, 4, FALSE), "")) -> 155 | D106: =IF($A106="", "", IFERROR(VLOOKUP($A106, Stock_New!$A:$M, 6, FALSE), "")) -> 186 | E106: =D106-C106 -> 31 | F106: =B106*D106-B106*C106 -> 155
A107: فازة خزف صغيرة تركي | B107: 10 | C107: =IF($A107="", "", IFERROR(VLOOKUP($A107, Stock_New!$A:$M, 4, FALSE), "")) -> 40 | D107: =IF($A107="", "", IFERROR(VLOOKUP($A107, Stock_New!$A:$M, 6, FALSE), "")) -> 48 | E107: =D107-C107 -> 8 | F107: =B107*D107-B107*C107 -> 80
A108: بوكيه مشمش | B108: 5 | C108: =IF($A108="", "", IFERROR(VLOOKUP($A108, Stock_New!$A:$M, 4, FALSE), "")) -> 50 | D108: =IF($A108="", "", IFERROR(VLOOKUP($A108, Stock_New!$A:$M, 6, FALSE), "")) -> 60 | E108: =D108-C108 -> 10 | F108: =B108*D108-B108*C108 -> 50
A109: قرنفل جيبسفيل | B109: 6.3333333 | C109: =IF($A109="", "", IFERROR(VLOOKUP($A109, Stock_New!$A:$M, 4, FALSE), "")) -> 75 | D109: =IF($A109="", "", IFERROR(VLOOKUP($A109, Stock_New!$A:$M, 6, FALSE), "")) -> 90 | E109: =D109-C109 -> 15 | F109: =B109*D109-B109*C109 -> 95
A110: شجرة مشمش فرعين | B110: 3 | C110: =IF($A110="", "", IFERROR(VLOOKUP($A110, Stock_New!$A:$M, 4, FALSE), "")) -> 175 | D110: =IF($A110="", "", IFERROR(VLOOKUP($A110, Stock_New!$A:$M, 6, FALSE), "")) -> 210 | E110: =D110-C110 -> 35 | F110: =B110*D110-B110*C110 -> 105
A111: مبخرة كهرباء 002/7 | B111: 1 | C111: =IF($A111="", "", IFERROR(VLOOKUP($A111, Stock_New!$A:$M, 4, FALSE), "")) -> 167.5 | D111: =IF($A111="", "", IFERROR(VLOOKUP($A111, Stock_New!$A:$M, 6, FALSE), "")) -> 201 | E111: =D111-C111 -> 33.5 | F111: =B111*D111-B111*C111 -> 33.5
A112: بخور ميسك كيس 5097 | B112: 6 | C112: =IF($A112="", "", IFERROR(VLOOKUP($A112, Stock_New!$A:$M, 4, FALSE), "")) | D112: =IF($A112="", "", IFERROR(VLOOKUP($A112, Stock_New!$A:$M, 6, FALSE), "")) | E112: =D112-C112 -> 0 | F112: =B112*D112-B112*C112 -> 0
A113: شمع 006/96 | B113: 14 | C113: =IF($A113="", "", IFERROR(VLOOKUP($A113, Stock_New!$A:$M, 4, FALSE), "")) -> 11.13 | D113: =IF($A113="", "", IFERROR(VLOOKUP($A113, Stock_New!$A:$M, 6, FALSE), "")) -> 13.36 | E113: =D113-C113 -> 2.23 | F113: =B113*D113-B113*C113 -> 31.22
A114: شوكة صغيرة | B114: 6 | C114: =IF($A114="", "", IFERROR(VLOOKUP($A114, Stock_New!$A:$M, 4, FALSE), "")) -> 130 | D114: =IF($A114="", "", IFERROR(VLOOKUP($A114, Stock_New!$A:$M, 6, FALSE), "")) -> 156 | E114: =D114-C114 -> 26 | F114: =B114*D114-B114*C114 -> 156
A115: بوكية اربع وردات | B115: 4 | C115: =IF($A115="", "", IFERROR(VLOOKUP($A115, Stock_New!$A:$M, 4, FALSE), "")) -> 85 | D115: =IF($A115="", "", IFERROR(VLOOKUP($A115, Stock_New!$A:$M, 6, FALSE), "")) -> 102 | E115: =D115-C115 -> 17 | F115: =B115*D115-B115*C115 -> 68
A116: أباجورة USB ناش 358 (عرض خاص) | B116: 2 | C116: =IF($A116="", "", IFERROR(VLOOKUP($A116, Stock_New!$A:$M, 4, FALSE), "")) -> 135 | D116: =IF($A116="", "", IFERROR(VLOOKUP($A116, Stock_New!$A:$M, 6, FALSE), "")) -> 162 | E116: =D116-C116 -> 27 | F116: =B116*D116-B116*C116 -> 54
... A315: مكعب روبيك ك 551 | B315: 3 | C315: =IF($A315="", "", IFERROR(VLOOKUP($A315, Stock_New!$A:$M, 4, FALSE), "")) -> 15 | D315: =IF($A315="", "", IFERROR(VLOOKUP($A315, Stock_New!$A:$M, 6, FALSE), "")) -> 18 | E315: =D315-C315 -> 3 | F315: =B315*D315-B315*C315 -> 9
A316: بولة خزف صغيرة | B316: 3
A317: مقزم مشمش | B317: 30
A318: عربية كروم صوت + نور 630 | B318: 2
A319: نيشان دارتس 482/1 | B319: 2
A320: نافورة ديكور 270 sm | B320: 1
A321: مبخرة فحم 3788 | B321: 1
A322: بلدي فرسان 24 | B322: 1
A323: بوكيه مشمش الفرسان | B323: 2
A324: ورد ديكور محمد رشدي | B324: 6
A325: مبخرة فحم 3207 | B325: 1
A326: شنطة هدايا صغير عادي | B326: 1
A327: فواحة USB 170/4 | B327: 1
... A385: طقم عربيات 6ق 575/1 | B385: 1

Sheet Stock_New
A1: Product Name | B1: ItemType | C1: Supplier | D1: AvgPurchasePrice | E1: AvailableQty | F1: SuggestedSalePrice | G1: LastUpdate | H1: TotalPurchasedQty | I1: TotalSoldQty | J1: TotalPurchaseValue | K1: TotalSalesValue | L1: LastUsageNote | M1: Toal Available
A2: موديل رقم 2052 | B2: سيلفرات | C2: ذكريا | D2: 1599 | E2: 1 | F2: 1918.8 | G2: 45856 | H2: 1 | I2: 0 | J2: 1599 | K2: 0 | M2: 1599
A3: موديل رقم 2053 | B3: سيلفرات | C3: ذكريا | D3: 1599 | E3: 1 | F3: 1918.8 | G3: 45856 | H3: 1 | I3: 0 | J3: 1599 | K3: 0 | M3: 1599
A4: موديل رقم 2058 | B4: سيلفرات | C4: ذكريا | D4: 1499 | E4: 1 | F4: 1798.8 | G4: 45856 | H4: 1 | I4: 0 | J4: 1499 | K4: 0 | M4: 1499
A5: موديل رقم 2057 | B5: سيلفرات | C5: ذكريا | D5: 1499 | E5: 0 | F5: 1798.8 | G5: 46090 | H5: 1 | I5: 1 | J5: 1499 | K5: 1500 | M5: 0
A6: موديل رقم 2051 | B6: سيلفرات | C6: ذكريا | D6: 1399 | E6: 2 | F6: 1678.8 | G6: 45856 | H6: 2 | I6: 0 | J6: 2798 | K6: 0 | M6: 2798
A7: موديل رقم 2043 | B7: سيلفرات | C7: ذكريا | D7: 1299 | E7: 1 | F7: 1558.8 | G7: 45856 | H7: 1 | I7: 0 | J7: 1299 | K7: 0 | M7: 1299
A8: موديل رقم 2042 | B8: سيلفرات | C8: ذكريا | D8: 1299 | E8: 1 | F8: 1558.8 | G8: 45856 | H8: 1 | I8: 0 | J8: 1299 | K8: 0 | M8: 1299
A9: موديل رقم 2001 | B9: سيلفرات | C9: ذكريا | D9: 1250 | E9: 1 | F9: 1500 | G9: 45856 | H9: 1 | I9: 0 | J9: 1250 | K9: 0 | M9: 1250
A10: موديل رقم 2003 | B10: سيلفرات | C10: ذكريا | D10: 1100 | E10: 2 | F10: 1320 | G10: 45856 | H10: 2 | I10: 0 | J10: 2200 | K10: 0 | M10: 2200
A11: سيكس ليف 5 جزع 170 سم | B11: شجر | C11: شركة الفرسان | D11: 1100 | E11: 1 | F11: 1320 | G11: 45987 | H11: 1 | I11: 0 | J11: 1100 | K11: 0 | M11: 1100
A12: موديل 935 | B12: سيلفرات | C12: ذكريا | D12: 999 | E12: 1 | F12: 1198.8 | G12: 45856 | H12: 1 | I12: 0 | J12: 999 | K12: 0 | M12: 999
A13: موديل 936 | B13: سيلفرات | C13: ذكريا | D13: 999 | E13: 1 | F13: 1198.8 | G13: 45856 | H13: 1 | I13: 0 | J13: 999 | K13: 0 | M13: 999
... A15: فازة ازاز كبيره وبوكيه | B15: بوكيه | C15: ذكريا | D15: 725 | E15: 1 | F15: 870 | G15: 45812 | H15: 1 | I15: 0 | J15: 725 | K15: 0 | M15: 725
A16: طقم باسكت | B16: سيلفرات | C16: ذكريا | D16: 725 | E16: 1 | F16: 870 | G16: done | H16: 2 | I16: 1 | J16: 1450 | K16: 934.53 | M16: 725
A17: شجرة موز 6 فرع | B17: شجر | C17: ذكريا | D17: 725 | E17: 1 | F17: 870 | G17: 45812 | H17: 1 | I17: 0 | J17: 725 | K17: 0 | M17: 725
A18: شمعدان نخلة | B18: سيلفرات | C18: ذكريا | D18: 625 | E18: 0 | F18: 750 | G18: 45945 | H18: 1 | I18: 1 | J18: 625 | K18: 800 | M18: 0
A19: شمعدان كريستال | B19: سيلفرات | C19: ذكريا | D19: 598.33 | E19: 1 | F19: 718 | G19: 46089 | H19: 3 | I19: 2 | J19: 1795 | K19: 1524.6 | M19: 598.33
A20: بونبونيرة عجلة | B20: سيلفرات | C20: ذكريا | D20: 575 | E20: 0 | F20: 690 | G20: 45898 | H20: 1 | I20: 1 | J20: 575 | K20: 700 | M20: 0
A21: شجرة ذرة وسط | B21: شجر | C21: ذكريا | D21: 575 | E21: 0 | F21: 690 | G21: 46037.857 | H21: 1 | I21: 1 | J21: 575 | K21: 600 | M21: 0
A22: شجرة موز 9 فرع | B22: شجر | C22: ذكريا | D22: 575 | E22: 0 | F22: 690 | G22: 46095.936 | H22: 1 | I22: 1 | J22: 575 | K22: 600 | M22: 0
A23: شجرة اريكا وسط | B23: شجر | C23: ذكريا | D23: 562.5 | E23: 0 | F23: 675 | G23: 46095.936 | H23: 2 | I23: 2 | J23: 1125 | K23: 1374.29 | M23: 0
A24: طقم بلورة زجاج | B24: سيلفرات | C24: ذكريا | D24: 525 | E24: 1 | F24: 630 | G24: 45835 | H24: 1 | I24: 0 | J24: 525 | K24: 0 | M24: 525
A25: شيالة ازاز 3 خلص | B25: سيلفر | C25: ذكريا | D25: 525 | E25: 0 | F25: 630 | G25: 45957 | H25: 1 | I25: 1 | J25: 525 | K25: 630 | M25: 0
A26: شجرة موز خمسة جزع 130 سم | B26: شجر | C26: شركة الفرسان | D26: 500 | E26: 1 | F26: 600 | G26: 45987 | H26: 1 | I26: 0 | J26: 500 | K26: 0 | M26: 500
A27: نافورة 1934 | B27: ديكور مكتب | C27: سنتر محمد رشدي | D27: 499 | E27: 0 | F27: 598.8 | G27: 46160 | H27: 1 | I27: 1 | J27: 499 | K27: 650 | M27: 499
A28: نافورة ديكور 10883 | B28: تحف | C28: محمد رشدي | D28: 490 | E28: 0 | F28: 588 | G28: 46100 | H28: 2 | I28: 2 | J28: 980 | K28: 1250 | M28: 0
... A33: بوت هاند ميد كبير | B33: بوكيه | C33: ذكريا | D33: 425 | E33: 2 | F33: 510 | G33: 45856 | H33: 2 | I33: 0 | J33: 850 | K33: 0 | M33: 850
A34: بوكيه كريستال شفاف وبوكيه اخضر | B34: بوكيه | C34: ذكريا | D34: =330+90 -> 420 | E34: 1 | F34: 612 | G34: 45835 | H34: 1 | I34: 0 | J34: 510 | K34: 0 | M34: 510
A35: طقم زجاج ابيض وريش وورد صغير | B35: بوكيه | C35: ذكريا | D35: 415 | E35: 1 | F35: 498 | G35: 45812 | H35: 1 | I35: 0 | J35: 415 | K35: 0 | M35: 415
A36: شجرة نجمة جلد | B36: شجر | C36: شركة حسين علي | D36: 412.5 | E36: 4 | F36: 495 | G36: 46116 | H36: 8 | I36: 4 | J36: 3300 | K36: 2000 | M36: 1650
A37: شجرة مانجا 18 ورقة | B37: شجر | C37: ذكريا | D37: 400 | E37: 0 | F37: 480 | G37: 45919 | H37: 1 | I37: 1 | J37: 400 | K37: 480 | M37: 0
A38: شجرة بامبو | B38: شجر | C38: ذكريا | D38: 400 | E38: 1 | F38: 480 | G38: 45812 | H38: 1 | I38: 0 | J38: 400 | K38: 0 | M38: 400
A39: فازة بورسلين كبيرة ابيض مذهب | B39: بورسلين | C39: شركة حسين علي | D39: 400 | E39: 3 | F39: 480 | G39: 46095 | H39: 3 | I39: 0 | J39: 1200 | K39: 0 | M39: 1200
A40: بوكيه فازة بورسلين دهبي وورد شبه التاج | B40: بوكيه | C40: ذكريا | D40: 385 | E40: 0 | F40: 462 | G40: 45901 | H40: 1 | I40: 1 | J40: 385 | K40: 490 | M40: 0
A41: شجرة موز صغيرة درجة عالية | B41: شجر | C41: ذكريا | D41: 375 | E41: 1 | F41: 450 | G41: 45929 | H41: 1 | I41: 0 | J41: 375 | K41: 0 | M41: 375
A42: فازة كريستال عسلي | B42: زجاج | C42: ذكريا | D42: 365 | E42: 0 | F42: 438 | G42: done | H42: 1 | I42: 1 | J42: 365 | K42: 789.61 | M42: 0
A43: شكل عاج كبير | B43: سيلفرات | C43: ذكريا | D43: 355 | E43: 2 | F43: 426 | G43: 45835 | H43: 2 | I43: 0 | J43: 710 | K43: 0 | M43: 710
A44: شيالة ازاز 3 | B44: سيلفرات | C44: شركة التقوى | D44: 350 | E44: 9 | F44: 420 | G44: 46100 | H44: 12 | I44: 3 | J44: 4200 | K44: 1300 | M44: 3150
A45: فازة بورسلين برجول كبيرة | B45: سيلفرات | C45: شركة الفرسان | D45: 350 | E45: 0 | F45: 420 | G45: 46097 | H45: 2 | I45: 2 | J45: 700 | K45: 800 | M45: 0
A46: نافورة ديكور 270 sm | B46: تحف | C46: محمد رشدي | D46: 338 | E46: 0 | F46: 405.6 | G46: 46107 | H46: 1 | I46: 1 | J46: 338 | K46: 500 | M46: 338
A47: نافورة ديكور 3307 sm | B47: تحف | C47: محمد رشدي | D47: 338 | E47: 1 | F47: 405.6 | G47: 46099 | H47: 1 | I47: 0 | J47: 338 | K47: 0 | M47: 338
A48: نافورة ديكور 3309 | B48: نافورة ديكور | C48: سنتر محمد رشدي | D48: 338 | E48: 1 | F48: 405.6 | G48: 46165 | H48: 1 | I48: 0 | J48: 338 | K48: 0
A49: نافورة ديكور 206/1 | B49: نافورة ديكور | C49: سنتر محمد رشدي | D49: 338 | E49: 0 | F49: 405.6 | G49: 46159 | H49: 1 | I49: 1 | J49: 338 | K49: 500
A50: نافورة ديكور 3307 | B50: نافورة ديكور | C50: سنتر محمد رشدي | D50: 338 | E50: 1 | F50: 405.6 | G50: 46165 | H50: 1 | I50: 0 | J50: 338 | K50: 0
A51: نافورة ديكور 3311 | B51: نافورة ديكور | C51: سنتر محمد رشدي | D51: 338 | E51: 1 | F51: 405.6 | G51: 46165 | H51: 1 | I51: 0 | J51: 338 | K51: 0
A52: نافورة ديكور 3310 | B52: نافورة ديكور | C52: سنتر محمد رشدي | D52: 338 | E52: 0 | F52: 405.6 | G52: 46166 | H52: 1 | I52: 1 | J52: 338 | K52: 500
A53: شجرة ياسمين 110سم | B53: شجر | C53: manufactured | D53: 330 | E53: 1 | F53: 396 | G53: 7350945 | H53: 2 | I53: 1 | J53: 660 | K53: 450 | L53: Manufactured via شجرة-ياسمين-110 | M53: 330
A54: طقم زجاج ابيض وبوكيه اخضر | B54: بوكيه | C54: ذكريا | D54: 325 | E54: 1 | F54: 390 | G54: 45812 | H54: 1 | I54: 0 | J54: 325 | K54: 0 | M54: 325
A55: شجرة موز كبيرة | B55: شجر | C55: ذكريا | D55: 325 | E55: 0 | F55: 390 | G55: 46099 | H55: 2 | I55: 2 | J55: 650 | K55: 789.73 | M55: 0
A56: شجرة مشمش خمس فروع | B56: شجر | C56: ذكريا | D56: 325 | E56: 0 | F56: 390 | G56: 45999 | H56: 2 | I56: 2 | J56: 650 | K56: 814.58 | M56: 0
A57: فواحة | B57: كهربائيات | C57: ذكريا | D57: 325 | E57: 2 | F57: 390 | G57: 45845 | H57: 2 | I57: 0 | J57: 650 | K57: 0 | M57: 650
A58: بونبونيرة | B58: سيلفرات | C58: ذكريا | D58: 325 | E58: 1 | F58: 390 | G58: 45856 | H58: 1 | I58: 0 | J58: 325 | K58: 0 | M58: 325
A59: فازة بورسلين كبيرة | B59: سيلفرات | C59: ذكريا | D59: 325 | E59: 0 | F59: 390 | G59: 46088 | H59: 2 | I59: 2 | J59: 650 | K59: 700 | M59: 0
A60: شمعدان رفيع كريستال | B60: سيلفرات | C60: ذكريا | D60: 325 | E60: 2 | F60: 390 | G60: 45945 | H60: 2 | I60: 0 | J60: 650 | K60: 0 | M60: 650
A61: شجرة ياسمين 80سم | B61: شجر | C61: manufactured | D61: 315 | E61: 0 | F61: 378 | G61: 46152 | H61: 1 | I61: 6 | J61: 315 | K61: 2280 | L61: Manufactured via شجرة-ياسمين | M61: 0
A62: شجرة مكثفة | B62: شجر | C62: ذكريا | D62: 310 | E62: 0 | F62: 372 | G62: done | H62: 1 | I62: 1 | J62: 310 | K62: 450 | M62: 0
A63: شجرة مكثفة ورق | B63: شجر | C63: ذكريا | D63: 310 | E63: 1 | F63: 372 | G63: 45835 | H63: 1 | I63: 0 | J63: 310 | K63: 0 | M63: 310
A64: بوكيه بلاستيك و ريش واخضر عرايس:) | B64: بوكيه | C64: ذكريا | D64: 310 | E64: 0 | F64: 372 | G64: 45899 | H64: 1 | I64: 1 | J64: 310 | K64: 374.74 | M64: 0
A65: طقم زجاج ابيض وريش بس | B65: بوكيه | C65: ذكريا | D65: 300 | E65: 1 | F65: 360 | G65: 45812 | H65: 1 | I65: 0 | J65: 300 | K65: 0 | M65: 300
A66: طقم كاندي غزالة | B66: مطبخ | C66: ذكريا | D66: 300 | E66: 0 | F66: 360 | G66: 45998.011 | H66: 2 | I66: 2 | J66: 600 | K66: 779.6 | M66: 0
A67: طقم كاندي | B67: سيلفرات | C67: ذكريا | D67: 300 | E67: 1 | F67: 360 | G67: 46075 | H67: 2 | I67: 1 | J67: 600 | K67: 300 | M67: 300
A68: فازة بورسلين وسط ابيض مذهب | B68: بورسلين | C68: شركة حسين علي | D68: 300 | E68: 2 | F68: 360 | G68: 46095 | H68: 2 | I68: 0 | J68: 600 | K68: 0 | M68: 600
A69: ديكور ميكياج 0250 | B69: ميكاب | C69: سنتر محمد رشدي | D69: 300 | E69: 2 | F69: 360 | G69: 46083 | H69: 2 | I69: 0 | J69: 600 | K69: 0 | M69: 600
A70: شجرة موزة جلد 9 ورقة فردي 40×10 اسم | B70: شجر | C70: شركة الفرسان | D70: 300 | E70: 0 | F70: 360 | G70: 46168 | H70: 1 | I70: 1 | J70: 300 | K70: 375 | M70: 300
A71: فازة بورسلين برجول صغير | B71: فازة | C71: شركة الفرسان | D71: 300 | E71: 2 | F71: 360 | G71: 46095 | H71: 2 | I71: 0 | J71: 600 | K71: 0 | M71: 600
A72: شجرة فانباخيا صغيرة 12 | B72: شجر | C72: شركة حسين علي | D72: 300 | E72: 1 | F72: 360 | G72: 46154 | H72: 1 | I72: 0 | J72: 300 | K72: 0
A73: فازة ازاز وبوكيه ورد غالي | B73: بوكيه زجاج | C73: ذكريا | D73: 295 | E73: 2 | F73: 354 | G73: 45812 | H73: 2 | I73: 0 | J73: 590 | K73: 0 | M73: 590
A74: بوكيه بلاستيك و ريش واخضر عرايس:) | B74: بوكيه | D74: 290 | E74: 1 | M74: 290
A75: ديكور معدن 6450/1 | B75: سيلفرات | C75: سنتر محمد رشدي | D75: 290 | E75: 1 | F75: 348 | G75: 46168 | H75: 2 | I75: 1 | J75: 580 | K75: 400 | M75: 580
A76: مصلية لوكس- 0511 | B76: سيلفر | C76: سنتر محمد رشدي | D76: 288 | E76: 1 | F76: 345.6 | G76: 46067 | H76: 1 | I76: 0 | J76: 288 | K76: 0 | M76: 288
A77: شجرة مشمش 4 فروع | B77: شجر | C77: ذكريا | D77: 275 | E77: 4 | F77: 330 | G77: 45998.011 | H77: 5 | I77: 1 | J77: 1375 | K77: 329.77 | M77: 1100
A78: بوكيهورد كثيف وفازة بورسلين بقاعدة | B78: بوكيه | C78: ذكريا | D78: 275 | E78: 0 | F78: 330 | G78: 45835 | H78: 1 | I78: 0 | J78: 275 | K78: 0 | L78: Used 1 in تفكيك | M78: 0
A79: شجرة مشمش اربع فروع | B79: شجر | C79: ذكريا | D79: 275 | E79: 3 | F79: 330 | G79: 45845 | H79: 3 | I79: 0 | J79: 825 | K79: 0 | M79: 825
A80: بوت تركي هاند ميد | B80: بوتات | C80: ذكريا | D80: 275 | E80: 0 | F80: 330 | G80: 9/30/2025 | H80: 1 | I80: 1 | J80: 275 | K80: 400 | M80: 0
A81: ورد توليب بزهور | B81: ورد لوحده | C81: ذكريا | D81: 275 | E81: 0 | F81: 330 | G81: 46088 | H81: 1 | I81: 1 | J81: 275 | K81: 330 | M81: 0
A82: شبكة ورق شجر | B82: لوح | C82: ذكريا | D82: 275 | E82: 0 | F82: 330 | G82: 46057 | H82: 1 | I82: 1 | J82: 275 | K82: 300 | M82: 0
A83: سرير ستارة وورم - 6005 | B83: كهربائيات | C83: سنتر محمد رشدي | D83: 255 | E83: 5 | F83: 306 | G83: 46067 | H83: 5 | I83: 0 | J83: 1275 | K83: 0 | M83: 1275
A84: منظم بلاستيك 89 | B84: ميكاب | C84: سنتر محمد رشدي | D84: 255 | E84: 1 | F84: 306 | G84: 46090 | H84: 2 | I84: 1 | J84: 510 | K84: 350 | M84: 255
A85: شجرة موز صغيرة | B85: شجر | C85: ذكريا | D85: 250 | E85: 0 | F85: 300 | G85: 45899 | H85: 1 | I85: 1 | J85: 250 | K85: 299.79 | M85: 0
A86: دستة ورق نعناع | B86: ورق شجر | C86: شركة الفرسان | D86: 250 | E86: 1 | F86: 300 | G86: 45987 | H86: 1 | I86: 0 | J86: 250 | K86: 0 | M86: 250
A87: دستة ورق خروع الوان | B87: ورق شجر | C87: شركة الفرسان | D87: 250 | E87: 1 | F87: 300 | G87: 45987 | H87: 1 | I87: 0 | J87: 250 | K87: 0 | M87: 250
A88: فازة بورسلين صغيرابيض مذهب | B88: بورسلين | C88: شركة حسين علي | D88: 250 | E88: 2 | F88: 300 | G88: 46095 | H88: 2 | I88: 0 | J88: 500 | K88: 0 | M88: 500
A89: سرية وورم- 8021 | B89: كهربائيات | C89: سنتر محمد رشدي | D89: 250 | E89: 3 | F89: 300 | G89: 46067 | H89: 3 | I89: 0 | J89: 750 | K89: 0 | M89: 750
A90: عروسة نضارة 6018 | B90: لعب | C90: محمد رشدي | D90: 250 | E90: 3 | F90: 300 | G90: 46099 | H90: 3 | I90: 0 | J90: 750 | K90: 0 | M90: 750
A91: شجرة كريز 36 | B91: شجر | C91: شركة حسين علي | D91: 250 | E91: 2 | F91: 300 | G91: 46154 | H91: 2 | I91: 0 | J91: 500 | K91: 0
A92: مبخرة فحم - 4343 | B92: مباخر | C92: سنتر محمد رشدي | D92: 245 | E92: 0 | F92: 294 | G92: 46160 | H92: 1 | I92: 1 | J92: 245 | K92: 320 | M92: 245
A93: سرية وورم - 8044 | B93: كهربائيات | C93: سنتر محمد رشدي | D93: 242 | E93: 5 | F93: 290.4 | G93: 46067 | H93: 5 | I93: 0 | J93: 1210 | K93: 0 | M93: 1210
A94: موزه فردي 120 سم V7 فردي sf-106 | B94: شجر | C94: شركة الفرسان | D94: 240 | E94: 1 | F94: 288 | G94: 46083 | H94: 1 | I94: 0 | J94: 240 | K94: 0 | M94: 240
A95: شجرة فانباخيا صغيرة | B95: شجر | C95: ذكريا | D95: 235 | E95: 0 | F95: 282 | G95: 45998.011 | H95: 1 | I95: 1 | J95: 235 | K95: 284.86 | M95: 0
A96: بوت صغير هااند ميد و 2 بوكيه | B96: بوكيه | C96: ذكريا | D96: 235 | E96: 1 | F96: 282 | G96: 45924 | H96: 3 | I96: 2 | J96: 705 | K96: 699.65 | M96: 235
A97: شجرة بلدي 48 | B97: شجر | C97: شركة حسين علي | D97: 233.33 | E97: 2 | F97: 280 | G97: 46152 | H97: 6 | I97: 4 | J97: 1400 | K97: 1135 | M97: 699.99
A98: ديكور بالنور 678/1 | B98: كهربائيات | C98: سنتر محمد رشدي | D98: 229.5 | E98: 2 | F98: 275.4 | G98: 46083 | H98: 2 | I98: 0 | J98: 459 | K98: 0 | M98: 459
A99: ديكور بالنور 678/2 | B99: كهربائيات | C99: سنتر محمد رشدي | D99: 229.5 | E99: 0 | F99: 275.4 | G99: 46136.042 | H99: 2 | I99: 2 | J99: 459 | K99: 570 | M99: 229.5
A100: شمعدان ديكور ساعة 3B | B100: شمعدان | C100: سنتر محمد رشدي | D100: 227 | E100: 1 | F100: 272.4 | G100: 46154 | H100: 1 | I100: 0 | J100: 227 | K100: 0
A101: شجرة مشمش 3 فروع | B101: شجر | C101: ذكريا | D101: 225 | E101: 1 | F101: 270 | G101: 45999 | H101: 1 | I101: 0 | J101: 225 | K101: 0 | M101: 225
A102: بوكيه ورد كبير ابيض واخضر | B102: بوكيه | C102: ذكريا | D102: 225 | E102: 0 | F102: 270 | G102: done | H102: 1 | I102: 1 | J102: 225 | K102: 300 | M102: 0
A103: ورد بلدي | B103: ورد لوحده | C103: ذكريا | D103: 225 | E103: 0 | F103: 270 | G103: 46023.837 | H103: 5 | I103: 5 | J103: 1125 | K103: 1549.81 | M103: 0
A104: شجرة موز صغيرة | B104: كهربائيات | C104: ذكريا | D104: 225 | E104: 3 | F104: 270 | G104: 45904 | H104: 3 | I104: 0 | J104: 675 | K104: 0 | M104: 675
A105: ورد بلدي مسحوب | B105: ورد لوحده | C105: ذكريا | D105: 225 | E105: 5 | F105: 270 | G105: 46136.042 | H105: 6 | I105: 1 | J105: 1350 | K105: 420 | M105: 1350
...

Sheet جرد 2026
A1: Product Name | B1: ItemType | C1: Supplier | D1: AvailableQty | E1: Cost price | F1: Toal Available | G1: Should be
A2: شجرة مانغوليا 80 سم | B2: =IF(A2="","",IFERROR(VLOOKUP(A2, Stock_New!A:M, 2, FALSE),"")) -> شجر صناعي | C2: =IF(A2="","",IFERROR(VLOOKUP(A2, Stock_New!A:M, 3, FALSE),"")) -> manufactured | D2: =3+2+1+1 -> 7 | E2: 90 | F2: =E2*D2 -> 630 | G2: =IF($A2="", "", IFERROR(VLOOKUP($A2, Stock_New!$A:$M, 5, FALSE), "")) -> 4
A3: شجرة مانغوليا 110 سم | B3: =IF(A3="","",IFERROR(VLOOKUP(A3, Stock_New!A:M, 2, FALSE),"")) -> شجر | C3: =IF(A3="","",IFERROR(VLOOKUP(A3, Stock_New!A:M, 3, FALSE),"")) -> manufactured | D3: =2+4+2+1+2 -> 11 | E3: 105 | F3: =E3*D3 -> 1155 | G3: =IF($A3="", "", IFERROR(VLOOKUP($A3, Stock_New!$A:$M, 5, FALSE), "")) -> 4
A4: شجرة مانغوليا 150 سم | B4: =IF(A4="","",IFERROR(VLOOKUP(A4, Stock_New!A:M, 2, FALSE),"")) -> شجر صناعي | C4: =IF(A4="","",IFERROR(VLOOKUP(A4, Stock_New!A:M, 3, FALSE),"")) -> manufactured | D4: 1 | E4: 130 | F4: =E4*D4 -> 130 | G4: =IF($A4="", "", IFERROR(VLOOKUP($A4, Stock_New!$A:$M, 5, FALSE), "")) -> 1
A5: شجرة بنجامين 80سم | B5: =IF(A5="","",IFERROR(VLOOKUP(A5, Stock_New!A:M, 2, FALSE),"")) -> شجر | C5: =IF(A5="","",IFERROR(VLOOKUP(A5, Stock_New!A:M, 3, FALSE),"")) -> manufactured | D5: =2+1+2+1+3+1+3+1 -> 14 | E5: =35+20+10 -> 65 | F5: =E5*D5 -> 910 | G5: =IF($A5="", "", IFERROR(VLOOKUP($A5, Stock_New!$A:$M, 5, FALSE), "")) -> 2
A6: شجرة بنجامين 110سم | B6: =IF(A6="","",IFERROR(VLOOKUP(A6, Stock_New!A:M, 2, FALSE),"")) -> بوكيه | C6: =IF(A6="","",IFERROR(VLOOKUP(A6, Stock_New!A:M, 3, FALSE),"")) -> manufactured | D6: =2+1+2+3 -> 8 | E6: =70+20+10 -> 100 | F6: =E6*D6 -> 800 | G6: =IF($A6="", "", IFERROR(VLOOKUP($A6, Stock_New!$A:$M, 5, FALSE), "")) -> 1
A7: شجرة خروع 80 سم | B7: شجر | C7: manufactured | D7: 1 | E7: =100+20+10 -> 130 | F7: =E7*D7 -> 130 | G7: =IF($A7="", "", IFERROR(VLOOKUP($A7, Stock_New!$A:$M, 5, FALSE), ""))
A8: شجرة ياسمين 80 سم مكثفة | B8: شجر | C8: manufactured | D8: 1 | E8: =3*90+20+10 -> 300 | F8: =E8*D8 -> 300 | G8: =IF($A8="", "", IFERROR(VLOOKUP($A8, Stock_New!$A:$M, 5, FALSE), ""))
A9: شجرة ياسمين 110سم | B9: =IF(A9="","",IFERROR(VLOOKUP(A9, Stock_New!A:M, 2, FALSE),"")) -> شجر | C9: =IF(A9="","",IFERROR(VLOOKUP(A9, Stock_New!A:M, 3, FALSE),"")) -> manufactured | D9: 1 | E9: =IF($A9="", "", IFERROR(VLOOKUP($A9, Stock_New!$A:$M, 4, FALSE), "")) -> 330 | F9: =E9*D9 -> 330 | G9: =IF($A9="", "", IFERROR(VLOOKUP($A9, Stock_New!$A:$M, 5, FALSE), "")) -> 1
A10: شجرة ياسمين 80سم | B10: =IF(A10="","",IFERROR(VLOOKUP(A10, Stock_New!A:M, 2, FALSE),"")) -> شجر | C10: =IF(A10="","",IFERROR(VLOOKUP(A10, Stock_New!A:M, 3, FALSE),"")) -> manufactured | D10: 1 | E10: =3*75+10+20 -> 255 | F10: =E10*D10 -> 255 | G10: =IF($A10="", "", IFERROR(VLOOKUP($A10, Stock_New!$A:$M, 5, FALSE), "")) -> 0
A11: شجرة مشمش فرعين | B11: =IF(A11="","",IFERROR(VLOOKUP(A11, Stock_New!A:M, 2, FALSE),"")) -> شجر | C11: =IF(A11="","",IFERROR(VLOOKUP(A11, Stock_New!A:M, 3, FALSE),"")) -> ذكريا | D11: =1+1+1 -> 3 | E11: =3*75+10+20 -> 255 | F11: =E11*D11 -> 765 | G11: =IF($A11="", "", IFERROR(VLOOKUP($A11, Stock_New!$A:$M, 5, FALSE), "")) -> 3
A12: بوت وسط فاضي | B12: =IF(A12="","",IFERROR(VLOOKUP(A12, Stock_New!A:M, 2, FALSE),"")) -> بوتات | C12: =IF(A12="","",IFERROR(VLOOKUP(A12, Stock_New!A:M, 3, FALSE),"")) -> عبدالفتاح | D12: =13+4+1+4+65+6+12+10+13+14 -> 142 | E12: =IF($A12="", "", IFERROR(VLOOKUP($A12, Stock_New!$A:$M, 4, FALSE), "")) -> 35 | F12: =E12*D12 -> 4970 | G12: =IF($A12="", "", IFERROR(VLOOKUP($A12, Stock_New!$A:$M, 5, FALSE), "")) -> 121
A13: شجرة نجمة جلد | B13: =IF(A13="","",IFERROR(VLOOKUP(A13, Stock_New!A:M, 2, FALSE),"")) -> شجر | C13: =IF(A13="","",IFERROR(VLOOKUP(A13, Stock_New!A:M, 3, FALSE),"")) -> شركة حسين علي | D13: =2+2 -> 4 | E13: =IF($A13="", "", IFERROR(VLOOKUP($A13, Stock_New!$A:$M, 4, FALSE), "")) -> 412.5 | F13: =E13*D13 -> 1650 | G13: =IF($A13="", "", IFERROR(VLOOKUP($A13, Stock_New!$A:$M, 5, FALSE), "")) -> 4
A14: شجرة جلد تركيب 18 عصفورة | B14: =IF(A14="","",IFERROR(VLOOKUP(A14, Stock_New!A:M, 2, FALSE),"")) -> شجر | C14: =IF(A14="","",IFERROR(VLOOKUP(A14, Stock_New!A:M, 3, FALSE),"")) -> شركة حسين علي | D14: =1+1 -> 2 | E14: =IF($A14="", "", IFERROR(VLOOKUP($A14, Stock_New!$A:$M, 4, FALSE), "")) -> 200 | F14: =E14*D14 -> 400 | G14: =IF($A14="", "", IFERROR(VLOOKUP($A14, Stock_New!$A:$M, 5, FALSE), "")) -> 2
A15: بوت جامبو طويل | B15: =IF(A15="","",IFERROR(VLOOKUP(A15, Stock_New!A:M, 2, FALSE),"")) -> بوتات | C15: =IF(A15="","",IFERROR(VLOOKUP(A15, Stock_New!A:M, 3, FALSE),"")) -> عبدالفتاح | D15: =2+2+5 -> 9 | E15: =IF($A15="", "", IFERROR(VLOOKUP($A15, Stock_New!$A:$M, 4, FALSE), "")) -> 175 | F15: =E15*D15 -> 1575 | G15: =IF($A15="", "", IFERROR(VLOOKUP($A15, Stock_New!$A:$M, 5, FALSE), "")) -> 9
A16: شجرة مشمش 4 فروع | B16: =IF(A16="","",IFERROR(VLOOKUP(A16, Stock_New!A:M, 2, FALSE),"")) -> شجر | C16: =IF(A16="","",IFERROR(VLOOKUP(A16, Stock_New!A:M, 3, FALSE),"")) -> ذكريا | D16: =2+1+3 -> 6 | E16: =IF($A16="", "", IFERROR(VLOOKUP($A16, Stock_New!$A:$M, 4, FALSE), "")) -> 275 | F16: =E16*D16 -> 1650 | G16: =IF($A16="", "", IFERROR(VLOOKUP($A16, Stock_New!$A:$M, 5, FALSE), "")) -> 4
A17: بوت كبير عادي | B17: =IF(A17="","",IFERROR(VLOOKUP(A17, Stock_New!A:M, 2, FALSE),"")) -> بوتات | C17: =IF(A17="","",IFERROR(VLOOKUP(A17, Stock_New!A:M, 3, FALSE),"")) -> ذكريا | D17: =2+1+1 -> 4 | E17: =IF($A17="", "", IFERROR(VLOOKUP($A17, Stock_New!$A:$M, 4, FALSE), "")) -> 135 | F17: =E17*D17 -> 540 | G17: =IF($A17="", "", IFERROR(VLOOKUP($A17, Stock_New!$A:$M, 5, FALSE), "")) -> 21
A18: شجرة موزة جلد 9 ورقة فردي 40×10 اسم | B18: =IF(A18="","",IFERROR(VLOOKUP(A18, Stock_New!A:M, 2, FALSE),"")) -> شجر | C18: =IF(A18="","",IFERROR(VLOOKUP(A18, Stock_New!A:M, 3, FALSE),"")) -> شركة الفرسان | D18: 1 | E18: =IF($A18="", "", IFERROR(VLOOKUP($A18, Stock_New!$A:$M, 4, FALSE), "")) -> 300 | F18: =E18*D18 -> 300 | G18: =IF($A18="", "", IFERROR(VLOOKUP($A18, Stock_New!$A:$M, 5, FALSE), "")) -> 0
A19: شجرة اريكا وسط | B19: =IF(A19="","",IFERROR(VLOOKUP(A19, Stock_New!A:M, 2, FALSE),"")) -> شجر | C19: =IF(A19="","",IFERROR(VLOOKUP(A19, Stock_New!A:M, 3, FALSE),"")) -> ذكريا | D19: 1 | E19: 565 | F19: =E19*D19 -> 565 | G19: =IF($A19="", "", IFERROR(VLOOKUP($A19, Stock_New!$A:$M, 5, FALSE), "")) -> 0
A20: بوت تركي كبير | B20: =IF(A20="","",IFERROR(VLOOKUP(A20, Stock_New!A:M, 2, FALSE),"")) -> بوتات | C20: =IF(A20="","",IFERROR(VLOOKUP(A20, Stock_New!A:M, 3, FALSE),"")) -> عبدالفتاح | D20: =2+5+1+17 -> 25 | E20: =IF($A20="", "", IFERROR(VLOOKUP($A20, Stock_New!$A:$M, 4, FALSE), "")) -> 65 | F20: =E20*D20 -> 1625 | G20: =IF($A20="", "", IFERROR(VLOOKUP($A20, Stock_New!$A:$M, 5, FALSE), "")) -> 13
A21: شجرة بلدي 48 | B21: =IF(A21="","",IFERROR(VLOOKUP(A21, Stock_New!A:M, 2, FALSE),"")) -> شجر | C21: =IF(A21="","",IFERROR(VLOOKUP(A21, Stock_New!A:M, 3, FALSE),"")) -> شركة حسين علي | D21: 2 | E21: =IF($A21="", "", IFERROR(VLOOKUP($A21, Stock_New!$A:$M, 4, FALSE), "")) -> 233.33 | F21: =E21*D21 -> 466.66 | G21: =IF($A21="", "", IFERROR(VLOOKUP($A21, Stock_New!$A:$M, 5, FALSE), "")) -> 2
A22: بوت وسط | B22: =IF(A22="","",IFERROR(VLOOKUP(A22, Stock_New!A:M, 2, FALSE),"")) -> بوتات | C22: =IF(A22="","",IFERROR(VLOOKUP(A22, Stock_New!A:M, 3, FALSE),"")) -> ذكريا | D22: =1+7 -> 8 | E22: 90 | F22: =E22*D22 -> 720 | G22: =IF($A22="", "", IFERROR(VLOOKUP($A22, Stock_New!$A:$M, 5, FALSE), "")) -> 17
A23: بوت طويل مستطيل فاضي | B23: =IF(A23="","",IFERROR(VLOOKUP(A23, Stock_New!A:M, 2, FALSE),"")) -> بوتات | C23: =IF(A23="","",IFERROR(VLOOKUP(A23, Stock_New!A:M, 3, FALSE),"")) -> ذكريا | D23: 3 | E23: =IF($A23="", "", IFERROR(VLOOKUP($A23, Stock_New!$A:$M, 4, FALSE), "")) -> 85 | F23: =E23*D23 -> 255 | G23: =IF($A23="", "", IFERROR(VLOOKUP($A23, Stock_New!$A:$M, 5, FALSE), "")) -> 3
A24: بوت تركي | B24: =IF(A24="","",IFERROR(VLOOKUP(A24, Stock_New!A:M, 2, FALSE),"")) -> بوتات | C24: =IF(A24="","",IFERROR(VLOOKUP(A24, Stock_New!A:M, 3, FALSE),"")) -> ذكريا | D24: =1+1+1 -> 3 | E24: =IF($A24="", "", IFERROR(VLOOKUP($A24, Stock_New!$A:$M, 4, FALSE), "")) -> 105 | F24: =E24*D24 -> 315 | G24: =IF($A24="", "", IFERROR(VLOOKUP($A24, Stock_New!$A:$M, 5, FALSE), "")) -> 2
A25: شجرة جاهزة | B25: =IF(A25="","",IFERROR(VLOOKUP(A25, Stock_New!A:M, 2, FALSE),"")) -> شجر | C25: =IF(A25="","",IFERROR(VLOOKUP(A25, Stock_New!A:M, 3, FALSE),"")) -> ذكريا | D25: =2+2+6 -> 10 | E25: =IF($A25="", "", IFERROR(VLOOKUP($A25, Stock_New!$A:$M, 4, FALSE), "")) -> 84 | F25: =E25*D25 -> 840 | G25: =IF($A25="", "", IFERROR(VLOOKUP($A25, Stock_New!$A:$M, 5, FALSE), "")) -> 16
A26: جلد تركيب 12 | B26: =IF(A26="","",IFERROR(VLOOKUP(A26, Stock_New!A:M, 2, FALSE),"")) -> شجر | C26: =IF(A26="","",IFERROR(VLOOKUP(A26, Stock_New!A:M, 3, FALSE),"")) -> شركة حسين علي | D26: 7 | E26: =IF($A26="", "", IFERROR(VLOOKUP($A26, Stock_New!$A:$M, 4, FALSE), "")) -> 85 | F26: =E26*D26 -> 595 | G26: =IF($A26="", "", IFERROR(VLOOKUP($A26, Stock_New!$A:$M, 5, FALSE), "")) -> 6
A27: شجرة تركيب 18 ورقة موزة | B27: =IF(A27="","",IFERROR(VLOOKUP(A27, Stock_New!A:M, 2, FALSE),"")) -> شجر | C27: =IF(A27="","",IFERROR(VLOOKUP(A27, Stock_New!A:M, 3, FALSE),"")) -> عبدالفتاح | D27: =1+4 -> 5 | E27: =IF($A27="", "", IFERROR(VLOOKUP($A27, Stock_New!$A:$M, 4, FALSE), "")) -> 120 | F27: =E27*D27 -> 600 | G27: =IF($A27="", "", IFERROR(VLOOKUP($A27, Stock_New!$A:$M, 5, FALSE), "")) -> 7
A28: عباد 12 فرع SF-171 | B28: =IF(A28="","",IFERROR(VLOOKUP(A28, Stock_New!A:M, 2, FALSE),"")) -> ورد لوحدة | C28: =IF(A28="","",IFERROR(VLOOKUP(A28, Stock_New!A:M, 3, FALSE),"")) -> شركة الفرسان | D28: 4 | E28: =IF($A28="", "", IFERROR(VLOOKUP($A28, Stock_New!$A:$M, 4, FALSE), "")) -> 175 | F28: =E28*D28 -> 700 | G28: =IF($A28="", "", IFERROR(VLOOKUP($A28, Stock_New!$A:$M, 5, FALSE), "")) -> 4
A29: طحالب أبيض فرسان | B29: =IF(A29="","",IFERROR(VLOOKUP(A29, Stock_New!A:M, 2, FALSE),"")) -> ورد لوحدة | C29: =IF(A29="","",IFERROR(VLOOKUP(A29, Stock_New!A:M, 3, FALSE),"")) -> شركة الفرسان | D29: =3/5+2 -> 2.6 | E29: =IF($A29="", "", IFERROR(VLOOKUP($A29, Stock_New!$A:$M, 4, FALSE), "")) -> 50 | F29: =E29*D29 -> 130 | G29: =IF($A29="", "", IFERROR(VLOOKUP($A29, Stock_New!$A:$M, 5, FALSE), "")) -> 3
A30: بلدي 12 فرسان | B30: =IF(A30="","",IFERROR(VLOOKUP(A30, Stock_New!A:M, 2, FALSE),"")) -> ورد لوحدة | C30: =IF(A30="","",IFERROR(VLOOKUP(A30, Stock_New!A:M, 3, FALSE),"")) -> شركة الفرسان | D30: =1+3+1+2/12 -> 5.1666667 | E30: =IF($A30="", "", IFERROR(VLOOKUP($A30, Stock_New!$A:$M, 4, FALSE), "")) -> 85 | F30: =E30*D30 -> 439.16667 | G30: =IF($A30="", "", IFERROR(VLOOKUP($A30, Stock_New!$A:$M, 5, FALSE), "")) -> 4.3333333
A31: افرع طويلة | B31: =IF(A31="","",IFERROR(VLOOKUP(A31, Stock_New!A:M, 2, FALSE),"")) -> ورد لوحده | C31: =IF(A31="","",IFERROR(VLOOKUP(A31, Stock_New!A:M, 3, FALSE),"")) -> ذكريا | D31: =1+5+3+14 -> 23 | E31: =IF($A31="", "", IFERROR(VLOOKUP($A31, Stock_New!$A:$M, 4, FALSE), "")) -> 75 | F31: =E31*D31 -> 1725 | G31: =IF($A31="", "", IFERROR(VLOOKUP($A31, Stock_New!$A:$M, 5, FALSE), "")) -> 29
A32: بلدي 24 | B32: =IF(A32="","",IFERROR(VLOOKUP(A32, Stock_New!A:M, 2, FALSE),"")) -> ورد لحدة | C32: =IF(A32="","",IFERROR(VLOOKUP(A32, Stock_New!A:M, 3, FALSE),"")) -> شركة حسين علي | D32: =1+5 -> 6 | E32: =IF($A32="", "", IFERROR(VLOOKUP($A32, Stock_New!$A:$M, 4, FALSE), "")) -> 175 | F32: =E32*D32 -> 1050 | G32: =IF($A32="", "", IFERROR(VLOOKUP($A32, Stock_New!$A:$M, 5, FALSE), "")) -> 6
A33: توليب 24 حسين علي | B33: =IF(A33="","",IFERROR(VLOOKUP(A33, Stock_New!A:M, 2, FALSE),"")) -> ورد لحدة | C33: =IF(A33="","",IFERROR(VLOOKUP(A33, Stock_New!A:M, 3, FALSE),"")) -> شركة حسين علي | D33: 2 | E33: =IF($A33="", "", IFERROR(VLOOKUP($A33, Stock_New!$A:$M, 4, FALSE), "")) -> 150 | F33: =E33*D33 -> 300 | G33: =IF($A33="", "", IFERROR(VLOOKUP($A33, Stock_New!$A:$M, 5, FALSE), "")) -> 7
A34: ريشة دوناتس | B34: =IF(A34="","",IFERROR(VLOOKUP(A34, Stock_New!A:M, 2, FALSE),"")) -> ريش | C34: =IF(A34="","",IFERROR(VLOOKUP(A34, Stock_New!A:M, 3, FALSE),"")) -> شركة حسين علي | D34: =6+1+1+30+9+2 -> 49 | E34: =IF($A34="", "", IFERROR(VLOOKUP($A34, Stock_New!$A:$M, 4, FALSE), "")) -> 15 | F34: =E34*D34 -> 735 | G34: =IF($A34="", "", IFERROR(VLOOKUP($A34, Stock_New!$A:$M, 5, FALSE), "")) -> 52
A35: بوكيه ورد نوعين | B35: =IF(A35="","",IFERROR(VLOOKUP(A35, Stock_New!A:M, 2, FALSE),"")) -> ورد لوحده | C35: =IF(A35="","",IFERROR(VLOOKUP(A35, Stock_New!A:M, 3, FALSE),"")) -> ذكريا | D35: 1 | E35: =IF($A35="", "", IFERROR(VLOOKUP($A35, Stock_New!$A:$M, 4, FALSE), "")) -> 145 | F35: =E35*D35 -> 145 | G35: =IF($A35="", "", IFERROR(VLOOKUP($A35, Stock_New!$A:$M, 5, FALSE), "")) -> 0
A36: بوكيه ابيض | B36: =IF(A36="","",IFERROR(VLOOKUP(A36, Stock_New!A:M, 2, FALSE),"")) -> ورد لوحده | C36: =IF(A36="","",IFERROR(VLOOKUP(A36, Stock_New!A:M, 3, FALSE),"")) -> ذكريا | D36: 1 | E36: =IF($A36="", "", IFERROR(VLOOKUP($A36, Stock_New!$A:$M, 4, FALSE), "")) -> 145 | F36: =E36*D36 -> 145 | G36: =IF($A36="", "", IFERROR(VLOOKUP($A36, Stock_New!$A:$M, 5, FALSE), "")) -> 0
A37: بوكيه بلاسيتك وورد مسك الليل | B37: =IF(A37="","",IFERROR(VLOOKUP(A37, Stock_New!A:M, 2, FALSE),"")) -> بوكيه | C37: =IF(A37="","",IFERROR(VLOOKUP(A37, Stock_New!A:M, 3, FALSE),"")) -> ذكريا | D37: 1 | E37: =IF($A37="", "", IFERROR(VLOOKUP($A37, Stock_New!$A:$M, 4, FALSE), "")) -> 112.5 | F37: =E37*D37 -> 112.5 | G37: =IF($A37="", "", IFERROR(VLOOKUP($A37, Stock_New!$A:$M, 5, FALSE), "")) -> 1
A38: بوكيه بلاستيك ورد مقفول وورد صغير | B38: =IF(A38="","",IFERROR(VLOOKUP(A38, Stock_New!A:M, 2, FALSE),"")) -> بوكيه | C38: =IF(A38="","",IFERROR(VLOOKUP(A38, Stock_New!A:M, 3, FALSE),"")) -> ذكريا | D38: 2 | E38: =IF($A38="", "", IFERROR(VLOOKUP($A38, Stock_New!$A:$M, 4, FALSE), "")) -> 160 | F38: =E38*D38 -> 320 | G38: =IF($A38="", "", IFERROR(VLOOKUP($A38, Stock_New!$A:$M, 5, FALSE), "")) -> 0
A39: بوكيه ريش حمام | B39: =IF(A39="","",IFERROR(VLOOKUP(A39, Stock_New!A:M, 2, FALSE),"")) -> بوكيه | C39: =IF(A39="","",IFERROR(VLOOKUP(A39, Stock_New!A:M, 3, FALSE),"")) -> ذكريا | D39: 1 | E39: =IF($A39="", "", IFERROR(VLOOKUP($A39, Stock_New!$A:$M, 4, FALSE), "")) -> 135 | F39: =E39*D39 -> 135 | G39: =IF($A39="", "", IFERROR(VLOOKUP($A39, Stock_New!$A:$M, 5, FALSE), "")) -> 2
A40: بوكيه بلاستيك وبوكيه اخضر | B40: =IF(A40="","",IFERROR(VLOOKUP(A40, Stock_New!A:M, 2, FALSE),"")) -> بوكيه | C40: =IF(A40="","",IFERROR(VLOOKUP(A40, Stock_New!A:M, 3, FALSE),"")) -> ذكريا | D40: 2 | E40: =IF($A40="", "", IFERROR(VLOOKUP($A40, Stock_New!$A:$M, 4, FALSE), "")) -> 140 | F40: =E40*D40 -> 280 | G40: =IF($A40="", "", IFERROR(VLOOKUP($A40, Stock_New!$A:$M, 5, FALSE), "")) -> 2
A41: بوكيه قرنفل وبلدي | B41: =IF(A41="","",IFERROR(VLOOKUP(A41, Stock_New!A:M, 2, FALSE),"")) -> بوكيه | C41: =IF(A41="","",IFERROR(VLOOKUP(A41, Stock_New!A:M, 3, FALSE),"")) -> manufactured | D41: 1 | E41: 90 | F41: =E41*D41 -> 90 | G41: =IF($A41="", "", IFERROR(VLOOKUP($A41, Stock_New!$A:$M, 5, FALSE), "")) -> 1
A42: بوكيه بق السيبع جلد | B42: =IF(A42="","",IFERROR(VLOOKUP(A42, Stock_New!A:M, 2, FALSE),"")) -> ورد لوحده | C42: =IF(A42="","",IFERROR(VLOOKUP(A42, Stock_New!A:M, 3, FALSE),"")) -> ذكريا | D42: =1+2+1 -> 4 | E42: =IF($A42="", "", IFERROR(VLOOKUP($A42, Stock_New!$A:$M, 4, FALSE), "")) -> 175 | F42: =E42*D42 -> 700 | G42: =IF($A42="", "", IFERROR(VLOOKUP($A42, Stock_New!$A:$M, 5, FALSE), "")) -> 3
A43: ورد زهور صغير | B43: =IF(A43="","",IFERROR(VLOOKUP(A43, Stock_New!A:M, 2, FALSE),"")) -> ورد لوحده | C43: =IF(A43="","",IFERROR(VLOOKUP(A43, Stock_New!A:M, 3, FALSE),"")) -> ذكريا | D43: =1+1+2+3+1 -> 8 | E43: =IF($A43="", "", IFERROR(VLOOKUP($A43, Stock_New!$A:$M, 4, FALSE), "")) -> 30 | F43: =E43*D43 -> 240 | G43: =IF($A43="", "", IFERROR(VLOOKUP($A43, Stock_New!$A:$M, 5, FALSE), "")) -> 0.5
A44: 12 اواس علاء شاكر | B44: =IF(A44="","",IFERROR(VLOOKUP(A44, Stock_New!A:M, 2, FALSE),"")) -> ورد لوحدة | C44: =IF(A44="","",IFERROR(VLOOKUP(A44, Stock_New!A:M, 3, FALSE),"")) -> شركة علاء شاكر | D44: =1+6+1 -> 8 | E44: =IF($A44="", "", IFERROR(VLOOKUP($A44, Stock_New!$A:$M, 4, FALSE), "")) -> 70 | F44: =E44*D44 -> 560 | G44: =IF($A44="", "", IFERROR(VLOOKUP($A44, Stock_New!$A:$M, 5, FALSE), "")) -> 8
A45: بوت صغير فاضي | B45: =IF(A45="","",IFERROR(VLOOKUP(A45, Stock_New!A:M, 2, FALSE),"")) -> بوتات | C45: =IF(A45="","",IFERROR(VLOOKUP(A45, Stock_New!A:M, 3, FALSE),"")) -> شركة حسين علي | D45: =5+9+1+9+1+2+14+8 -> 49 | E45: =IF($A45="", "", IFERROR(VLOOKUP($A45, Stock_New!$A:$M, 4, FALSE), "")) -> 20 | F45: =E45*D45 -> 980 | G45: =IF($A45="", "", IFERROR(VLOOKUP($A45, Stock_New!$A:$M, 5, FALSE), "")) -> 9
A46: مقزمات | B46: بوكيه | C46: manufacture | D46: =36+12+9+15 -> 72 | E46: 10 | F46: =E46*D46 -> 720 | G46: =IF($A46="", "", IFERROR(VLOOKUP($A46, Stock_New!$A:$M, 5, FALSE), ""))
A47: مزرعة | B47: =IF(A47="","",IFERROR(VLOOKUP(A47, Stock_New!A:M, 2, FALSE),"")) -> بوكيه | C47: =IF(A47="","",IFERROR(VLOOKUP(A47, Stock_New!A:M, 3, FALSE),"")) -> ذكريا | D47: 24 | E47: =IF($A47="", "", IFERROR(VLOOKUP($A47, Stock_New!$A:$M, 4, FALSE), "")) -> 37 | F47: =E47*D47 -> 888 | G47: =IF($A47="", "", IFERROR(VLOOKUP($A47, Stock_New!$A:$M, 5, FALSE), "")) -> 10
A48: مزرعة كثيفة | B48: =IF(A48="","",IFERROR(VLOOKUP(A48, Stock_New!A:M, 2, FALSE),"")) -> بوكيه | C48: =IF(A48="","",IFERROR(VLOOKUP(A48, Stock_New!A:M, 3, FALSE),"")) -> manufactured | D48: 10 | E48: =21.5 -> 21.5 | F48: =E48*D48 -> 215 | G48: =IF($A48="", "", IFERROR(VLOOKUP($A48, Stock_New!$A:$M, 5, FALSE), "")) -> 5
A49: بوت بشريطة دهبي حسين علي | B49: =IF(A49="","",IFERROR(VLOOKUP(A49, Stock_New!A:M, 2, FALSE),"")) -> بوتات | C49: =IF(A49="","",IFERROR(VLOOKUP(A49, Stock_New!A:M, 3, FALSE),"")) -> شركة حسين علي | D49: =2+1+3+5 -> 11 | E49: =IF($A49="", "", IFERROR(VLOOKUP($A49, Stock_New!$A:$M, 4, FALSE), "")) -> 100 | F49: =E49*D49 -> 1100 | G49: =IF($A49="", "", IFERROR(VLOOKUP($A49, Stock_New!$A:$M, 5, FALSE), "")) -> 11
A50: جلد 54 تركيب احمر | B50: شجر | C50: شركة حسين علي | D50: =1+2 -> 3 | E50: 220 | F50: =E50*D50 -> 660 | G50: =IF($A50="", "", IFERROR(VLOOKUP($A50, Stock_New!$A:$M, 5, FALSE), ""))
A51: شجرة بنجامين 80سم وكرز | B51: شجر | C51: manufactured | D51: 1 | E51: =65+75+10 -> 150 | F51: =E51*D51 -> 150 | G51: =IF($A51="", "", IFERROR(VLOOKUP($A51, Stock_New!$A:$M, 5, FALSE), ""))
A52: بروبلين 14 سم | B52: =IF(A52="","",IFERROR(VLOOKUP(A52, Stock_New!A:M, 2, FALSE),"")) -> بوتات | C52: =IF(A52="","",IFERROR(VLOOKUP(A52, Stock_New!A:M, 3, FALSE),"")) -> شركة الفرسان | D52: =1+5+2 -> 8 | E52: =IF($A52="", "", IFERROR(VLOOKUP($A52, Stock_New!$A:$M, 4, FALSE), "")) -> 20 | F52: =E52*D52 -> 160 | G52: =IF($A52="", "", IFERROR(VLOOKUP($A52, Stock_New!$A:$M, 5, FALSE), "")) -> 9
A53: ياسمين جيرمينجامبو | B53: =IF(A53="","",IFERROR(VLOOKUP(A53, Stock_New!A:M, 2, FALSE),"")) -> ورد لوحدة | C53: =IF(A53="","",IFERROR(VLOOKUP(A53, Stock_New!A:M, 3, FALSE),"")) -> شركة الفرسان | D53: 7 | E53: =IF($A53="", "", IFERROR(VLOOKUP($A53, Stock_New!$A:$M, 4, FALSE), "")) -> 85 | F53: =E53*D53 -> 595 | G53: =IF($A53="", "", IFERROR(VLOOKUP($A53, Stock_New!$A:$M, 5, FALSE), "")) -> 5
A54: خضرة اللوان 18 | B54: =IF(A54="","",IFERROR(VLOOKUP(A54, Stock_New!A:M, 2, FALSE),"")) -> ورد لوحدة | C54: =IF(A54="","",IFERROR(VLOOKUP(A54, Stock_New!A:M, 3, FALSE),"")) -> شركة الفرسان | D54: =6/18+6+7+2 -> 15.333333 | E54: =IF($A54="", "", IFERROR(VLOOKUP($A54, Stock_New!$A:$M, 4, FALSE), "")) -> 110 | F54: =E54*D54 -> 1686.6667 | G54: =IF($A54="", "", IFERROR(VLOOKUP($A54, Stock_New!$A:$M, 5, FALSE), "")) -> 1.4444444
A55: فازة زجاج كبيرة | B55: فازة | C55: ذكريا | D55: 1 | E55: 350 | F55: =E55*D55 -> 350 | G55: =IF($A55="", "", IFERROR(VLOOKUP($A55, Stock_New!$A:$M, 5, FALSE), ""))
A56: فازة ازاز وبوكيه | B56: =IF(A56="","",IFERROR(VLOOKUP(A56, Stock_New!A:M, 2, FALSE),"")) -> بوكيه | C56: =IF(A56="","",IFERROR(VLOOKUP(A56, Stock_New!A:M, 3, FALSE),"")) -> ذكريا | D56: 1 | E56: =IF($A56="", "", IFERROR(VLOOKUP($A56, Stock_New!$A:$M, 4, FALSE), "")) -> 180 | F56: =E56*D56 -> 180 | G56: =IF($A56="", "", IFERROR(VLOOKUP($A56, Stock_New!$A:$M, 5, FALSE), "")) -> 0
A57: فازة زجاج 629/21 | B57: =IF(A57="","",IFERROR(VLOOKUP(A57, Stock_New!A:M, 2, FALSE),"")) -> فازة زجاج | C57: =IF(A57="","",IFERROR(VLOOKUP(A57, Stock_New!A:M, 3, FALSE),"")) -> سنتر محمد رشدي | D57: 2 | E57: =IF($A57="", "", IFERROR(VLOOKUP($A57, Stock_New!$A:$M, 4, FALSE), "")) -> 139 | F57: =E57*D57 -> 278 | G57: =IF($A57="", "", IFERROR(VLOOKUP($A57, Stock_New!$A:$M, 5, FALSE), "")) -> 2
A58: عباد 12 فرع SF-171 | B58: =IF(A58="","",IFERROR(VLOOKUP(A58, Stock_New!A:M, 2, FALSE),"")) -> ورد لوحدة | C58: =IF(A58="","",IFERROR(VLOOKUP(A58, Stock_New!A:M, 3, FALSE),"")) -> شركة الفرسان | D58: 1 | E58: =IF($A58="", "", IFERROR(VLOOKUP($A58, Stock_New!$A:$M, 4, FALSE), "")) -> 175 | F58: =E58*D58 -> 175 | G58: =IF($A58="", "", IFERROR(VLOOKUP($A58, Stock_New!$A:$M, 5, FALSE), "")) -> 4
A59: بوكيه كريستال شفاف وبوكيه اخضر | B59: =IF(A59="","",IFERROR(VLOOKUP(A59, Stock_New!A:M, 2, FALSE),"")) -> بوكيه | C59: =IF(A59="","",IFERROR(VLOOKUP(A59, Stock_New!A:M, 3, FALSE),"")) -> ذكريا | D59: 1 | E59: =IF($A59="", "", IFERROR(VLOOKUP($A59, Stock_New!$A:$M, 4, FALSE), "")) -> 420 | F59: =E59*D59 -> 420 | G59: =IF($A59="", "", IFERROR(VLOOKUP($A59, Stock_New!$A:$M, 5, FALSE), "")) -> 1
A60: ريش بورد | B60: =IF(A60="","",IFERROR(VLOOKUP(A60, Stock_New!A:M, 2, FALSE),"")) -> ورد لوحده | C60: =IF(A60="","",IFERROR(VLOOKUP(A60, Stock_New!A:M, 3, FALSE),"")) -> ذكريا | D60: 3 | E60: =IF($A60="", "", IFERROR(VLOOKUP($A60, Stock_New!$A:$M, 4, FALSE), "")) -> 85 | F60: =E60*D60 -> 255 | G60: =IF($A60="", "", IFERROR(VLOOKUP($A60, Stock_New!$A:$M, 5, FALSE), "")) -> 3
A61: خضرة حشو 12 | B61: =IF(A61="","",IFERROR(VLOOKUP(A61, Stock_New!A:M, 2, FALSE),"")) -> ورد لوحدة | C61: =IF(A61="","",IFERROR(VLOOKUP(A61, Stock_New!A:M, 3, FALSE),"")) -> شركة حسين علي | D61: =1+6 -> 7 | E61: =IF($A61="", "", IFERROR(VLOOKUP($A61, Stock_New!$A:$M, 4, FALSE), "")) -> 50 | F61: =E61*D61 -> 350 | G61: =IF($A61="", "", IFERROR(VLOOKUP($A61, Stock_New!$A:$M, 5, FALSE), "")) -> 9.5833333
A62: شجرة موز صغيرة درجة عالية | B62: =IF(A62="","",IFERROR(VLOOKUP(A62, Stock_New!A:M, 2, FALSE),"")) -> شجر | C62: =IF(A62="","",IFERROR(VLOOKUP(A62, Stock_New!A:M, 3, FALSE),"")) -> ذكريا | D62: 1 | E62: =IF($A62="", "", IFERROR(VLOOKUP($A62, Stock_New!$A:$M, 4, FALSE), "")) -> 375 | F62: =E62*D62 -> 375 | G62: =IF($A62="", "", IFERROR(VLOOKUP($A62, Stock_New!$A:$M, 5, FALSE), "")) -> 1
A63: بوكيه دوار شمس | B63: =IF(A63="","",IFERROR(VLOOKUP(A63, Stock_New!A:M, 2, FALSE),"")) -> ورد لوحده | C63: =IF(A63="","",IFERROR(VLOOKUP(A63, Stock_New!A:M, 3, FALSE),"")) -> ذكريا | D63: 1 | E63: =IF($A63="", "", IFERROR(VLOOKUP($A63, Stock_New!$A:$M, 4, FALSE), "")) -> 105 | F63: =E63*D63 -> 105 | G63: =IF($A63="", "", IFERROR(VLOOKUP($A63, Stock_New!$A:$M, 5, FALSE), "")) -> 1
A64: فازة بورسلين | B64: =IF(A64="","",IFERROR(VLOOKUP(A64, Stock_New!A:M, 2, FALSE),"")) -> سيلفرات | C64: =IF(A64="","",IFERROR(VLOOKUP(A64, Stock_New!A:M, 3, FALSE),"")) -> ذكريا | D64: 2 | E64: =IF($A64="", "", IFERROR(VLOOKUP($A64, Stock_New!$A:$M, 4, FALSE), "")) -> 195 | F64: =E64*D64 -> 390 | G64: =IF($A64="", "", IFERROR(VLOOKUP($A64, Stock_New!$A:$M, 5, FALSE), "")) -> 1
A65: بوكيه وورد مجفف | B65: =IF(A65="","",IFERROR(VLOOKUP(A65, Stock_New!A:M, 2, FALSE),"")) -> ورد لوحده | C65: =IF(A65="","",IFERROR(VLOOKUP(A65, Stock_New!A:M, 3, FALSE),"")) -> ذكريا | D65: 1 | E65: =IF($A65="", "", IFERROR(VLOOKUP($A65, Stock_New!$A:$M, 4, FALSE), "")) -> 185 | F65: =E65*D65 -> 185 | G65: =IF($A65="", "", IFERROR(VLOOKUP($A65, Stock_New!$A:$M, 5, FALSE), "")) -> 1
A66: بوكيه ورد صغير 5 فرع | B66: ورد لوحده | C66: ذكريا | D66: 1 | E66: 55 | F66: =E66*D66 -> 55 | G66: =IF($A66="", "", IFERROR(VLOOKUP($A66, Stock_New!$A:$M, 5, FALSE), ""))
A67: فازة ازاز وبوكيه | B67: فازة | C67: =IF(A67="","",IFERROR(VLOOKUP(A67, Stock_New!A:M, 3, FALSE),"")) -> ذكريا | D67: 2 | E67: 70 | F67: =E67*D67 -> 140 | G67: =IF($A67="", "", IFERROR(VLOOKUP($A67, Stock_New!$A:$M, 5, FALSE), "")) -> 0
A68: ورد لوزة نفخ | B68: =IF(A68="","",IFERROR(VLOOKUP(A68, Stock_New!A:M, 2, FALSE),"")) -> ورد لوحدة | C68: =IF(A68="","",IFERROR(VLOOKUP(A68, Stock_New!A:M, 3, FALSE),"")) -> شركة حسين علي | D68: =1+1+3+1+6/10 -> 6.6 | E68: =IF($A68="", "", IFERROR(VLOOKUP($A68, Stock_New!$A:$M, 4, FALSE), "")) -> 135 | F68: =E68*D68 -> 891 | G68: =IF($A68="", "", IFERROR(VLOOKUP($A68, Stock_New!$A:$M, 5, FALSE), "")) -> 6
A69: سحبة قرنفل ونجمة | B69: =IF(A69="","",IFERROR(VLOOKUP(A69, Stock_New!A:M, 2, FALSE),"")) -> ورد لوحدة | C69: =IF(A69="","",IFERROR(VLOOKUP(A69, Stock_New!A:M, 3, FALSE),"")) -> شركة حسين علي | D69: =1+4+1 -> 6 | E69: =IF($A69="", "", IFERROR(VLOOKUP($A69, Stock_New!$A:$M, 4, FALSE), "")) -> 135 | F69: =E69*D69 -> 810 | G69: =IF($A69="", "", IFERROR(VLOOKUP($A69, Stock_New!$A:$M, 5, FALSE), "")) -> 6
A70: فازة زجاج 219/4 | B70: =IF(A70="","",IFERROR(VLOOKUP(A70, Stock_New!A:M, 2, FALSE),"")) -> كريستال | C70: =IF(A70="","",IFERROR(VLOOKUP(A70, Stock_New!A:M, 3, FALSE),"")) -> محمد رشدي | D70: 2 | E70: =IF($A70="", "", IFERROR(VLOOKUP($A70, Stock_New!$A:$M, 4, FALSE), "")) -> 58 | F70: =E70*D70 -> 116 | G70: =IF($A70="", "", IFERROR(VLOOKUP($A70, Stock_New!$A:$M, 5, FALSE), "")) -> 2
A71: فازة زجاج 219/2 | B71: =IF(A71="","",IFERROR(VLOOKUP(A71, Stock_New!A:M, 2, FALSE),"")) -> كريستال | C71: =IF(A71="","",IFERROR(VLOOKUP(A71, Stock_New!A:M, 3, FALSE),"")) -> محمد رشدي | D71: 2 | E71: =IF($A71="", "", IFERROR(VLOOKUP($A71, Stock_New!$A:$M, 4, FALSE), "")) -> 75 | F71: =E71*D71 -> 150 | G71: =IF($A71="", "", IFERROR(VLOOKUP($A71, Stock_New!$A:$M, 5, FALSE), "")) -> 2
A72: فازة خزف متوسطة | B72: =IF(A72="","",IFERROR(VLOOKUP(A72, Stock_New!A:M, 2, FALSE),"")) -> خزف | C72: =IF(A72="","",IFERROR(VLOOKUP(A72, Stock_New!A:M, 3, FALSE),"")) -> ذكريا | D72: =2+2 -> 4 | E72: =IF($A72="", "", IFERROR(VLOOKUP($A72, Stock_New!$A:$M, 4, FALSE), "")) -> 75 | F72: =E72*D72 -> 300 | G72: =IF($A72="", "", IFERROR(VLOOKUP($A72, Stock_New!$A:$M, 5, FALSE), "")) -> 2
A73: فازة خزف غالية | B73: =IF(A73="","",IFERROR(VLOOKUP(A73, Stock_New!A:M, 2, FALSE),"")) -> خزف | C73: =IF(A73="","",IFERROR(VLOOKUP(A73, Stock_New!A:M, 3, FALSE),"")) -> ذكريا | D73: 1 | E73: =IF($A73="", "", IFERROR(VLOOKUP($A73, Stock_New!$A:$M, 4, FALSE), "")) -> 95 | F73: =E73*D73 -> 95 | G73: =IF($A73="", "", IFERROR(VLOOKUP($A73, Stock_New!$A:$M, 5, FALSE), "")) -> 1
A74: بوكيه ازاز صغير | B74: =IF(A74="","",IFERROR(VLOOKUP(A74, Stock_New!A:M, 2, FALSE),"")) -> بوكيه | C74: =IF(A74="","",IFERROR(VLOOKUP(A74, Stock_New!A:M, 3, FALSE),"")) -> ذكريا | D74: 1 | E74: =IF($A74="", "", IFERROR(VLOOKUP($A74, Stock_New!$A:$M, 4, FALSE), "")) -> 155 | F74: =E74*D74 -> 155 | G74: =IF($A74="", "", IFERROR(VLOOKUP($A74, Stock_New!$A:$M, 5, FALSE), "")) -> 1
A75: طقم زجاج ابيض وبوكيه اخضر | B75: =IF(A75="","",IFERROR(VLOOKUP(A75, Stock_New!A:M, 2, FALSE),"")) -> بوكيه | C75: =IF(A75="","",IFERROR(VLOOKUP(A75, Stock_New!A:M, 3, FALSE),"")) -> ذكريا | D75: 1 | E75: =IF($A75="", "", IFERROR(VLOOKUP($A75, Stock_New!$A:$M, 4, FALSE), "")) -> 325 | F75: =E75*D75 -> 325 | G75: =IF($A75="", "", IFERROR(VLOOKUP($A75, Stock_New!$A:$M, 5, FALSE), "")) -> 1
A76: طقم زجاج ابيض فاضي | B76: =IF(A76="","",IFERROR(VLOOKUP(A76, Stock_New!A:M, 2, FALSE),"")) -> زجاج ابيض | C76: =IF(A76="","",IFERROR(VLOOKUP(A76, Stock_New!A:M, 3, FALSE),"")) -> ذكريا | D76: 3 | E76: =IF($A76="", "", IFERROR(VLOOKUP($A76, Stock_New!$A:$M, 4, FALSE), "")) -> 125 | F76: =E76*D76 -> 375 | G76: =IF($A76="", "", IFERROR(VLOOKUP($A76, Stock_New!$A:$M, 5, FALSE), "")) -> 1
A77: بوكيه مشمش الفرسان | B77: =IF(A77="","",IFERROR(VLOOKUP(A77, Stock_New!A:M, 2, FALSE),"")) -> ورد لوحدة | C77: =IF(A77="","",IFERROR(VLOOKUP(A77, Stock_New!A:M, 3, FALSE),"")) -> شركة الفرسان | D77: =2+12 -> 14 | E77: =IF($A77="", "", IFERROR(VLOOKUP($A77, Stock_New!$A:$M, 4, FALSE), "")) -> 45 | F77: =E77*D77 -> 630 | G77: =IF($A77="", "", IFERROR(VLOOKUP($A77, Stock_New!$A:$M, 5, FALSE), "")) -> 18
A78: قطعة دوناتس | B78: =IF(A78="","",IFERROR(VLOOKUP(A78, Stock_New!A:M, 2, FALSE),"")) -> خزف | C78: =IF(A78="","",IFERROR(VLOOKUP(A78, Stock_New!A:M, 3, FALSE),"")) -> ذكريا | D78: 1 | E78: =IF($A78="", "", IFERROR(VLOOKUP($A78, Stock_New!$A:$M, 4, FALSE), "")) -> 45 | F78: =E78*D78 -> 45 | G78: =IF($A78="", "", IFERROR(VLOOKUP($A78, Stock_New!$A:$M, 5, FALSE), "")) -> 1
A79: مزرعة شلال | B79: =IF(A79="","",IFERROR(VLOOKUP(A79, Stock_New!A:M, 2, FALSE),"")) -> بوكيه | C79: =IF(A79="","",IFERROR(VLOOKUP(A79, Stock_New!A:M, 3, FALSE),"")) -> ذكريا | D79: =1+23 -> 24 | E79: =IF($A79="", "", IFERROR(VLOOKUP($A79, Stock_New!$A:$M, 4, FALSE), "")) -> 45 | F79: =E79*D79 -> 1080 | G79: =IF($A79="", "", IFERROR(VLOOKUP($A79, Stock_New!$A:$M, 5, FALSE), "")) -> 25
A80: فازة خزف ريش | B80: =IF(A80="","",IFERROR(VLOOKUP(A80, Stock_New!A:M, 2, FALSE),"")) -> بوكيه | C80: =IF(A80="","",IFERROR(VLOOKUP(A80, Stock_New!A:M, 3, FALSE),"")) -> ذكريا | D80: 1 | E80: =IF($A80="", "", IFERROR(VLOOKUP($A80, Stock_New!$A:$M, 4, FALSE), "")) -> 175 | F80: =E80*D80 -> 175 | G80: =IF($A80="", "", IFERROR(VLOOKUP($A80, Stock_New!$A:$M, 5, FALSE), "")) -> 0
A81: فازة خزف ورد روز وبوكيه صغير | B81: =IF(A81="","",IFERROR(VLOOKUP(A81, Stock_New!A:M, 2, FALSE),"")) -> بوكيه | C81: =IF(A81="","",IFERROR(VLOOKUP(A81, Stock_New!A:M, 3, FALSE),"")) -> ذكريا | D81: 1 | E81: =IF($A81="", "", IFERROR(VLOOKUP($A81, Stock_New!$A:$M, 4, FALSE), "")) -> 192.5 | F81: =E81*D81 -> 192.5 | G81: =IF($A81="", "", IFERROR(VLOOKUP($A81, Stock_New!$A:$M, 5, FALSE), "")) -> 2
A82: لليام 9 فرع | B82: =IF(A82="","",IFERROR(VLOOKUP(A82, Stock_New!A:M, 2, FALSE),"")) -> ورد لوحدة | C82: =IF(A82="","",IFERROR(VLOOKUP(A82, Stock_New!A:M, 3, FALSE),"")) -> شركة الفرسان | D82: =1+1+10+1+2+1+1+7/9 -> 17.777778 | E82: =IF($A82="", "", IFERROR(VLOOKUP($A82, Stock_New!$A:$M, 4, FALSE), "")) -> 125 | F82: =E82*D82 -> 2222.2222 | G82: =IF($A82="", "", IFERROR(VLOOKUP($A82, Stock_New!$A:$M, 5, FALSE), "")) -> 6.7777778
A83: بوكيه فرع اخضر جديد | B83: =IF(A83="","",IFERROR(VLOOKUP(A83, Stock_New!A:M, 2, FALSE),"")) -> ورد لوحده | C83: =IF(A83="","",IFERROR(VLOOKUP(A83, Stock_New!A:M, 3, FALSE),"")) -> ذكريا | D83: =1+2+5 -> 8 | E83: =IF($A83="", "", IFERROR(VLOOKUP($A83, Stock_New!$A:$M, 4, FALSE), "")) -> 95 | F83: =E83*D83 -> 760 | G83: =IF($A83="", "", IFERROR(VLOOKUP($A83, Stock_New!$A:$M, 5, FALSE), "")) -> 10.5
A84: دستة مانجوليا | B84: =IF(A84="","",IFERROR(VLOOKUP(A84, Stock_New!A:M, 2, FALSE),"")) -> ورق شجر | C84: =IF(A84="","",IFERROR(VLOOKUP(A84, Stock_New!A:M, 3, FALSE),"")) -> عبدالفتاح | D84: =3/12 -> 0.25 | E84: =IF($A84="", "", IFERROR(VLOOKUP($A84, Stock_New!$A:$M, 4, FALSE), "")) -> 220 | F84: =E84*D84 -> 55 | G84: =IF($A84="", "", IFERROR(VLOOKUP($A84, Stock_New!$A:$M, 5, FALSE), "")) -> 0
A85: مقزم وردة قطيفة | B85: =IF(A85="","",IFERROR(VLOOKUP(A85, Stock_New!A:M, 2, FALSE),"")) -> بوكيه | C85: =IF(A85="","",IFERROR(VLOOKUP(A85, Stock_New!A:M, 3, FALSE),"")) -> manufactured | D85: 2 | E85: =IF($A85="", "", IFERROR(VLOOKUP($A85, Stock_New!$A:$M, 4, FALSE), "")) -> 32.707143 | F85: =E85*D85 -> 65.414286 | G85: =IF($A85="", "", IFERROR(VLOOKUP($A85, Stock_New!$A:$M, 5, FALSE), "")) -> 3
A86: مقزم اربع وردات قطيفة | B86: =IF(A86="","",IFERROR(VLOOKUP(A86, Stock_New!A:M, 2, FALSE),"")) -> بوكيه | C86: =IF(A86="","",IFERROR(VLOOKUP(A86, Stock_New!A:M, 3, FALSE),"")) -> manufactured | D86: 1 | E86: =IF($A86="", "", IFERROR(VLOOKUP($A86, Stock_New!$A:$M, 4, FALSE), "")) -> 56.666667 | F86: =E86*D86 -> 56.666667 | G86: =IF($A86="", "", IFERROR(VLOOKUP($A86, Stock_New!$A:$M, 5, FALSE), "")) -> 0
A87: مقزم تلات فروع قرنفل جيبسفيل | B87: بوكيه | C87: manufacrured | D87: 1 | E87: 40 | F87: =E87*D87 -> 40 | G87: =IF($A87="", "", IFERROR(VLOOKUP($A87, Stock_New!$A:$M, 5, FALSE), ""))
A88: مقزم هيدروجين | B88: بوكيه | C88: manufacrured | D88: 1 | E88: 40 | F88: =E88*D88 -> 40 | G88: =IF($A88="", "", IFERROR(VLOOKUP($A88, Stock_New!$A:$M, 5, FALSE), ""))
A89: فازة فخار مطبق حجارة صغيرة | B89: =IF(A89="","",IFERROR(VLOOKUP(A89, Stock_New!A:M, 2, FALSE),"")) -> فازة | C89: =IF(A89="","",IFERROR(VLOOKUP(A89, Stock_New!A:M, 3, FALSE),"")) -> شركة الفرسان | D89: =1+1 -> 2 | E89: =IF($A89="", "", IFERROR(VLOOKUP($A89, Stock_New!$A:$M, 4, FALSE), "")) -> 175 | F89: =E89*D89 -> 350 | G89: =IF($A89="", "", IFERROR(VLOOKUP($A89, Stock_New!$A:$M, 5, FALSE), "")) -> 1
A90: فازة فخار مطبق حجارة كبيرة | B90: =IF(A90="","",IFERROR(VLOOKUP(A90, Stock_New!A:M, 2, FALSE),"")) -> فازة | C90: =IF(A90="","",IFERROR(VLOOKUP(A90, Stock_New!A:M, 3, FALSE),"")) -> شركة الفرسان | D90: =1+1 -> 2 | E90: =IF($A90="", "", IFERROR(VLOOKUP($A90, Stock_New!$A:$M, 4, FALSE), "")) -> 225 | F90: =E90*D90 -> 450 | G90: =IF($A90="", "", IFERROR(VLOOKUP($A90, Stock_New!$A:$M, 5, FALSE), "")) -> 1
A91: فازة بورسلين كبيرة ابيض مذهب | B91: =IF(A91="","",IFERROR(VLOOKUP(A91, Stock_New!A:M, 2, FALSE),"")) -> بورسلين | C91: =IF(A91="","",IFERROR(VLOOKUP(A91, Stock_New!A:M, 3, FALSE),"")) -> شركة حسين علي | D91: 2 | E91: =IF($A91="", "", IFERROR(VLOOKUP($A91, Stock_New!$A:$M, 4, FALSE), "")) -> 400 | F91: =E91*D91 -> 800 | G91: =IF($A91="", "", IFERROR(VLOOKUP($A91, Stock_New!$A:$M, 5, FALSE), "")) -> 3
A92: فازة بورسلين وسط ابيض مذهب | B92: =IF(A92="","",IFERROR(VLOOKUP(A92, Stock_New!A:M, 2, FALSE),"")) -> بورسلين | C92: =IF(A92="","",IFERROR(VLOOKUP(A92, Stock_New!A:M, 3, FALSE),"")) -> شركة حسين علي | D92: 2 | E92: =IF($A92="", "", IFERROR(VLOOKUP($A92, Stock_New!$A:$M, 4, FALSE), "")) -> 300 | F92: =E92*D92 -> 600 | G92: =IF($A92="", "", IFERROR(VLOOKUP($A92, Stock_New!$A:$M, 5, FALSE), "")) -> 2
A93: فازة بورسلين صغيرابيض مذهب | B93: =IF(A93="","",IFERROR(VLOOKUP(A93, Stock_New!A:M, 2, FALSE),"")) -> بورسلين | C93: =IF(A93="","",IFERROR(VLOOKUP(A93, Stock_New!A:M, 3, FALSE),"")) -> شركة حسين علي | D93: 2 | E93: =IF($A93="", "", IFERROR(VLOOKUP($A93, Stock_New!$A:$M, 4, FALSE), "")) -> 250 | F93: =E93*D93 -> 500 | G93: =IF($A93="", "", IFERROR(VLOOKUP($A93, Stock_New!$A:$M, 5, FALSE), "")) -> 2
A94: فازة بورسلين برجول صغير | B94: =IF(A94="","",IFERROR(VLOOKUP(A94, Stock_New!A:M, 2, FALSE),"")) -> فازة | C94: =IF(A94="","",IFERROR(VLOOKUP(A94, Stock_New!A:M, 3, FALSE),"")) -> شركة الفرسان | D94: 2 | E94: =IF($A94="", "", IFERROR(VLOOKUP($A94, Stock_New!$A:$M, 4, FALSE), "")) -> 300 | F94: =E94*D94 -> 600 | G94: =IF($A94="", "", IFERROR(VLOOKUP($A94, Stock_New!$A:$M, 5, FALSE), "")) -> 2
A95: مزرعة خزف صغيرة | B95: =IF(A95="","",IFERROR(VLOOKUP(A95, Stock_New!A:M, 2, FALSE),"")) -> مقزمات | C95: =IF(A95="","",IFERROR(VLOOKUP(A95, Stock_New!A:M, 3, FALSE),"")) -> manufactured | D95: 8 | E95: =IF($A95="", "", IFERROR(VLOOKUP($A95, Stock_New!$A:$M, 4, FALSE), "")) -> 23.222222 | F95: =E95*D95 -> 185.77778 | G95: =IF($A95="", "", IFERROR(VLOOKUP($A95, Stock_New!$A:$M, 5, FALSE), "")) -> 22
A96: مزرعة خزف كبيرة | B96: =IF(A96="","",IFERROR(VLOOKUP(A96, Stock_New!A:M, 2, FALSE),"")) -> مقزمات | C96: =IF(A96="","",IFERROR(VLOOKUP(A96, Stock_New!A:M, 3, FALSE),"")) -> manufactured | D96: 7 | E96: =IF($A96="", "", IFERROR(VLOOKUP($A96, Stock_New!$A:$M, 4, FALSE), "")) -> 32.333333 | F96: =E96*D96 -> 226.33333 | G96: =IF($A96="", "", IFERROR(VLOOKUP($A96, Stock_New!$A:$M, 5, FALSE), "")) -> 30
A97: فازة خزف صغيرة تركي | B97: =IF(A97="","",IFERROR(VLOOKUP(A97, Stock_New!A:M, 2, FALSE),"")) -> خزف | C97: =IF(A97="","",IFERROR(VLOOKUP(A97, Stock_New!A:M, 3, FALSE),"")) -> ذكريا | D97: =1+3 -> 4 | E97: =IF($A97="", "", IFERROR(VLOOKUP($A97, Stock_New!$A:$M, 4, FALSE), "")) -> 40 | F97: =E97*D97 -> 160 | G97: =IF($A97="", "", IFERROR(VLOOKUP($A97, Stock_New!$A:$M, 5, FALSE), "")) -> 0
A98: غزالة خزف | B98: =IF(A98="","",IFERROR(VLOOKUP(A98, Stock_New!A:M, 2, FALSE),"")) -> خزف | C98: =IF(A98="","",IFERROR(VLOOKUP(A98, Stock_New!A:M, 3, FALSE),"")) -> شركة حسين علي | D98: 2 | E98: =IF($A98="", "", IFERROR(VLOOKUP($A98, Stock_New!$A:$M, 4, FALSE), "")) -> 150 | F98: =E98*D98 -> 300 | G98: =IF($A98="", "", IFERROR(VLOOKUP($A98, Stock_New!$A:$M, 5, FALSE), "")) -> 2
A99: فازة خزف وبوكيه ورد مقفول | B99: =IF(A99="","",IFERROR(VLOOKUP(A99, Stock_New!A:M, 2, FALSE),"")) -> بوكيه | C99: =IF(A99="","",IFERROR(VLOOKUP(A99, Stock_New!A:M, 3, FALSE),"")) -> ذكريا | D99: 1 | E99: =IF($A99="", "", IFERROR(VLOOKUP($A99, Stock_New!$A:$M, 4, FALSE), "")) -> 125 | F99: =E99*D99 -> 125 | G99: =IF($A99="", "", IFERROR(VLOOKUP($A99, Stock_New!$A:$M, 5, FALSE), "")) -> 3
A100: فازة خزف وورد احمر صغير | B100: =IF(A100="","",IFERROR(VLOOKUP(A100, Stock_New!A:M, 2, FALSE),"")) -> بوكيه | C100: =IF(A100="","",IFERROR(VLOOKUP(A100, Stock_New!A:M, 3, FALSE),"")) -> ذكريا | D100: 2 | E100: =IF($A100="", "", IFERROR(VLOOKUP($A100, Stock_New!$A:$M, 4, FALSE), "")) -> 135 | F100: =E100*D100 -> 270 | G100: =IF($A100="", "", IFERROR(VLOOKUP($A100, Stock_New!$A:$M, 5, FALSE), "")) -> 0
...

Sheet الورقة13
A1: راس مال | B1: -350503
A2: راتب | B2: =24153 -> 24153
A3: ايجار وتامين | B3: =37800 -> 37800
A4: تاسيس | B4: 64000
A5: اجمالي قيمة الجر | B5: =sum('جرد 2026'!F:F)+12000+18240+8680+2000+16050 -> 236155.62
B6: =SUM(B1:B5) -> 11605.619 | C6: =16500+10000+1700+12000 -> 40200
D7: =B5+C6 -> 276355.62
A10: الناتج | C10: =B6-D7 -> -264750

Sheet Orders_New
A1: ItemName | B1: ItemType | C1: Qty | D1: PurchasePrice | E1: Supplier | F1: OrderDate | G1: Status | H1: OrderID | I1: EnteredBy | J1: Notes
A2: فازة ازاز كبيره وبوكيه | B2: بوكيه | C2: 1 | D2: 725 | E2: ذكريا | F2: 45812 | G2: done | H2: ORD-1765058110612-119
A3: طقم زجاج ابيض وريش وورد صغير | B3: بوكيه | C3: 1 | D3: 415 | E3: ذكريا | F3: 45812 | G3: done | H3: ORD-1765058110618-468
A4: طقم زجاج ابيض وبوكيه اخضر | B4: بوكيه | C4: 1 | D4: 325 | E4: ذكريا | F4: 45812 | G4: done | H4: ORD-1765058110625-839
A5: طقم زجاج ابيض وريش بس | B5: بوكيه | C5: 1 | D5: 300 | E5: ذكريا | F5: 45812 | G5: done | H5: ORD-1765058110631-241
A6: فازة ازاز وبوكيه ورد غالي | B6: بوكيه زجاج | C6: 2 | D6: 295 | E6: ذكريا | F6: 45812 | G6: done | H6: ORD-1765058110639-611
A7: فازة ازاز وبوكيه ابيض وبيبي فلاور | B7: بوكيه زجاج | C7: 1 | D7: 200 | E7: ذكريا | F7: 45812 | G7: done | H7: ORD-1765058110644-364
A8: فازة خزف وبوكيه ابيض كبير | B8: بوكيه | C8: 1 | D8: 185 | E8: ذكريا | F8: 45812 | G8: done | H8: ORD-1765058110663-808
A9: فازة خزف وبوكيه ورد مقفول وورد صغير | B9: بوكيه | C9: 2 | D9: 180 | E9: ذكريا | F9: 45812 | G9: done | H9: ORD-1765058110669-489
A10: فازة ازاز وبوكيه | B10: بوكيه | C10: 3 | D10: 180 | E10: ذكريا | F10: 45812 | G10: done | H10: ORD-1765058110675-912
A11: بوكيه بلاستيك ورد كبير | B11: بوكيه | C11: 1 | D11: 175 | E11: ذكريا | F11: 45812 | G11: done | H11: ORD-1765058110681-293
A12: فازة خزف كبيره مشمش | B12: بوكيه | C12: 4 | D12: 175 | E12: ذكريا | F12: 45812 | G12: done | H12: ORD-1765058110687-965
A13: بوكيه بلاستيك | B13: بوكيه | C13: 2 | D13: 160 | E13: ذكريا | F13: 45812 | G13: done | H13: ORD-1765058110692-472
... A20: فازة خزف وبوكيه ورد مقفول | B20: بوكيه | C20: 3 | D20: 125 | E20: ذكريا | F20: 45812 | G20: done | H20: ORD-1765058110737-508
A21: بوكيه خزف مقسوم ورد شبه التاج | B21: بوكيه | C21: 2 | D21: =225/2 -> 112.5 | E21: ذكريا | F21: 45812 | G21: done | H21: ORD-1765058110743-574
A22: طقم زجاج ابيض فاضي | B22: زجاج ابيض | C22: 1 | D22: 125 | E22: ذكريا | F22: 45812 | G22: done | H22: ORD-1765058110749-731
A23: طقم دوناتس | B23: خزف | C23: 3 | D23: 135 | E23: ذكريا | F23: 45812 | G23: done | H23: ORD-1765058110758-650
A24: قطعة دوناتس | B24: خزف | C24: 2 | D24: =135/3 -> 45 | E24: ذكريا | F24: 45812 | G24: done | H24: ORD-1765058110764-606
A25: مزرعة بورسلين | B25: بوكيه | C25: 1 | D25: 55 | E25: ذكريا | F25: 45812 | G25: done | H25: ORD-1765058110769-292
A26: مزرعة بورسلين | B26: بوكيه | C26: 9 | D26: 35 | E26: ذكريا | F26: 45812 | G26: done | H26: ORD-1765058110788-263
A27: بوكيه اخضر | B27: ورد لوحده | C27: 2 | D27: 175 | E27: ذكريا | F27: 45812 | G27: done | H27: ORD-1765058110793-854
A28: طقم باسكت | B28: سيلفرات | C28: 1 | D28: 755 | E28: ذكريا | F28: 45812 | G28: done | H28: ORD-1765058110799-949
A29: شمعدان نخلة | B29: سيلفرات | C29: 1 | D29: 625 | E29: ذكريا | F29: 45812 | G29: done | H29: ORD-1765058110804-393
A30: شمعدان كريستال | B30: سيلفرات | C30: 1 | D30: 595 | E30: ذكريا | F30: 45812 | G30: done | H30: ORD-1765058110810-328
A31: شوكة كبيرة | B31: سيلفرات | C31: 3 | D31: 220 | E31: ذكريا | F31: 45812 | G31: done | H31: ORD-1765058110816-819
A32: شوكة وسط | B32: سيلفرات | C32: 6 | D32: 155 | E32: ذكريا | F32: 45812 | G32: done | H32: ORD-1765058110822-671
A33: شوكة صغيرة | B33: سيلفرات | C33: 6 | D33: 130 | E33: ذكريا | F33: 45812 | G33: done | H33: ORD-1765058110828-852
A34: شمعدان رفيع طويل عادي | B34: سيلفرات | C34: 2 | D34: 205 | E34: ذكريا | F34: 45812 | G34: done | H34: ORD-1765058110834-694
A35: شمعدان رفيع طويل اسود | B35: سيلفرات | C35: 2 | D35: 215 | E35: ذكريا | F35: 45812 | G35: done | H35: ORD-1765058110840-835
A36: كريستالة ديكور | B36: سيلفرات | C36: 3 | D36: 175 | E36: ذكريا | F36: 45812 | G36: done | H36: ORD-1765058110846-535
... A108: بوكيه بلاستيك واتنين صغيرين | B108: بوكيه | C108: 1 | D108: 125 | E108: ذكريا | F108: 45835 | G108: done | H108: ORD-1765058111377-814
A109: بوكيه بلاسيتك وورد مسك الليل | B109: بوكيه | C109: 2 | D109: =225/2 -> 112.5 | E109: ذكريا | F109: 45835 | G109: done | H109: ORD-1765058111383-847
A110: بوكيه ريش وورد صغير | B110: بوكيه | C110: 1 | D110: 110 | E110: ذكريا | F110: 45835 | G110: done | H110: ORD-1765058111389-358
A111: بوكيه بلاسيتك وورد احمر صغير | B111: بوكيه | C111: 1 | D111: 110 | E111: ذكريا | F111: 45835 | G111: done | H111: ORD-1765058111394-179
A112: بوكيه بلاستيك وورد روز | B112: بوكيه | C112: 1 | D112: 110 | E112: ذكريا | F112: 45835 | G112: done | H112: ORD-1765058111399-739
A113: بوكيه بلاستيك وورد مقفول | B113: بوكيه | C113: 2 | D113: 110 | E113: ذكريا | F113: 45835 | G113: done | H113: ORD-1765058111404-618
A114: مزرعة | B114: بوكيه | C114: 32 | D114: 35 | E114: ذكريا | F114: 45835 | G114: done | H114: ORD-1765058111409-193
A115: مزرعة صغيرة اكليرك | B115: بوكيه | C115: 16 | D115: 30 | E115: ذكريا | F115: 45835 | G115: done | H115: ORD-1765058111414-458
A116: اشكال السيرفرات | B116: سيلفرات | C116: 13 | D116: 120 | E116: ذكريا | F116: 45845 | G116: done | H116: ORD-1765058111419-420
A117: اشكال سيلفرات اقل | B117: سيلفرات | C117: 2 | D117: 95 | E117: ذكريا | F117: 45845 | G117: done | H117: ORD-1765058111424-533
A118: كتاب ديكور | B118: كتب | C118: 12 | D118: 17 | E118: ذكريا | F118: 45845 | G118: done | H118: ORD-1765058111429-539
A119: اباجورة شكل 0 | B119: كهربائيات | C119: 6 | D119: 165 | E119: ذكريا | F119: 45845 | G119: done | H119: ORD-1765058111449-456
A120: فواحة | B120: كهربائيات | C120: 2 | D120: 325 | E120: ذكريا | F120: 45845 | G120: done | H120: ORD-1765058111454-949
A121: مبخرة غزالة | B121: خزف | C121: 12 | D121: 60 | E121: ذكريا | F121: 45845 | G121: done | H121: ORD-1765058111459-745
... A130: بولا خزف وبوكيه ورد صغير | B130: بوكيه | C130: 6 | D130: 80 | E130: ذكريا | F130: 45856 | G130: done | H130: ORD-1765058111524-169
A131: بوت صغير هااند ميد و 2 بوكيه | B131: بوكيه | C131: 3 | D131: =85+150 -> 235 | E131: ذكريا | F131: 45856 | G131: done | H131: ORD-1765058111529-490
A132: بوت تركي هاند ميد | B132: بوتات | C132: 1 | D132: =275 -> 275 | E132: ذكريا | F132: 45856 | G132: done | H132: ORD-1765058111533-853
A133: بوت هاند ميد كبير | B133: بوكيه | C133: 2 | D133: 425 | E133: ذكريا | F133: 45856 | G133: done | H133: ORD-1765058111538-182
A134: بوت بشريطة دهبي | B134: بوتات | C134: 10 | D134: 175 | E134: ذكريا | F134: 45856 | G134: done | H134: ORD-1765058111559-881
A135: فرع مشمش جديد | B135: ورد لوحده | C135: 2 | D135: 150 | E135: ذكريا | F135: 45856 | G135: done | H135: ORD-1765058111564-838
A136: بوكيه كله | B136: ورد لوحده | C136: 1 | D136: 175 | E136: ذكريا | F136: 45856 | G136: done | H136: ORD-1765058111568-939
A137: بوكيه ورد كبير | B137: ورد لوحده | C137: 1 | D137: 145 | E137: ذكريا | F137: 45856 | G137: done | H137: ORD-1765058111573-890
A138: طفاية كريستال | B138: سيلفرات | C138: 2 | D138: 110 | E138: ذكريا | F138: 45856 | G138: done | H138: ORD-1765058111590-174
A139: كريستالة معلقة | B139: سيلفرات | C139: 4 | D139: 120 | E139: ذكريا | F139: 45856 | G139: done | H139: ORD-1765058111595-257
A140: نتيجة | B140: سيلفرات | C140: 2 | D140: 140 | E140: ذكريا | F140: 45856 | G140: done | H140: ORD-1765058111599-551
A141: طقم باسكت | B141: سيلفرات | C141: 1 | D141: 695 | E141: ذكريا | F141: 45856 | G141: done | H141: ORD-1765058111616-775
A142: موديل رقم 2043 | B142: سيلفرات | C142: 1 | D142: 1299 | E142: ذكريا | F142: 45856 | G142: done | H142: ORD-1765058111622-426
A143: موديل رقم 2042 | B143: سيلفرات | C143: 1 | D143: 1299 | E143: ذكريا | F143: 45856 | G143: done | H143: ORD-1765058111631-532
A144: موديل رقم 2051 | B144: سيلفرات | C144: 2 | D144: 1399 | E144: ذكريا | F144: 45856 | G144: done | H144: ORD-1765058111636-570
... A162: بولا خزف وريشة | B162: بوكيه | C162: 4 | D162: 55 | E162: ذكريا | F162: 45812 | G162: done | H162: ORD-1765058111726-680
A163: بوكيه بلاستيك وورد احمر | B163: بوكيه | C163: 1 | D163: 220 | E163: ذكريا | G163: done | H163: ORD-1765058111731-185
A164: ستارة خرز | B164: سيلفرات | C164: 3 | D164: 170 | E164: ذكريا | F164: 45896 | G164: done | H164: ORD-1765058111741-646
A165: بوكيه بق السيبع جلد | B165: ورد لوحده | C165: 3 | D165: 175 | E165: ذكريا | F165: 45896 | G165: done | H165: ORD-1765058111746-909
A166: بوكيه جلد | B166: ورد لوحده | C166: 14 | D166: 75 | E166: ذكريا | F166: 45896 | G166: done | H166: ORD-1765058111751-957
A167: بوكيه فل منفوش | B167: ورد لوحده | C167: 4 | D167: 90 | E167: ذكريا | F167: 45896 | G167: done | H167: ORD-1765058111756-699
A168: بوكيه دوار شمس | B168: ورد لوحده | C168: 1 | D168: 105 | E168: ذكريا | F168: 45896 | G168: done | H168: ORD-1765058111761-645
A169: شجرة موز 6 فرع | B169: شجر | C169: 1 | D169: 725 | E169: ذكريا | F169: 45812 | G169: done | H169: ORD-1765058111765-522
A170: مزرعة شلال | B170: بوكيه | C170: 43 | D170: 45 | E170: ذكريا | F170: 45812 | G170: done | H170: ORD-1765058111771-631
A171: اباجورة شكل 0 | B171: كهربائيات | C171: 40 | D171: 140 | E171: شركة البطل | G171: done | H171: ORD-1765058111777-440
A172: ورد فلاور شبه الفل | B172: ورد لوحده | C172: 2 | D172: 85 | E172: ذكريا | F172: 45904 | G172: done | H172: ORD-1765058111782-197
A173: توليب | B173: ورد لوحده | C173: 1 | D173: 175 | E173: ذكريا | F173: 45904 | G173: done | H173: ORD-1765058111787-204
A174: ورد زهور صغير | B174: ورد لوحده | C174: 7 | D174: 30 | E174: ذكريا | F174: 45904 | G174: done | H174: ORD-1765058111793-294
A175: ورد توليب بزهور | B175: ورد لوحده | C175: 1 | D175: 275 | E175: ذكريا | F175: 45904 | G175: done | H175: ORD-1765058111797-995
A176: ورد بلدي | B176: ورد لوحده | C176: 5 | D176: 225 | E176: ذكريا | F176: 45904 | G176: done | H176: ORD-1765058111802-991
A177: مزرعة | B177: بوكيه | C177: 32 | D177: 28 | E177: ذكريا | F177: 45904 | G177: done | H177: ORD-1765058111820-255
A178: كريستالة معلقة هلال | B178: سيلفرات | C178: 4 | D178: 105 | E178: ذكريا | F178: 45904 | G178: done | H178: ORD-1765058111825-845
A179: فازة بورسلين كبيرة | B179: سيلفرات | C179: 2 | D179: 325 | E179: ذكريا | F179: 45904 | G179: done | H179: ORD-1765058111831-712
A180: فازة بورسلين | B180: سيلفرات | C180: 9 | D180: 195 | E180: ذكريا | F180: 45904 | G180: done | H180: ORD-1765058111843-334
A181: طفاية كريستال ازاز | B181: سيلفرات | C181: 2 | D181: 70 | E181: ذكريا | F181: 45904 | G181: done | H181: ORD-1765058111849-979
A182: شجرة موز صغيرة | B182: كهربائيات | C182: 3 | D182: 225 | E182: ذكريا | F182: 45904 | G182: done | H182: ORD-1765058111854-608
A183: شجرة اريكا وسط | B183: شجر | C183: 1 | D183: 575 | E183: ذكريا | F183: 45904 | G183: done | H183: ORD-1765058111872-535
... A191: لوحة كبيرة | B191: لوح | C191: 2 | D191: 170 | E191: ذكريا | F191: 45929 | G191: done | H191: ORD-1765058111973-423
A192: بوت مستطيل بكسر رخام | B192: بوتات | C192: 2 | D192: =85+75 -> 160 | E192: ذكريا | F192: 45929 | G192: done | H192: ORD-1765058111978-838
A193: شجرة ذرة وسط | B193: شجر | C193: 1 | D193: 575 | E193: ذكريا | F193: 45929 | G193: done | H193: ORD-1765058111984-478
A194: شجرة موز 9 فرع | B194: شجر | C194: 1 | D194: 575 | E194: ذكريا | F194: 45929 | G194: done | H194: ORD-1765058111989-173
A195: شجرة موز صغيرة درجة عالية | B195: شجر | C195: 1 | D195: 375 | E195: ذكريا | F195: 45929 | G195: done | H195: ORD-1765058111996-192
A196: دوناتس مستطيل | B196: خزف | C196: 2 | D196: 135 | E196: ذكريا | F196: 45929 | G196: done | H196: ORD-1765058112001-547
A197: شجرة صغيرة 3d | B197: شجر | C197: 20 | D197: 65 | E197: ذكريا | F197: 45929 | G197: done | H197: ORD-1765058112006-809
A198: شيالة ازاز 3 | B198: سيلفر | C198: 1 | D198: 525 | E198: ذكريا | F198: 45929 | G198: done | H198: ORD-1765058112012-186
A199: كريستالة ديكور | B199: سيلفر | C199: 2 | D199: 135 | E199: ذكريا | F199: 45929 | G199: done | H199: ORD-1765058112017-909
A200: شبكة ورق شجر | B200: لوح | C200: 1 | D200: 275 | E200: ذكريا | F200: 45929 | G200: done | H200: ORD-1765058112022-769
A201: بوت صغير هاند ميد | B201: بوتات | C201: 5 | D201: 75 | E201: ذكريا | F201: 45929 | G201: done | H201: ORD-1765058112027-882
A202: بوت 2 شريطة دهبي | B202: بوتات | C202: 2 | D202: 175 | E202: ذكريا | F202: 45929 | G202: done | H202: ORD-1765058112033-916
A203: شجرة جاهزة | B203: شجر | C203: 2 | D203: 75 | E203: ذكريا | F203: 45929 | G203: done | H203: ORD-1765058112054-678
A204: بوكيه جيبس فل | B204: ورد لوحده | C204: 14 | D204: 30 | E204: ذكريا | F204: 45929 | G204: done | H204: ORD-1765058112058-986
... A227: مزرعة صغيرة اكليرك | B227: بوكيه | C227: 24 | D227: 27 | E227: ذكريا | F227: 45961 | G227: done | H227: ORD-1765058112345-434
F228: 45961 | G228: invalid
A229: ورد خرشوف احمر | B229: ورد لوحده | C229: 2 | D229: 145 | E229: ذكريا | F229: 45961 | G229: done | H229: ORD-1765058112353-347
A230: مزرعة صغيرة اكليرك اصغر | B230: بوكيه | C230: 36 | D230: 16 | E230: ذكريا | F230: 45961 | G230: done | H230: ORD-1765058112358-889
A231: طقم شمع | B231: شمع | C231: 2 | D231: =275/2 -> 137.5 | E231: ذكريا | F231: 45945 | G231: done | H231: ORD-1765058112364-214
...

Sheet Sales_New
A1: ProductName | B1: ItemType | C1: Qty | D1: Supplier | E1: SuggestedPrice | F1: ActualUnitPrice | G1: Discount | H1: TotalSale | I1: SaleDate | J1: Status | K1: SaleID | L1: EnteredBy | M1: اسم العميل | N1: الباقي | O1: تم دفع | P1: التكلفة
A2: بوت تركي | B2: =IF(A2="","",IFERROR(VLOOKUP(A2, Stock_New!A:M, 2, FALSE),"")) -> بوتات | C2: 2 | D2: =IF(A2="","",IFERROR(VLOOKUP(A2, Stock_New!A:M, 3, FALSE),"")) -> ذكريا | E2: =IF($A2="", "", IFERROR(VLOOKUP($A2, Stock_New!$A:$M, 6, FALSE), "")) -> 126 | F2: 120 | H2: 240 | I2: done | J2: done | K2: SAL-1765059347259-242 | M2: عم خالد | N2: =550-200-350 -> 0
A3: شجرة تركيب 12 ورقة | B3: =IF(A3="","",IFERROR(VLOOKUP(A3, Stock_New!A:M, 2, FALSE),"")) -> شجر | C3: 2 | D3: =IF(A3="","",IFERROR(VLOOKUP(A3, Stock_New!A:M, 3, FALSE),"")) -> ذكريا | E3: =IF($A3="", "", IFERROR(VLOOKUP($A3, Stock_New!$A:$M, 6, FALSE), "")) -> 114 | F3: 75 | G3: 0 | H3: 150 | I3: done | J3: done | K3: SAL-1765059347287-676 | M3: عم خالد | N3: =550-200-350 -> 0
A4: بوكيه خزف | B4: =IF(A4="","",IFERROR(VLOOKUP(A4, Stock_New!A:M, 2, FALSE),"")) -> بوكيه | C4: 1 | D4: =IF(A4="","",IFERROR(VLOOKUP(A4, Stock_New!A:M, 3, FALSE),"")) -> ذكريا | E4: =IF($A4="", "", IFERROR(VLOOKUP($A4, Stock_New!$A:$M, 6, FALSE), "")) -> 168 | F4: 150 | G4: 0 | H4: 150 | I4: done | J4: done | K4: SAL-1765059347322-954 | M4: عم خالد | N4: =550-200-350 -> 0
A5: فازة خزف وورد احمر صغير | B5: =IF(A5="","",IFERROR(VLOOKUP(A5, Stock_New!A:M, 2, FALSE),"")) -> بوكيه | C5: 1 | D5: =IF(A5="","",IFERROR(VLOOKUP(A5, Stock_New!A:M, 3, FALSE),"")) -> ذكريا | E5: =IF($A5="", "", IFERROR(VLOOKUP($A5, Stock_New!$A:$M, 6, FALSE), "")) -> 162 | F5: 195 | G5: 0 | H5: 195 | I5: done | J5: done | K5: SAL-1765059347355-448 | M5: عم خالد | N5: =550-200-350 -> 0
A6: فازة خزف وبوكيه ابيض كبير | B6: =IF(A6="","",IFERROR(VLOOKUP(A6, Stock_New!A:M, 2, FALSE),"")) -> بوكيه | C6: 1 | D6: =IF(A6="","",IFERROR(VLOOKUP(A6, Stock_New!A:M, 3, FALSE),"")) -> ذكريا | E6: =IF($A6="", "", IFERROR(VLOOKUP($A6, Stock_New!$A:$M, 6, FALSE), "")) -> 222 | F6: 235 | G6: 0 | H6: 235 | I6: done | J6: done | K6: SAL-1765059347379-326
A7: مزرعة | B7: =IF(A7="","",IFERROR(VLOOKUP(A7, Stock_New!A:M, 2, FALSE),"")) -> بوكيه | C7: 2 | D7: =IF(A7="","",IFERROR(VLOOKUP(A7, Stock_New!A:M, 3, FALSE),"")) -> ذكريا | E7: =IF($A7="", "", IFERROR(VLOOKUP($A7, Stock_New!$A:$M, 6, FALSE), "")) -> 44.4 | F7: 50 | G7: 0 | H7: 100 | I7: done | J7: done | K7: SAL-1765059347412-273
A8: شجرة ورق عريض | B8: =IF(A8="","",IFERROR(VLOOKUP(A8, Stock_New!A:M, 2, FALSE),"")) -> شجر | C8: 1 | D8: =IF(A8="","",IFERROR(VLOOKUP(A8, Stock_New!A:M, 3, FALSE),"")) -> ذكريا | E8: =IF($A8="", "", IFERROR(VLOOKUP($A8, Stock_New!$A:$M, 6, FALSE), "")) -> 234 | F8: 245 | G8: 0 | H8: 245 | I8: done | J8: done | K8: SAL-1765059347444-973
A9: بوكيه ورد احمر صغير واخضر | B9: =IF(A9="","",IFERROR(VLOOKUP(A9, Stock_New!A:M, 2, FALSE),"")) -> بوكيه | C9: 1 | D9: =IF(A9="","",IFERROR(VLOOKUP(A9, Stock_New!A:M, 3, FALSE),"")) -> ذكريا | E9: =IF($A9="", "", IFERROR(VLOOKUP($A9, Stock_New!$A:$M, 6, FALSE), "")) -> 204 | F9: 220 | G9: 0 | H9: 220 | I9: done | J9: done | K9: SAL-1765059347473-514
A10: مج بشاليموه | B10: =IF(A10="","",IFERROR(VLOOKUP(A10, Stock_New!A:M, 2, FALSE),"")) -> مطبخ | C10: 2 | D10: =IF(A10="","",IFERROR(VLOOKUP(A10, Stock_New!A:M, 3, FALSE),"")) -> ذكريا | E10: =IF($A10="", "", IFERROR(VLOOKUP($A10, Stock_New!$A:$M, 6, FALSE), "")) -> 90 | F10: 100 | G10: 0 | H10: 200 | I10: done | J10: done | K10: SAL-1765059347499-157 | M10: عم سعد
A11: فازة خزف وورد احمر صغير | B11: =IF(A11="","",IFERROR(VLOOKUP(A11, Stock_New!A:M, 2, FALSE),"")) -> بوكيه | C11: 1 | D11: =IF(A11="","",IFERROR(VLOOKUP(A11, Stock_New!A:M, 3, FALSE),"")) -> ذكريا | E11: =IF($A11="", "", IFERROR(VLOOKUP($A11, Stock_New!$A:$M, 6, FALSE), "")) -> 162 | F11: 195 | G11: 0 | H11: 195 | I11: done | J11: done | K11: SAL-1765059347533-739 | M11: عم سعد
A12: اشكال السيرفرات | B12: =IF(A12="","",IFERROR(VLOOKUP(A12, Stock_New!A:M, 2, FALSE),"")) -> سيلفرات | C12: 1 | D12: =IF(A12="","",IFERROR(VLOOKUP(A12, Stock_New!A:M, 3, FALSE),"")) -> ذكريا | E12: =IF($A12="", "", IFERROR(VLOOKUP($A12, Stock_New!$A:$M, 6, FALSE), "")) -> 144 | F12: 180 | G12: 0 | H12: 180 | I12: done | J12: done | K12: SAL-1765059347558-695 | M12: عم سعد
A13: بوت تركي | B13: =IF(A13="","",IFERROR(VLOOKUP(A13, Stock_New!A:M, 2, FALSE),"")) -> بوتات | C13: 1 | D13: =IF(A13="","",IFERROR(VLOOKUP(A13, Stock_New!A:M, 3, FALSE),"")) -> ذكريا | E13: =IF($A13="", "", IFERROR(VLOOKUP($A13, Stock_New!$A:$M, 6, FALSE), "")) -> 126 | F13: 140 | G13: 0 | H13: 140 | I13: done | J13: done | K13: SAL-1765059347584-687 | M13: عم سعد
A14: مبخرة غزالة | B14: =IF(A14="","",IFERROR(VLOOKUP(A14, Stock_New!A:M, 2, FALSE),"")) -> خزف | C14: 1 | D14: =IF(A14="","",IFERROR(VLOOKUP(A14, Stock_New!A:M, 3, FALSE),"")) -> ذكريا | E14: =IF($A14="", "", IFERROR(VLOOKUP($A14, Stock_New!$A:$M, 6, FALSE), "")) -> 72 | F14: 120 | G14: 0 | H14: 120 | I14: done | J14: done | K14: SAL-1765059347616-473 | M14: عم سعد
A15: مزرعة | B15: =IF(A15="","",IFERROR(VLOOKUP(A15, Stock_New!A:M, 2, FALSE),"")) -> بوكيه | C15: 3 | D15: =IF(A15="","",IFERROR(VLOOKUP(A15, Stock_New!A:M, 3, FALSE),"")) -> ذكريا | E15: =IF($A15="", "", IFERROR(VLOOKUP($A15, Stock_New!$A:$M, 6, FALSE), "")) -> 44.4 | F15: 50 | G15: 0 | H15: 150 | I15: done | J15: done | K15: SAL-1765059347643-179 | M15: محمد حامد التمساح
A16: بوكيه بلاستيك وورد احمر | B16: =IF(A16="","",IFERROR(VLOOKUP(A16, Stock_New!A:M, 2, FALSE),"")) -> بوكيه | C16: 1 | D16: =IF(A16="","",IFERROR(VLOOKUP(A16, Stock_New!A:M, 3, FALSE),"")) -> ذكريا | E16: =IF($A16="", "", IFERROR(VLOOKUP($A16, Stock_New!$A:$M, 6, FALSE), "")) -> 264 | F16: 252 | G16: 0 | H16: 252 | I16: done | J16: done | K16: SAL-1765059347675-928 | M16: محمد حامد التمساح
A17: بوكيه بلاستيك ورد كبير | B17: =IF(A17="","",IFERROR(VLOOKUP(A17, Stock_New!A:M, 2, FALSE),"")) -> بوكيه | C17: 1 | D17: =IF(A17="","",IFERROR(VLOOKUP(A17, Stock_New!A:M, 3, FALSE),"")) -> ذكريا | E17: =IF($A17="", "", IFERROR(VLOOKUP($A17, Stock_New!$A:$M, 6, FALSE), "")) -> 210 | F17: 290 | G17: 0 | H17: 290 | I17: done | J17: done | K17: SAL-1765059347709-743 | M17: محمد حامد التمساح
A18: بوكيه بلاستيك ورد مقفول وورد صغير | B18: =IF(A18="","",IFERROR(VLOOKUP(A18, Stock_New!A:M, 2, FALSE),"")) -> بوكيه | C18: 1 | D18: =IF(A18="","",IFERROR(VLOOKUP(A18, Stock_New!A:M, 3, FALSE),"")) -> ذكريا | E18: =IF($A18="", "", IFERROR(VLOOKUP($A18, Stock_New!$A:$M, 6, FALSE), "")) -> 192 | F18: 233 | G18: 0 | H18: 233 | I18: done | J18: done | K18: SAL-1765059347739-667 | M18: محمد حامد التمساح
A19: فازة خزف وورد احمر صغير | B19: =IF(A19="","",IFERROR(VLOOKUP(A19, Stock_New!A:M, 2, FALSE),"")) -> بوكيه | C19: 2 | D19: =IF(A19="","",IFERROR(VLOOKUP(A19, Stock_New!A:M, 3, FALSE),"")) -> ذكريا | E19: =IF($A19="", "", IFERROR(VLOOKUP($A19, Stock_New!$A:$M, 6, FALSE), "")) -> 162 | F19: 180 | G19: 0 | H19: =(1-Sales_New!$G19)*Sales_New!$F19*Sales_New!$C19 -> 360 | I19: done | J19: insufficient | M19: محمد حامد التمساح
A20: كريستالة ديكور | B20: =IF(A20="","",IFERROR(VLOOKUP(A20, Stock_New!A:M, 2, FALSE),"")) -> سيلفرات | C20: 1 | D20: =IF(A20="","",IFERROR(VLOOKUP(A20, Stock_New!A:M, 3, FALSE),"")) -> ذكريا | E20: =IF($A20="", "", IFERROR(VLOOKUP($A20, Stock_New!$A:$M, 6, FALSE), "")) -> 210 | F20: 220 | G20: 0 | H20: 220 | I20: done | J20: done | K20: SAL-1765059347778-898 | M20: محمد حامد التمساح
A21: مزرعة | B21: =IF(A21="","",IFERROR(VLOOKUP(A21, Stock_New!A:M, 2, FALSE),"")) -> بوكيه | C21: 1 | D21: =IF(A21="","",IFERROR(VLOOKUP(A21, Stock_New!A:M, 3, FALSE),"")) -> ذكريا | E21: =IF($A21="", "", IFERROR(VLOOKUP($A21, Stock_New!$A:$M, 6, FALSE), "")) -> 44.4 | F21: 50 | G21: 0 | H21: 50 | I21: done | J21: done | K21: SAL-1765059347812-969 | M21: زبون
A22: مج بشاليموه | B22: =IF(A22="","",IFERROR(VLOOKUP(A22, Stock_New!A:M, 2, FALSE),"")) -> مطبخ | C22: 1 | D22: =IF(A22="","",IFERROR(VLOOKUP(A22, Stock_New!A:M, 3, FALSE),"")) -> ذكريا | E22: =IF($A22="", "", IFERROR(VLOOKUP($A22, Stock_New!$A:$M, 6, FALSE), "")) -> 90 | F22: 100 | G22: 0 | H22: 100 | I22: done | J22: done | K22: SAL-1765059347851-686 | M22: زبون
A23: شجرة ورق عريض قماش | B23: =IF(A23="","",IFERROR(VLOOKUP(A23, Stock_New!A:M, 2, FALSE),"")) -> شجر | C23: 2 | D23: =IF(A23="","",IFERROR(VLOOKUP(A23, Stock_New!A:M, 3, FALSE),"")) -> ذكريا | E23: =IF($A23="", "", IFERROR(VLOOKUP($A23, Stock_New!$A:$M, 6, FALSE), "")) -> 227.15 | F23: 245 | G23: 0 | H23: 490 | I23: done | J23: done | K23: SAL-1765059762383-965 | M23: زبون
A24: بوت تركي | B24: =IF(A24="","",IFERROR(VLOOKUP(A24, Stock_New!A:M, 2, FALSE),"")) -> بوتات | C24: 2 | D24: =IF(A24="","",IFERROR(VLOOKUP(A24, Stock_New!A:M, 3, FALSE),"")) -> ذكريا | E24: =IF($A24="", "", IFERROR(VLOOKUP($A24, Stock_New!$A:$M, 6, FALSE), "")) -> 126 | F24: 135 | G24: 0 | H24: 270 | I24: done | J24: done | K24: SAL-1765059347894-950 | M24: زبون
A25: مزرعة | B25: =IF(A25="","",IFERROR(VLOOKUP(A25, Stock_New!A:M, 2, FALSE),"")) -> بوكيه | C25: 2 | D25: =IF(A25="","",IFERROR(VLOOKUP(A25, Stock_New!A:M, 3, FALSE),"")) -> ذكريا | E25: =IF($A25="", "", IFERROR(VLOOKUP($A25, Stock_New!$A:$M, 6, FALSE), "")) -> 44.4 | F25: 50 | G25: 0 | H25: 100 | I25: done | J25: done | K25: SAL-1765059347922-722 | M25: فاطمة اخت ايمان
A26: مزرعة | B26: =IF(A26="","",IFERROR(VLOOKUP(A26, Stock_New!A:M, 2, FALSE),"")) -> بوكيه | C26: 3 | D26: =IF(A26="","",IFERROR(VLOOKUP(A26, Stock_New!A:M, 3, FALSE),"")) -> ذكريا | E26: =IF($A26="", "", IFERROR(VLOOKUP($A26, Stock_New!$A:$M, 6, FALSE), "")) -> 44.4 | F26: 50 | G26: 0 | H26: 150 | I26: done | J26: done | K26: SAL-1765059347947-317 | M26: زبون
A27: بوكيه بلاستيك و ورد بني وصغير | B27: =IF(A27="","",IFERROR(VLOOKUP(A27, Stock_New!A:M, 2, FALSE),"")) -> بوكيه | C27: 1 | D27: =IF(A27="","",IFERROR(VLOOKUP(A27, Stock_New!A:M, 3, FALSE),"")) -> ذكريا | E27: =IF($A27="", "", IFERROR(VLOOKUP($A27, Stock_New!$A:$M, 6, FALSE), "")) -> 162 | F27: 250 | G27: 0.1 | H27: 249.75 | I27: done | J27: done | K27: SAL-1765059347975-219 | M27: زبون
A28: مزرعة | B28: =IF(A28="","",IFERROR(VLOOKUP(A28, Stock_New!A:M, 2, FALSE),"")) -> بوكيه | C28: 2 | D28: =IF(A28="","",IFERROR(VLOOKUP(A28, Stock_New!A:M, 3, FALSE),"")) -> ذكريا | E28: =IF($A28="", "", IFERROR(VLOOKUP($A28, Stock_New!$A:$M, 6, FALSE), "")) -> 44.4 | F28: 50 | G28: 0.1 | H28: 99.9 | I28: done | J28: done | K28: SAL-1765059348003-390 | M28: زبون
A29: كتاب ديكور | B29: =IF(A29="","",IFERROR(VLOOKUP(A29, Stock_New!A:M, 2, FALSE),"")) -> كتب | C29: 10 | D29: =IF(A29="","",IFERROR(VLOOKUP(A29, Stock_New!A:M, 3, FALSE),"")) -> ذكريا | E29: =IF($A29="", "", IFERROR(VLOOKUP($A29, Stock_New!$A:$M, 6, FALSE), "")) -> 20.4 | F29: 25 | G29: 0.1 | H29: 249.8 | I29: done | J29: done | K29: SAL-1765059348029-887 | M29: زبونة
A30: طقم كاندي غزالة | B30: =IF(A30="","",IFERROR(VLOOKUP(A30, Stock_New!A:M, 2, FALSE),"")) -> مطبخ | C30: 1 | D30: =IF(A30="","",IFERROR(VLOOKUP(A30, Stock_New!A:M, 3, FALSE),"")) -> ذكريا | E30: =IF($A30="", "", IFERROR(VLOOKUP($A30, Stock_New!$A:$M, 6, FALSE), "")) -> 360 | F30: 400 | G30: 0.1 | H30: 399.6 | I30: done | J30: done | K30: SAL-1765059348052-580 | M30: عروسة
A31: مج بشاليموه | B31: =IF(A31="","",IFERROR(VLOOKUP(A31, Stock_New!A:M, 2, FALSE),"")) -> مطبخ | C31: 1 | D31: =IF(A31="","",IFERROR(VLOOKUP(A31, Stock_New!A:M, 3, FALSE),"")) -> ذكريا | E31: =IF($A31="", "", IFERROR(VLOOKUP($A31, Stock_New!$A:$M, 6, FALSE), "")) -> 90 | F31: 100 | G31: 0.1 | H31: 99.9 | I31: done | J31: done | K31: SAL-1765059348075-275 | M31: عروسة
... A55: بوكيه ريش وورد صغير | B55: =IF(A55="","",IFERROR(VLOOKUP(A55, Stock_New!A:M, 2, FALSE),"")) -> بوكيه | C55: 1 | D55: =IF(A55="","",IFERROR(VLOOKUP(A55, Stock_New!A:M, 3, FALSE),"")) -> ذكريا | E55: =IF($A55="", "", IFERROR(VLOOKUP($A55, Stock_New!$A:$M, 6, FALSE), "")) -> 132 | F55: 210 | G55: 0.1 | H55: 209.79 | I55: done | J55: done | K55: SAL-1765059349066-375 | M55: بونة
A56: اباجورة شكل 0 | B56: =IF(A56="","",IFERROR(VLOOKUP(A56, Stock_New!A:M, 2, FALSE),"")) -> كهربائيات | C56: 1 | D56: =IF(A56="","",IFERROR(VLOOKUP(A56, Stock_New!A:M, 3, FALSE),"")) -> شركة البطل | E56: =IF($A56="", "", IFERROR(VLOOKUP($A56, Stock_New!$A:$M, 6, FALSE), "")) -> 144 | F56: 220 | G56: 0.1 | H56: 219.78 | I56: done | J56: done | K56: SAL-1765059349111-105 | M56: حجز محمود محمد مصطفى | N56: =1750-500-300-300-400-250 -> 0
A57: بوت بشريطة دهبي | B57: =IF(A57="","",IFERROR(VLOOKUP(A57, Stock_New!A:M, 2, FALSE),"")) -> بوتات | C57: 2 | D57: =IF(A57="","",IFERROR(VLOOKUP(A57, Stock_New!A:M, 3, FALSE),"")) -> ذكريا | E57: =IF($A57="", "", IFERROR(VLOOKUP($A57, Stock_New!$A:$M, 6, FALSE), "")) -> 197 | F57: 220 | G57: 0.1 | H57: 439.56 | I57: done | J57: done | K57: SAL-1765059349159-109 | M57: حجز محمود محمد مصطفى | N57: =1750-500-300-300-400-250 -> 0
A58: شجرة مشمش خمس فروع | B58: =IF(A58="","",IFERROR(VLOOKUP(A58, Stock_New!A:M, 2, FALSE),"")) -> شجر | C58: 1 | D58: =IF(A58="","",IFERROR(VLOOKUP(A58, Stock_New!A:M, 3, FALSE),"")) -> ذكريا | E58: =IF($A58="", "", IFERROR(VLOOKUP($A58, Stock_New!$A:$M, 6, FALSE), "")) -> 390 | F58: 425 | G58: 0.1 | H58: 424.58 | I58: done | J58: done | K58: SAL-1765059349226-783 | M58: حجز محمود محمد مصطفى | N58: =1750-500-300-300-400-250 -> 0
A59: شجرة اريكا وسط | B59: =IF(A59="","",IFERROR(VLOOKUP(A59, Stock_New!A:M, 2, FALSE),"")) -> شجر | C59: 1 | D59: =IF(A59="","",IFERROR(VLOOKUP(A59, Stock_New!A:M, 3, FALSE),"")) -> ذكريا | E59: =IF($A59="", "", IFERROR(VLOOKUP($A59, Stock_New!$A:$M, 6, FALSE), "")) -> 675 | F59: 715 | G59: 0.1 | H59: 714.29 | I59: done | J59: done | K59: SAL-1765059349269-768 | M59: حجز محمود محمد مصطفى | N59: =1750-500-300-300-400-250 -> 0
A60: بوت صغير هااند ميد و 2 بوكيه | B60: =IF(A60="","",IFERROR(VLOOKUP(A60, Stock_New!A:M, 2, FALSE),"")) -> بوكيه | C60: 1 | D60: =IF(A60="","",IFERROR(VLOOKUP(A60, Stock_New!A:M, 3, FALSE),"")) -> ذكريا | E60: =IF($A60="", "", IFERROR(VLOOKUP($A60, Stock_New!$A:$M, 6, FALSE), "")) -> 282 | F60: 350 | G60: 0.1 | H60: 349.65 | I60: done | J60: done | K60: SAL-1765059349341-529 | M60: زبونة
A61: شجر ورق الوان | B61: =IF(A61="","",IFERROR(VLOOKUP(A61, Stock_New!A:M, 2, FALSE),"")) -> شجر | C61: 1 | D61: =IF(A61="","",IFERROR(VLOOKUP(A61, Stock_New!A:M, 3, FALSE),"")) -> ذكريا | E61: =IF($A61="", "", IFERROR(VLOOKUP($A61, Stock_New!$A:$M, 6, FALSE), "")) -> 192 | F61: 200 | G61: 0 | H61: 200 | I61: done | J61: done | K61: SAL-1765059349390-343 | M61: زبونة
A62: شجرة مكثفة | B62: =IF(A62="","",IFERROR(VLOOKUP(A62, Stock_New!A:M, 2, FALSE),"")) -> شجر | C62: 1 | D62: =IF(A62="","",IFERROR(VLOOKUP(A62, Stock_New!A:M, 3, FALSE),"")) -> ذكريا | E62: =IF($A62="", "", IFERROR(VLOOKUP($A62, Stock_New!$A:$M, 6, FALSE), "")) -> 372 | F62: 450 | G62: 0 | H62: 450 | I62: done | J62: done | K62: SAL-1765059349440-492 | M62: زبونة
A63: بوت بشريطة دهبي | B63: =IF(A63="","",IFERROR(VLOOKUP(A63, Stock_New!A:M, 2, FALSE),"")) -> بوتات | C63: 2 | D63: =IF(A63="","",IFERROR(VLOOKUP(A63, Stock_New!A:M, 3, FALSE),"")) -> ذكريا | E63: =IF($A63="", "", IFERROR(VLOOKUP($A63, Stock_New!$A:$M, 6, FALSE), "")) -> 197 | F63: 220 | G63: 0 | H63: 440 | I63: done | J63: done | K63: SAL-1765059349480-506 | M63: زبونة
A64: طقم دوناتس طويل | B64: =IF(A64="","",IFERROR(VLOOKUP(A64, Stock_New!A:M, 2, FALSE),"")) -> خزف | C64: 1 | D64: =IF(A64="","",IFERROR(VLOOKUP(A64, Stock_New!A:M, 3, FALSE),"")) -> ذكريا | E64: =IF($A64="", "", IFERROR(VLOOKUP($A64, Stock_New!$A:$M, 6, FALSE), "")) -> 198 | F64: 335 | G64: 0 | H64: 335 | I64: done | J64: done | K64: SAL-1765059349519-256 | M64: زبونة
A65: بوكيه ورد كبير ابيض واخضر | B65: =IF(A65="","",IFERROR(VLOOKUP(A65, Stock_New!A:M, 2, FALSE),"")) -> بوكيه | C65: 1 | D65: =IF(A65="","",IFERROR(VLOOKUP(A65, Stock_New!A:M, 3, FALSE),"")) -> ذكريا | E65: =IF($A65="", "", IFERROR(VLOOKUP($A65, Stock_New!$A:$M, 6, FALSE), "")) -> 270 | F65: 300 | G65: 0 | H65: 300 | I65: done | J65: done | K65: SAL-1765059349575-580 | M65: زبونة
A66: شجرة ورق عريض جلد | B66: =IF(A66="","",IFERROR(VLOOKUP(A66, Stock_New!A:M, 2, FALSE),"")) -> شجر | C66: 1 | D66: =IF(A66="","",IFERROR(VLOOKUP(A66, Stock_New!A:M, 3, FALSE),"")) -> ذكريا | E66: =IF($A66="", "", IFERROR(VLOOKUP($A66, Stock_New!$A:$M, 6, FALSE), "")) -> 252 | F66: 264 | G66: 0 | H66: 264 | I66: done | J66: done | K66: SAL-1765059349640-905 | M66: زبونة
A67: بوت كبير عادي | B67: =IF(A67="","",IFERROR(VLOOKUP(A67, Stock_New!A:M, 2, FALSE),"")) -> بوتات | C67: 1 | D67: =IF(A67="","",IFERROR(VLOOKUP(A67, Stock_New!A:M, 3, FALSE),"")) -> ذكريا | E67: =IF($A67="", "", IFERROR(VLOOKUP($A67, Stock_New!$A:$M, 6, FALSE), "")) -> 162 | F67: 175 | G67: 0 | H67: 175 | I67: done | J67: done | K67: SAL-1765059349703-639 | M67: زبونة
A68: شجرة تركيب 18 ورقة | B68: =IF(A68="","",IFERROR(VLOOKUP(A68, Stock_New!A:M, 2, FALSE),"")) -> شجر | C68: 1 | D68: =IF(A68="","",IFERROR(VLOOKUP(A68, Stock_New!A:M, 3, FALSE),"")) -> ذكريا | E68: =IF($A68="", "", IFERROR(VLOOKUP($A68, Stock_New!$A:$M, 6, FALSE), "")) -> 174 | F68: 200 | G68: 0 | H68: 200 | I68: 45881 | J68: done | K68: SAL-1765059762406-441 | M68: زبونة
A69: بوت صغير | B69: =IF(A69="","",IFERROR(VLOOKUP(A69, Stock_New!A:M, 2, FALSE),"")) -> بوتات | C69: 1 | D69: =IF(A69="","",IFERROR(VLOOKUP(A69, Stock_New!A:M, 3, FALSE),"")) -> manufactured | E69: =IF($A69="", "", IFERROR(VLOOKUP($A69, Stock_New!$A:$M, 6, FALSE), "")) -> 27.3 | F69: 50 | G69: 0 | H69: 50 | I69: 45881 | J69: done | K69: SAL-1765059349763-131 | M69: زبونة
A70: مزرعة | B70: =IF(A70="","",IFERROR(VLOOKUP(A70, Stock_New!A:M, 2, FALSE),"")) -> بوكيه | C70: 3 | D70: =IF(A70="","",IFERROR(VLOOKUP(A70, Stock_New!A:M, 3, FALSE),"")) -> ذكريا | E70: =IF($A70="", "", IFERROR(VLOOKUP($A70, Stock_New!$A:$M, 6, FALSE), "")) -> 44.4 | F70: 50 | G70: 0 | H70: 150 | I70: 45894 | J70: done | K70: SAL-1765059349793-626 | M70: زبونة
A71: مزرعة صغيرة اكليرك | B71: =IF(A71="","",IFERROR(VLOOKUP(A71, Stock_New!A:M, 2, FALSE),"")) -> بوكيه | C71: 1 | D71: =IF(A71="","",IFERROR(VLOOKUP(A71, Stock_New!A:M, 3, FALSE),"")) -> ذكريا | E71: =IF($A71="", "", IFERROR(VLOOKUP($A71, Stock_New!$A:$M, 6, FALSE), "")) -> 33.84 | F71: 40 | G71: 0 | H71: 40 | I71: 45894 | J71: done | K71: SAL-1765059349825-503 | M71: زبونة
A72: ستارة خرز | B72: =IF(A72="","",IFERROR(VLOOKUP(A72, Stock_New!A:M, 2, FALSE),"")) -> سيلفرات | C72: 1 | D72: =IF(A72="","",IFERROR(VLOOKUP(A72, Stock_New!A:M, 3, FALSE),"")) -> ذكريا | E72: =IF($A72="", "", IFERROR(VLOOKUP($A72, Stock_New!$A:$M, 6, FALSE), "")) -> 204 | F72: 230 | G72: 0 | H72: 230 | I72: 45896 | J72: done | K72: SAL-1765059349858-877 | M72: زبونة
A73: بونبونيرة عجلة | B73: =IF(A73="","",IFERROR(VLOOKUP(A73, Stock_New!A:M, 2, FALSE),"")) -> سيلفرات | C73: 1 | D73: =IF(A73="","",IFERROR(VLOOKUP(A73, Stock_New!A:M, 3, FALSE),"")) -> ذكريا | E73: =IF($A73="", "", IFERROR(VLOOKUP($A73, Stock_New!$A:$M, 6, FALSE), "")) -> 690 | F73: 700 | G73: 0 | H73: 700 | I73: 45898 | J73: done | K73: SAL-1765059349899-623 | M73: زبونة
A74: علبة مناديل كريستال | B74: =IF(A74="","",IFERROR(VLOOKUP(A74, Stock_New!A:M, 2, FALSE),"")) -> سيلفرات | C74: 1 | D74: =IF(A74="","",IFERROR(VLOOKUP(A74, Stock_New!A:M, 3, FALSE),"")) -> شركة حسين علي | E74: =IF($A74="", "", IFERROR(VLOOKUP($A74, Stock_New!$A:$M, 6, FALSE), "")) -> 214.5 | F74: 205 | G74: 0 | H74: 205 | I74: 45898 | J74: done | K74: SAL-1765059349940-237
A75: كريستالة ديكور | B75: =IF(A75="","",IFERROR(VLOOKUP(A75, Stock_New!A:M, 2, FALSE),"")) -> سيلفرات | C75: 2 | D75: =IF(A75="","",IFERROR(VLOOKUP(A75, Stock_New!A:M, 3, FALSE),"")) -> ذكريا | E75: =IF($A75="", "", IFERROR(VLOOKUP($A75, Stock_New!$A:$M, 6, FALSE), "")) -> 210 | F75: 210 | G75: 0 | H75: 420 | I75: 45898 | J75: done | K75: SAL-1765059349977-884
A76: اباجورة شكل 0 | B76: =IF(A76="","",IFERROR(VLOOKUP(A76, Stock_New!A:M, 2, FALSE),"")) -> كهربائيات | C76: 2 | D76: =IF(A76="","",IFERROR(VLOOKUP(A76, Stock_New!A:M, 3, FALSE),"")) -> شركة البطل | E76: =IF($A76="", "", IFERROR(VLOOKUP($A76, Stock_New!$A:$M, 6, FALSE), "")) -> 144 | F76: 210 | G76: 0 | H76: 420 | I76: 45898 | J76: done | K76: SAL-1765059350014-634
A77: بوكيه بلاستيك و ريش واخضر عرايس:) | B77: =IF(A77="","",IFERROR(VLOOKUP(A77, Stock_New!A:M, 2, FALSE),"")) -> بوكيه | C77: 1 | D77: =IF(A77="","",IFERROR(VLOOKUP(A77, Stock_New!A:M, 3, FALSE),"")) -> ذكريا | E77: =IF($A77="", "", IFERROR(VLOOKUP($A77, Stock_New!$A:$M, 6, FALSE), "")) -> 372 | F77: 375 | G77: 0.07 | H77: 374.74 | I77: 45899 | J77: done | K77: SAL-1765059350051-624
A78: اباجورة شكل 0 | B78: =IF(A78="","",IFERROR(VLOOKUP(A78, Stock_New!A:M, 2, FALSE),"")) -> كهربائيات | C78: 2 | D78: =IF(A78="","",IFERROR(VLOOKUP(A78, Stock_New!A:M, 3, FALSE),"")) -> شركة البطل | E78: =IF($A78="", "", IFERROR(VLOOKUP($A78, Stock_New!$A:$M, 6, FALSE), "")) -> 144 | F78: 210 | G78: 0.07 | H78: 419.7 | I78: 45899 | J78: done | K78: SAL-1765059350083-902
A79: بوكيه خزف مقسوم ورد شبه التاج | B79: =IF(A79="","",IFERROR(VLOOKUP(A79, Stock_New!A:M, 2, FALSE),"")) -> بوكيه | C79: 1 | D79: =IF(A79="","",IFERROR(VLOOKUP(A79, Stock_New!A:M, 3, FALSE),"")) -> ذكريا | E79: =IF($A79="", "", IFERROR(VLOOKUP($A79, Stock_New!$A:$M, 6, FALSE), "")) -> 135 | F79: 185 | G79: 0.07 | H79: =(1-Sales_New!$G79)*Sales_New!$F79*Sales_New!$C79 -> 172.05 | I79: 45899 | J79: insufficient
A80: شجرة موز صغيرة | B80: =IF(A80="","",IFERROR(VLOOKUP(A80, Stock_New!A:M, 2, FALSE),"")) -> شجر | C80: 1 | D80: =IF(A80="","",IFERROR(VLOOKUP(A80, Stock_New!A:M, 3, FALSE),"")) -> ذكريا | E80: =IF($A80="", "", IFERROR(VLOOKUP($A80, Stock_New!$A:$M, 6, FALSE), "")) -> 300 | F80: 300 | G80: 0.07 | H80: 299.79 | I80: 45899 | J80: done | K80: SAL-1765059350126-193
A81: شجرة موز كبيرة | B81: =IF(A81="","",IFERROR(VLOOKUP(A81, Stock_New!A:M, 2, FALSE),"")) -> شجر | C81: 1 | D81: =IF(A81="","",IFERROR(VLOOKUP(A81, Stock_New!A:M, 3, FALSE),"")) -> ذكريا | E81: =IF($A81="", "", IFERROR(VLOOKUP($A81, Stock_New!$A:$M, 6, FALSE), "")) -> 390 | F81: 390 | G81: 0.07 | H81: 389.73 | I81: 45899 | J81: done | K81: SAL-1765059350171-777
A82: بوت وسط | B82: =IF(A82="","",IFERROR(VLOOKUP(A82, Stock_New!A:M, 2, FALSE),"")) -> بوتات | C82: 1 | D82: =IF(A82="","",IFERROR(VLOOKUP(A82, Stock_New!A:M, 3, FALSE),"")) -> ذكريا | E82: =IF($A82="", "", IFERROR(VLOOKUP($A82, Stock_New!$A:$M, 6, FALSE), "")) -> 106.88 | F82: 150 | G82: 0.07 | H82: 149.89 | I82: 45899 | J82: done | K82: SAL-1765059350249-756
A83: بوت كبير عادي | B83: =IF(A83="","",IFERROR(VLOOKUP(A83, Stock_New!A:M, 2, FALSE),"")) -> بوتات | C83: 1 | D83: =IF(A83="","",IFERROR(VLOOKUP(A83, Stock_New!A:M, 3, FALSE),"")) -> ذكريا | E83: =IF($A83="", "", IFERROR(VLOOKUP($A83, Stock_New!$A:$M, 6, FALSE), "")) -> 162 | F83: 160 | G83: 0.07 | H83: 159.89 | I83: 45899 | J83: done | K83: SAL-1765059350312-368
A84: مزرعة | B84: =IF(A84="","",IFERROR(VLOOKUP(A84, Stock_New!A:M, 2, FALSE),"")) -> بوكيه | C84: 2 | D84: =IF(A84="","",IFERROR(VLOOKUP(A84, Stock_New!A:M, 3, FALSE),"")) -> ذكريا | E84: =IF($A84="", "", IFERROR(VLOOKUP($A84, Stock_New!$A:$M, 6, FALSE), "")) -> 44.4 | F84: 50 | G84: 0 | H84: 100 | I84: 45901 | J84: done | K84: SAL-1765059350365-872
A85: مزرعة شلال | B85: =IF(A85="","",IFERROR(VLOOKUP(A85, Stock_New!A:M, 2, FALSE),"")) -> بوكيه | C85: 2 | D85: =IF(A85="","",IFERROR(VLOOKUP(A85, Stock_New!A:M, 3, FALSE),"")) -> ذكريا | E85: =IF($A85="", "", IFERROR(VLOOKUP($A85, Stock_New!$A:$M, 6, FALSE), "")) -> 54 | F85: 70 | G85: 0 | H85: 140 | I85: 45901 | J85: done | K85: SAL-1765059350421-937
A86: بوكيه فازة بورسلين دهبي وورد شبه التاج | B86: =IF(A86="","",IFERROR(VLOOKUP(A86, Stock_New!A:M, 2, FALSE),"")) -> بوكيه | C86: 1 | D86: =IF(A86="","",IFERROR(VLOOKUP(A86, Stock_New!A:M, 3, FALSE),"")) -> ذكريا | E86: =IF($A86="", "", IFERROR(VLOOKUP($A86, Stock_New!$A:$M, 6, FALSE), "")) -> 462 | F86: 490 | G86: 0 | H86: 490 | I86: 45901 | J86: done | K86: SAL-1765059350454-829
A87: شجرة ورق عريض | B87: =IF(A87="","",IFERROR(VLOOKUP(A87, Stock_New!A:M, 2, FALSE),"")) -> شجر | C87: 1 | D87: =IF(A87="","",IFERROR(VLOOKUP(A87, Stock_New!A:M, 3, FALSE),"")) -> ذكريا | E87: =IF($A87="", "", IFERROR(VLOOKUP($A87, Stock_New!$A:$M, 6, FALSE), "")) -> 234 | F87: 210 | G87: 0 | H87: 210 | I87: 45901 | J87: done | K87: SAL-1765059350496-678
A88: بوت بشريطة دهبي | B88: =IF(A88="","",IFERROR(VLOOKUP(A88, Stock_New!A:M, 2, FALSE),"")) -> بوتات | C88: 1 | D88: =IF(A88="","",IFERROR(VLOOKUP(A88, Stock_New!A:M, 3, FALSE),"")) -> ذكريا | E88: =IF($A88="", "", IFERROR(VLOOKUP($A88, Stock_New!$A:$M, 6, FALSE), "")) -> 197 | F88: 210 | G88: 0 | H88: 210 | I88: 45901 | J88: done | K88: SAL-1765059350527-655
A89: شجرة تركيب 18 ورقة | B89: =IF(A89="","",IFERROR(VLOOKUP(A89, Stock_New!A:M, 2, FALSE),"")) -> شجر | C89: 1 | D89: =IF(A89="","",IFERROR(VLOOKUP(A89, Stock_New!A:M, 3, FALSE),"")) -> ذكريا | E89: =IF($A89="", "", IFERROR(VLOOKUP($A89, Stock_New!$A:$M, 6, FALSE), "")) -> 174 | F89: 175 | G89: 0 | H89: 175 | I89: 45901 | J89: done | K89: SAL-1765059762427-337
A90: بوت وسط | B90: =IF(A90="","",IFERROR(VLOOKUP(A90, Stock_New!A:M, 2, FALSE),"")) -> بوتات | C90: 1 | D90: =IF(A90="","",IFERROR(VLOOKUP(A90, Stock_New!A:M, 3, FALSE),"")) -> ذكريا | E90: =IF($A90="", "", IFERROR(VLOOKUP($A90, Stock_New!$A:$M, 6, FALSE), "")) -> 106.88 | F90: 115 | G90: 0 | H90: 115 | I90: 45901 | J90: done | K90: SAL-1765059350548-724
A91: مزرعة صغيرة اكليرك | B91: =IF(A91="","",IFERROR(VLOOKUP(A91, Stock_New!A:M, 2, FALSE),"")) -> بوكيه | C91: 1 | D91: =IF(A91="","",IFERROR(VLOOKUP(A91, Stock_New!A:M, 3, FALSE),"")) -> ذكريا | E91: =IF($A91="", "", IFERROR(VLOOKUP($A91, Stock_New!$A:$M, 6, FALSE), "")) -> 33.84 | F91: 40 | G91: 0 | H91: 40 | I91: 45905 | J91: done | K91: SAL-1765059350582-786
... A104: بوكيه بلاسيتك وورد احمر صغير | B104: =IF(A104="","",IFERROR(VLOOKUP(A104, Stock_New!A:M, 2, FALSE),"")) -> بوكيه | C104: 1 | D104: =IF(A104="","",IFERROR(VLOOKUP(A104, Stock_New!A:M, 3, FALSE),"")) -> ذكريا | E104: =IF($A104="", "", IFERROR(VLOOKUP($A104, Stock_New!$A:$M, 6, FALSE), "")) -> 132 | F104: 190 | G104: 0 | H104: 190 | I104: 45909 | J104: done | K104: SAL-1765059350963-351
A105: مزرعة | B105: =IF(A105="","",IFERROR(VLOOKUP(A105, Stock_New!A:M, 2, FALSE),"")) -> بوكيه | C105: 1 | D105: =IF(A105="","",IFERROR(VLOOKUP(A105, Stock_New!A:M, 3, FALSE),"")) -> ذكريا | E105: =IF($A105="", "", IFERROR(VLOOKUP($A105, Stock_New!$A:$M, 6, FALSE), "")) -> 44.4 | F105: 50 | G105: 0 | H105: 50 | J105: done | K105: SAL-1765059350986-657
A106: مزرعة صغيرة اكليرك | B106: =IF(A106="","",IFERROR(VLOOKUP(A106, Stock_New!A:M, 2, FALSE),"")) -> بوكيه | C106: 1 | D106: =IF(A106="","",IFERROR(VLOOKUP(A106, Stock_New!A:M, 3, FALSE),"")) -> ذكريا | E106: =IF($A106="", "", IFERROR(VLOOKUP($A106, Stock_New!$A:$M, 6, FALSE), "")) -> 33.84 | F106: 40 | G106: 0 | H106: 40 | J106: done | K106: SAL-1765059351010-554
A107: فازة خزف وبوكيه ورد مقفول وورد صغير | B107: =IF(A107="","",IFERROR(VLOOKUP(A107, Stock_New!A:M, 2, FALSE),"")) -> بوكيه | C107: 1 | D107: =IF(A107="","",IFERROR(VLOOKUP(A107, Stock_New!A:M, 3, FALSE),"")) -> ذكريا | E107: =IF($A107="", "", IFERROR(VLOOKUP($A107, Stock_New!$A:$M, 6, FALSE), "")) -> 216 | F107: 235 | G107: 0.07 | H107: 234.84 | J107: done | K107: SAL-1765059351040-803
A108: بوكيه ورد احمر صغير واخضر | B108: =IF(A108="","",IFERROR(VLOOKUP(A108, Stock_New!A:M, 2, FALSE),"")) -> بوكيه | C108: 1 | D108: =IF(A108="","",IFERROR(VLOOKUP(A108, Stock_New!A:M, 3, FALSE),"")) -> ذكريا | E108: =IF($A108="", "", IFERROR(VLOOKUP($A108, Stock_New!$A:$M, 6, FALSE), "")) -> 204 | F108: 295 | G108: 0.07 | H108: =(1-Sales_New!$G108)*Sales_New!$F108*Sales_New!$C108 -> 274.35 | J108: insufficient
A109: بوكيه بلاستيك و ريش واخضر عرايس:) | B109: =IF(A109="","",IFERROR(VLOOKUP(A109, Stock_New!A:M, 2, FALSE),"")) -> بوكيه | C109: 1 | D109: =IF(A109="","",IFERROR(VLOOKUP(A109, Stock_New!A:M, 3, FALSE),"")) -> ذكريا | E109: =IF($A109="", "", IFERROR(VLOOKUP($A109, Stock_New!$A:$M, 6, FALSE), "")) -> 372 | F109: 430 | G109: 0.07 | H109: =(1-Sales_New!$G109)*Sales_New!$F109*Sales_New!$C109 -> 399.9 | J109: insufficient
A110: شجرة مشمش 4 فروع | B110: =IF(A110="","",IFERROR(VLOOKUP(A110, Stock_New!A:M, 2, FALSE),"")) -> شجر | C110: 1 | D110: =IF(A110="","",IFERROR(VLOOKUP(A110, Stock_New!A:M, 3, FALSE),"")) -> ذكريا | E110: =IF($A110="", "", IFERROR(VLOOKUP($A110, Stock_New!$A:$M, 6, FALSE), "")) -> 330 | F110: 330 | G110: 0.07 | H110: 329.77 | J110: done | K110: SAL-1765059351063-684
A111: بوت بشريطة دهبي | B111: =IF(A111="","",IFERROR(VLOOKUP(A111, Stock_New!A:M, 2, FALSE),"")) -> بوتات | C111: 1 | D111: =IF(A111="","",IFERROR(VLOOKUP(A111, Stock_New!A:M, 3, FALSE),"")) -> ذكريا | E111: =IF($A111="", "", IFERROR(VLOOKUP($A111, Stock_New!$A:$M, 6, FALSE), "")) -> 197 | F111: 220 | G111: 0.07 | H111: 219.85 | J111: done | K111: SAL-1765059351087-195
A112: شجرة ورق عريض | B112: =IF(A112="","",IFERROR(VLOOKUP(A112, Stock_New!A:M, 2, FALSE),"")) -> شجر | C112: 1 | D112: =IF(A112="","",IFERROR(VLOOKUP(A112, Stock_New!A:M, 3, FALSE),"")) -> ذكريا | E112: =IF($A112="", "", IFERROR(VLOOKUP($A112, Stock_New!$A:$M, 6, FALSE), "")) -> 234 | F112: 220 | G112: 0.07 | H112: 219.85 | J112: done | K112: SAL-1765059351108-527
A113: بوت بشريطة دهبي | B113: =IF(A113="","",IFERROR(VLOOKUP(A113, Stock_New!A:M, 2, FALSE),"")) -> بوتات | C113: 1 | D113: =IF(A113="","",IFERROR(VLOOKUP(A113, Stock_New!A:M, 3, FALSE),"")) -> ذكريا | E113: =IF($A113="", "", IFERROR(VLOOKUP($A113, Stock_New!$A:$M, 6, FALSE), "")) -> 197 | F113: 210 | G113: 0.07 | H113: 209.85 | J113: done | K113: SAL-1765059351134-810
A114: شجرة مانجا 18 ورقة | B114: =IF(A114="","",IFERROR(VLOOKUP(A114, Stock_New!A:M, 2, FALSE),"")) -> شجر | C114: 1 | D114: =IF(A114="","",IFERROR(VLOOKUP(A114, Stock_New!A:M, 3, FALSE),"")) -> ذكريا | E114: =IF($A114="", "", IFERROR(VLOOKUP($A114, Stock_New!$A:$M, 6, FALSE), "")) -> 480 | F114: 480 | H114: 480 | I114: 45919 | J114: done | K114: SAL-1765059351158-442
A115: بوت بشريطة دهبي | B115: =IF(A115="","",IFERROR(VLOOKUP(A115, Stock_New!A:M, 2, FALSE),"")) -> بوتات | C115: 1 | D115: =IF(A115="","",IFERROR(VLOOKUP(A115, Stock_New!A:M, 3, FALSE),"")) -> ذكريا | E115: =IF($A115="", "", IFERROR(VLOOKUP($A115, Stock_New!$A:$M, 6, FALSE), "")) -> 197 | F115: 210 | H115: 210 | I115: 45919 | J115: done | K115: SAL-1765059351185-683
A116: شمعدان رفيع طويل عادي | B116: =IF(A116="","",IFERROR(VLOOKUP(A116, Stock_New!A:M, 2, FALSE),"")) -> سيلفرات | C116: 1 | D116: =IF(A116="","",IFERROR(VLOOKUP(A116, Stock_New!A:M, 3, FALSE),"")) -> ذكريا | E116: =IF($A116="", "", IFERROR(VLOOKUP($A116, Stock_New!$A:$M, 6, FALSE), "")) -> 246 | F116: 275 | G116: 0.1 | H116: 274.73 | I116: 45919 | J116: done | K116: SAL-1765059351216-742
A117: كريستالة معلقة | B117: =IF(A117="","",IFERROR(VLOOKUP(A117, Stock_New!A:M, 2, FALSE),"")) -> سيلفرات | C117: 2 | D117: =IF(A117="","",IFERROR(VLOOKUP(A117, Stock_New!A:M, 3, FALSE),"")) -> ذكريا | E117: =IF($A117="", "", IFERROR(VLOOKUP($A117, Stock_New!$A:$M, 6, FALSE), "")) -> 144 | F117: 180 | G117: 0.1 | H117: 359.64 | I117: 45919 | J117: done | K117: SAL-1765059351246-449
A118: شجرة تركيب 18 ورقة | B118: =IF(A118="","",IFERROR(VLOOKUP(A118, Stock_New!A:M, 2, FALSE),"")) -> شجر | C118: 1 | D118: =IF(A118="","",IFERROR(VLOOKUP(A118, Stock_New!A:M, 3, FALSE),"")) -> ذكريا | E118: =IF($A118="", "", IFERROR(VLOOKUP($A118, Stock_New!$A:$M, 6, FALSE), "")) -> 174 | F118: 200 | G118: 0 | H118: 200 | I118: 45919 | J118: done | K118: SAL-1765059762453-418
A119: بوت صغير | B119: =IF(A119="","",IFERROR(VLOOKUP(A119, Stock_New!A:M, 2, FALSE),"")) -> بوتات | C119: 1 | D119: =IF(A119="","",IFERROR(VLOOKUP(A119, Stock_New!A:M, 3, FALSE),"")) -> manufactured | E119: =IF($A119="", "", IFERROR(VLOOKUP($A119, Stock_New!$A:$M, 6, FALSE), "")) -> 27.3 | F119: 45 | G119: 0 | H119: 45 | I119: 45919 | J119: done | K119: SAL-1765059351282-668
A120: اباجورة شكل 0 | B120: =IF(A120="","",IFERROR(VLOOKUP(A120, Stock_New!A:M, 2, FALSE),"")) -> كهربائيات | C120: 3 | E120: =IF($A120="", "", IFERROR(VLOOKUP($A120, Stock_New!$A:$M, 6, FALSE), "")) -> 144 | F120: 200 | G120: 0.1 | H120: 599.4 | I120: 45919 | J120: done | K120: SAL-1765059351311-245
A121: مبخرة غزالة | B121: =IF(A121="","",IFERROR(VLOOKUP(A121, Stock_New!A:M, 2, FALSE),"")) -> خزف | C121: 1 | D121: =IF(A121="","",IFERROR(VLOOKUP(A121, Stock_New!A:M, 3, FALSE),"")) -> ذكريا | E121: =IF($A121="", "", IFERROR(VLOOKUP($A121, Stock_New!$A:$M, 6, FALSE), "")) -> 72 | F121: 95 | G121: 0.1 | H121: 94.91 | I121: 45919 | J121: done | K121: SAL-1765059351345-737
A122: ورد بلدي | B122: =IF(A122="","",IFERROR(VLOOKUP(A122, Stock_New!A:M, 2, FALSE),"")) -> ورد لوحده | C122: 1 | D122: =IF(A122="","",IFERROR(VLOOKUP(A122, Stock_New!A:M, 3, FALSE),"")) -> ذكريا | E122: =IF($A122="", "", IFERROR(VLOOKUP($A122, Stock_New!$A:$M, 6, FALSE), "")) -> 270 | F122: 290 | G122: 0 | H122: 290 | I122: 45919 | J122: done | K122: SAL-1765059351372-180
A123: ورد زهور صغير | B123: =IF(A123="","",IFERROR(VLOOKUP(A123, Stock_New!A:M, 2, FALSE),"")) -> ورد لوحده | C123: 1 | D123: =IF(A123="","",IFERROR(VLOOKUP(A123, Stock_New!A:M, 3, FALSE),"")) -> ذكريا | E123: =IF($A123="", "", IFERROR(VLOOKUP($A123, Stock_New!$A:$M, 6, FALSE), "")) -> 36 | F123: 60 | G123: 0 | H123: 60 | I123: 45919 | J123: done | K123: SAL-1765059351394-294
A124: ورد بلدي | B124: =IF(A124="","",IFERROR(VLOOKUP(A124, Stock_New!A:M, 2, FALSE),"")) -> ورد لوحده | C124: 1 | D124: =IF(A124="","",IFERROR(VLOOKUP(A124, Stock_New!A:M, 3, FALSE),"")) -> ذكريا | E124: =IF($A124="", "", IFERROR(VLOOKUP($A124, Stock_New!$A:$M, 6, FALSE), "")) -> 270 | F124: 290 | G124: 0 | H124: 290 | I124: 45904 | J124: done | K124: SAL-1765059351422-820
A125: ورد زهور صغير | B125: =IF(A125="","",IFERROR(VLOOKUP(A125, Stock_New!A:M, 2, FALSE),"")) -> ورد لوحده | C125: 1 | D125: =IF(A125="","",IFERROR(VLOOKUP(A125, Stock_New!A:M, 3, FALSE),"")) -> ذكريا | E125: =IF($A125="", "", IFERROR(VLOOKUP($A125, Stock_New!$A:$M, 6, FALSE), "")) -> 36 | F125: 60 | G125: 0 | H125: 60 | I125: 45904 | J125: done | K125: SAL-1765059351442-959
A126: بوت صغير هااند ميد و 2 بوكيه | B126: =IF(A126="","",IFERROR(VLOOKUP(A126, Stock_New!A:M, 2, FALSE),"")) -> بوكيه | C126: 1 | D126: =IF(A126="","",IFERROR(VLOOKUP(A126, Stock_New!A:M, 3, FALSE),"")) -> ذكريا | E126: =IF($A126="", "", IFERROR(VLOOKUP($A126, Stock_New!$A:$M, 6, FALSE), "")) -> 282 | F126: 350 | G126: 0 | H126: 350 | I126: 45924 | J126: done | K126: SAL-1765059351474-645
A127: نتيجة | B127: =IF(A127="","",IFERROR(VLOOKUP(A127, Stock_New!A:M, 2, FALSE),"")) -> سيلفرات | C127: 1 | D127: =IF(A127="","",IFERROR(VLOOKUP(A127, Stock_New!A:M, 3, FALSE),"")) -> ذكريا | E127: =IF($A127="", "", IFERROR(VLOOKUP($A127, Stock_New!$A:$M, 6, FALSE), "")) -> 168 | F127: 220 | G127: 0 | H127: 220 | I127: 45924 | J127: done | K127: SAL-1765059351501-124
A128: فازة خزف متوسطة | B128: =IF(A128="","",IFERROR(VLOOKUP(A128, Stock_New!A:M, 2, FALSE),"")) -> خزف | C128: 1 | D128: =IF(A128="","",IFERROR(VLOOKUP(A128, Stock_New!A:M, 3, FALSE),"")) -> ذكريا | E128: =IF($A128="", "", IFERROR(VLOOKUP($A128, Stock_New!$A:$M, 6, FALSE), "")) -> 90 | F128: 100 | G128: 0 | H128: 100 | I128: 45924 | J128: done | K128: SAL-1765059351533-856
A129: اباجورة شكل 0 | B129: =IF(A129="","",IFERROR(VLOOKUP(A129, Stock_New!A:M, 2, FALSE),"")) -> كهربائيات | C129: 2 | E129: =IF($A129="", "", IFERROR(VLOOKUP($A129, Stock_New!$A:$M, 6, FALSE), "")) -> 144 | F129: 200 | G129: 0 | H129: 400 | I129: 9/30/2025 | J129: done | K129: SAL-1765059351558-710
A130: بوت تركي هاند ميد | B130: =IF(A130="","",IFERROR(VLOOKUP(A130, Stock_New!A:M, 2, FALSE),"")) -> بوتات | C130: 1 | D130: =IF(A130="","",IFERROR(VLOOKUP(A130, Stock_New!A:M, 3, FALSE),"")) -> ذكريا | E130: =IF($A130="", "", IFERROR(VLOOKUP($A130, Stock_New!$A:$M, 6, FALSE), "")) -> 330 | F130: 400 | G130: 0 | H130: 400 | I130: 9/30/2025 | J130: done | K130: SAL-1765059351588-912 | P130: 3375
A131: علبة مناديل كريستال | B131: =IF(A131="","",IFERROR(VLOOKUP(A131, Stock_New!A:M, 2, FALSE),"")) -> سيلفرات | C131: 1 | D131: =IF(A131="","",IFERROR(VLOOKUP(A131, Stock_New!A:M, 3, FALSE),"")) -> شركة حسين علي | E131: =IF($A131="", "", IFERROR(VLOOKUP($A131, Stock_New!$A:$M, 6, FALSE), "")) -> 214.5 | F131: 200 | G131: 0 | H131: 200 | I131: 9/30/2025 | J131: done | K131: SAL-1765059351618-734 | M131: حجز محمود محمد مصطفى | N131: =2335-150 -> 2185 | P131: =3375-500 -> 2875
A132: بوكيه ابيض كبير مجفف | B132: =IF(A132="","",IFERROR(VLOOKUP(A132, Stock_New!A:M, 2, FALSE),"")) -> ورد لوحده | C132: 1 | D132: =IF(A132="","",IFERROR(VLOOKUP(A132, Stock_New!A:M, 3, FALSE),"")) -> ذكريا | E132: =IF($A132="", "", IFERROR(VLOOKUP($A132, Stock_New!$A:$M, 6, FALSE), "")) -> 186 | F132: 200 | G132: 0 | H132: 200 | I132: 9/30/2025 | J132: done | K132: SAL-1765059351648-508 | M132: حجز محمود محمد مصطفى | N132: =2335-150 -> 2185
A133: بوكيه فل | B133: =IF(A133="","",IFERROR(VLOOKUP(A133, Stock_New!A:M, 2, FALSE),"")) -> ورد لوحده | C133: 2 | D133: =IF(A133="","",IFERROR(VLOOKUP(A133, Stock_New!A:M, 3, FALSE),"")) -> ذكريا | E133: =IF($A133="", "", IFERROR(VLOOKUP($A133, Stock_New!$A:$M, 6, FALSE), "")) -> 132 | F133: 130 | G133: 0 | H133: 260 | I133: 9/30/2025 | J133: done | K133: SAL-1765059351668-162 | M133: حجز محمود محمد مصطفى | N133: =2335-150 -> 2185
A134: فازة بورسلين كبيرة | B134: =IF(A134="","",IFERROR(VLOOKUP(A134, Stock_New!A:M, 2, FALSE),"")) -> سيلفرات | C134: 1 | D134: =IF(A134="","",IFERROR(VLOOKUP(A134, Stock_New!A:M, 3, FALSE),"")) -> ذكريا | E134: =IF($A134="", "", IFERROR(VLOOKUP($A134, Stock_New!$A:$M, 6, FALSE), "")) -> 390 | F134: 350 | G134: 0 | H134: 350 | I134: 9/30/2025 | J134: done | K134: SAL-1765059351699-749 | M134: حجز محمود محمد مصطفى | N134: =2335-150 -> 2185
A135: ورد زهور صغير | B135: =IF(A135="","",IFERROR(VLOOKUP(A135, Stock_New!A:M, 2, FALSE),"")) -> ورد لوحده | C135: 1 | D135: =IF(A135="","",IFERROR(VLOOKUP(A135, Stock_New!A:M, 3, FALSE),"")) -> ذكريا | E135: =IF($A135="", "", IFERROR(VLOOKUP($A135, Stock_New!$A:$M, 6, FALSE), "")) -> 36 | F135: 40 | G135: 0 | H135: 40 | I135: 9/30/2025 | J135: done | K135: SAL-1765059351747-379 | M135: حجز محمود محمد مصطفى | N135: =2335-150 -> 2185
...

Sheet Journal
A1: Date | B1: EntryID | C1: AccountDebit | D1: AccountCredit | E1: Amount | F1: Note
A2: 45998.011 | B2: SAL-1765059347259-242 | C2: COGS | D2: Inventory | E2: 210 | F2: COGS for بوت تركي
A3: 45998.011 | B3: SAL-1765059347259-242 | C3: Cash/AR | D3: Sales | E3: 240 | F3: Revenue for بوت تركي
A4: 45998.011 | B4: SAL-1765059347287-676 | C4: COGS | D4: Inventory | E4: 190 | F4: COGS for شجرة تركيب 12 ورقة
A5: 45998.011 | B5: SAL-1765059347287-676 | C5: Cash/AR | D5: Sales | E5: 150 | F5: Revenue for شجرة تركيب 12 ورقة
A6: 45998.011 | B6: SAL-1765059347322-954 | C6: COGS | D6: Inventory | E6: 140 | F6: COGS for بوكيه خزف
A7: 45998.011 | B7: SAL-1765059347322-954 | C7: Cash/AR | D7: Sales | E7: 150 | F7: Revenue for بوكيه خزف
A8: 45998.011 | B8: SAL-1765059347355-448 | C8: COGS | D8: Inventory | E8: 135 | F8: COGS for فازة خزف وورد احمر صغير
A9: 45998.011 | B9: SAL-1765059347355-448 | C9: Cash/AR | D9: Sales | E9: 195 | F9: Revenue for فازة خزف وورد احمر صغير
A10: 45998.011 | B10: SAL-1765059347379-326 | C10: COGS | D10: Inventory | E10: 185 | F10: COGS for فازة خزف وبوكيه ابيض كبير
A11: 45998.011 | B11: SAL-1765059347379-326 | C11: Cash/AR | D11: Sales | E11: 235 | F11: Revenue for فازة خزف وبوكيه ابيض كبير
A12: 45998.011 | B12: SAL-1765059347412-273 | C12: COGS | D12: Inventory | E12: 63 | F12: COGS for مزرعة
A13: 45998.011 | B13: SAL-1765059347412-273 | C13: Cash/AR | D13: Sales | E13: 100 | F13: Revenue for مزرعة
... A2551: 46172.911 | B2551: SAL-1780167096171-913 | C2551: Cash/AR | D2551: Sales | E2551: 200 | F2551: Revenue for علبة مناديل كريستال خلص

Sheet Logs_New
A1: TimeStamp | B1: العمود 2 | C1: ItemName | D1: Qty | E1: PurchasePrice | F1: ActualUnitPrice | G1: FinalUnitPrice | H1: TotalSale | I1: Profit | J1: Supplier | K1: RefRow | L1: Message | M1: User
A2: 46081.971 | B2: Manufacturing-Output | C2: بوت صغير | D2: 1 | E2: 22.75 | H2: 22.75 | J2: manufactured | K2: مقزم-شجر | L2: Product manufactured | M2: abdofwzy9@gmail.com
A3: 46081.971 | B3: Manufacturing-Output | C3: مقزم شجر | D3: 3 | E3: 14.083333 | H3: 42.25 | J3: manufactured | K3: مقزم-شجر | L3: Product manufactured | M3: abdofwzy9@gmail.com
A4: 46081.971 | B4: Manufacturing-Input | C4: شجرة صغيرة 3d | D4: 1 | E4: 65 | H4: 65 | J4: ذكريا | K4: مقزم-شجر | L4: Used in manufacturing | M4: abdofwzy9@gmail.com
A5: 46081.968 | B5: Manufacturing-Output | C5: بوت صغير | D5: 2 | E5: 22.75 | H5: 45.5 | J5: manufactured | K5: مقزم-شجر | L5: Product manufactured | M5: abdofwzy9@gmail.com
A6: 46081.968 | B6: Manufacturing-Output | C6: مقزم شجر | D6: 6 | E6: 14.083333 | H6: 84.5 | J6: manufactured | K6: مقزم-شجر | L6: Product manufactured | M6: abdofwzy9@gmail.com
A7: 46081.968 | B7: Manufacturing-Input | C7: شجرة صغيرة 3d | D7: 2 | E7: 65 | H7: 130 | J7: ذكريا | K7: مقزم-شجر | L7: Used in manufacturing | M7: abdofwzy9@gmail.com
A8: 46150.808 | B8: Mfg-In | C8: خضرة اللوان 18 | D8: 1 | E8: 110 | H8: 110 | J8: شركة الفرسان | K8: مقزم_خضرا _الوان | L8: Used | M8: abdofwzy9@gmail.com
A9: 46081.945 | B9: Manufacturing-Output | C9: بوكيه صغير | D9: 1 | E9: 28.5 | H9: 28.5 | J9: manufactured | K9: مقزم-شجر | L9: Product manufactured | M9: abdofwzy9@gmail.com
A10: 46081.945 | B10: Manufacturing-Output | C10: مقزم شجر | D10: 3 | E10: 22.166667 | H10: 66.5 | J10: manufactured | K10: مقزم-شجر | L10: Product manufactured | M10: abdofwzy9@gmail.com
A11: 46081.945 | B11: Manufacturing-Input | C11: بوت صغير مقزمات | D11: 3 | E11: 10 | H11: 30 | J11: شركة حسين علي | K11: مقزم-شجر | L11: Used in manufacturing | M11: abdofwzy9@gmail.com
A12: 46081.945 | B12: Manufacturing-Input | C12: شجرة صغيرة 3d | D12: 1 | E12: 65 | H12: 65 | J12: ذكريا | K12: مقزم-شجر | L12: Used in manufacturing | M12: abdofwzy9@gmail.com
A13: 46150.808 | B13: Mfg-In | C13: بروبلين 5سم عبدالله | D13: 18 | E13: 3.5 | H13: 63 | J13: شركة حسين علي | K13: مقزم_خضرا _الوان | L13: Used | M13: abdofwzy9@gmail.com
... A16: 46150.783 | B16: Mfg-In | C16: قصرية 20سم | D16: 1 | E16: 10 | H16: 10 | J16: عبدالفتاح | K16: شجرة_بنجامين_110سم | L16: Used | M16: abdofwzy9@gmail.com
A17: 46096.001 | B17: Purchase | C17: فازة بورسلين صغيرابيض مذهب | D17: 2 | E17: 250 | F17: 500 | G17: شركة حسين علي | H17: 500 | I17: ORD-1773525728614-154 | J17: Added 2 to stock (orderId:ORD-1773525728614-154) | K17: abdofwzy9@gmail.com
A18: 46096.001 | B18: Purchase | C18: فازة بورسلين وسط ابيض مذهب | D18: 2 | E18: 300 | F18: 600 | G18: شركة حسين علي | H18: 499 | I18: ORD-1773525728606-696 | J18: Added 2 to stock (orderId:ORD-1773525728606-696) | K18: abdofwzy9@gmail.com
A19: 46096.001 | B19: Purchase | C19: فازة بورسلين كبيرة ابيض مذهب | D19: 3 | E19: 400 | F19: 1200 | G19: شركة حسين علي | H19: 498 | J19: Added 3 to stock (orderId:) | K19: abdofwzy9@gmail.com
A20: 46150.729 | B20: Mfg-In | C20: بروبلين 5سم عبدالله | D20: 35 | E20: 3.5 | H20: 122.5 | J20: شركة حسين علي | K20: مقزم-قرنفل | L20: Used | M20: abdofwzy9@gmail.com
A21: 46066.906 | B21: Manufacturing-Output | C21: مقزم قرنفل | D21: 4 | E21: 10 | H21: 40 | J21: manufactured | K21: مقزم-قرنفل | L21: Product manufactured | M21: abdofwzy9@gmail.com
A22: 46066.906 | B22: Manufacturing-Input | C22: بوت صغير مقزمات | D22: 1 | E22: 10 | H22: 10 | J22: شركة حسين علي | K22: مقزم-قرنفل | L22: Used in manufacturing | M22: abdofwzy9@gmail.com
A23: 46066.906 | B23: Manufacturing-Input | C23: بوكية قرنفل | D23: 1 | E23: 30 | H23: 30 | J23: شركة حسين علي | K23: مقزم-قرنفل | L23: Used in manufacturing | M23: abdofwzy9@gmail.com
A24: 46150.729 | B24: Mfg-In | C24: قرنفل 2 | D24: 5 | E24: 30 | H24: 150 | J24: شركة حسين علي | K24: مقزم-قرنفل | L24: Used | M24: abdofwzy9@gmail.com
A25: 46172.911 | B25: Sale | C25: علبة مناديل كريستال خلص | D25: 1 | E25: 170 | F25: 200 | G25: 200 | H25: 200 | I25: 30 | J25: شركة الهضبة | K25: 1433 | L25: Sold (saleId:SAL-1780167096171-913) | M25: abdofwzy9@gmail.com
A26: 46083.001 | B26: Manufacturing-Output | C26: مقزم وردة حمرا قطيفة | D26: 7 | E26: 30 | H26: 210 | J26: manufactured | K26: مقزم-احمر-قطيفة | L26: Product manufactured | M26: abdofwzy9@gmail.com
A27: 46083.001 | B27: Manufacturing-Input | C27: بوت صغير مقزمات | D27: 7 | E27: 10 | H27: 70 | K27: مقزم-احمر-قطيفة | L27: Used in manufacturing | M27: abdofwzy9@gmail.com
A28: 46083.001 | B28: Manufacturing-Input | C28: بلدي قطيفة 7 فرع | D28: 1 | E28: 140 | H28: 140 | J28: شركة الفرسان | K28: مقزم-احمر-قطيفة | L28: Used in manufacturing | M28: abdofwzy9@gmail.com
A29: 46082.999 | B29: Manufacturing-Output | C29: مقزم وردة حمرا قطيفة | D29: 7 | E29: 20 | H29: 140 | J29: manufactured | K29: مقزم-احمر-قطيفة | L29: Product manufactured | M29: abdofwzy9@gmail.com
A30: 46082.999 | B30: Manufacturing-Input | C30: بلدي قطيفة 7 فرع | D30: 1 | E30: 140 | H30: 140 | J30: شركة الفرسان | K30: مقزم-احمر-قطيفة | L30: Used in manufacturing | M30: abdofwzy9@gmail.com
A31: 46082.997 | B31: Manufacturing-Output | C31: مقزم وردة حمرا قطيفة | D31: 7 | E31: 20 | H31: 140 | J31: manufactured | K31: مقزم-احمر-قطيفة | L31: Product manufactured | M31: abdofwzy9@gmail.com
A32: 46082.997 | B32: Manufacturing-Input | C32: بلدي قطيفة 7 فرع | D32: 1 | E32: 140 | H32: 140 | J32: شركة الفرسان | K32: مقزم-احمر-قطيفة | L32: Used in manufacturing | M32: abdofwzy9@gmail.com
A33: 46172.911 | B33: Sale | C33: بوكيه اربع وردات قطيفة | D33: 1 | E33: 56.666667 | F33: 70 | G33: 70 | H33: 70 | I33: 13.33 | J33: manufactured | K33: 1387 | L33: Sold (saleId:SAL-1780167096148-284) | M33: abdofwzy9@gmail.com
A34: 46075.022 | B34: Manufacturing-Output | C34: شجرة ياسمين 80سم | D34: 1 | E34: 315 | H34: 315 | J34: manufactured | K34: شجرة-ياسمين | L34: Product manufactured | M34: abdofwzy9@gmail.com
A35: 46075.022 | B35: Manufacturing-Input | C35: بوت وسط فاضي | D35: 1 | E35: 35 | H35: 35 | J35: عبدالفتاح | K35: شجرة-ياسمين | L35: Used in manufacturing | M35: abdofwzy9@gmail.com
A36: 46075.022 | B36: Manufacturing-Input | C36: قصرية 16سم | D36: 1 | E36: 5 | H36: 5 | J36: عبدالفتاح | K36: شجرة-ياسمين | L36: Used in manufacturing | M36: abdofwzy9@gmail.com
A37: 46075.022 | B37: Manufacturing-Input | C37: جزع 80 سم | D37: 1 | E37: 20 | H37: 20 | J37: عبدالفتاح | K37: شجرة-ياسمين | L37: Used in manufacturing | M37: abdofwzy9@gmail.com
A38: 46075.022 | B38: Manufacturing-Input | C38: ياسمين جيرمينجامبو | D38: 3 | E38: 85 | H38: 255 | J38: شركة الفرسان | K38: شجرة-ياسمين | L38: Used in manufacturing | M38: abdofwzy9@gmail.com
A39: 46172.911 | B39: Sale | C39: ورد ديكور محمد رشدي | D39: 2 | E39: 103 | F39: 150 | G39: 150 | H39: 300 | I39: 94 | J39: سنتر محمد رشدي | K39: 1380 | L39: Sold (saleId:SAL-1780167096123-816) | M39: abdofwzy9@gmail.com
A40: 46172.911 | B40: Sale | C40: طقم دوناتس | D40: 1 | E40: 110 | F40: 160 | G40: 160 | H40: 160 | I40: 50 | J40: شركة حسين علي | K40: 1373 | L40: Sold (saleId:SAL-1780167096100-996) | M40: abdofwzy9@gmail.com
A41: 46074.018 | B41: Purchase | C41: دابل فيس 18م | D41: 12 | E41: 28 | F41: 336 | H41: 447 | I41: ORD-1771626318054-237 | J41: Added 12 to stock (orderId:ORD-1771626318054-237) | K41: abdofwzy9@gmail.com
A42: 46074.018 | B42: Purchase | C42: دابل فيس 14م | D42: 12 | E42: 20 | F42: 240 | H42: 446 | I42: ORD-1771626318049-306 | J42: Added 12 to stock (orderId:ORD-1771626318049-306) | K42: abdofwzy9@gmail.com
A43: 46074.018 | B43: Purchase | C43: دابل فيس 12م | D43: 12 | E43: 15 | F43: 180 | H43: 445 | I43: ORD-1771626318044-937 | J43: Added 12 to stock (orderId:ORD-1771626318044-937) | K43: abdofwzy9@gmail.com
A44: 46074.018 | B44: Purchase | C44: بوت صغير | D44: 24 | E44: 20 | F44: 480 | H44: 444 | I44: ORD-1771626318039-215 | J44: Added 24 to stock (orderId:ORD-1771626318039-215) | K44: abdofwzy9@gmail.com
A45: 46074.018 | B45: Purchase | C45: بوت صغير مقزمات | D45: 24 | E45: 10 | F45: 240 | H45: 443 | I45: ORD-1771626318033-383 | J45: Added 24 to stock (orderId:ORD-1771626318033-383) | K45: abdofwzy9@gmail.com
A46: 46074.018 | B46: Purchase | C46: حجر ساعة | D46: 40 | E46: 11 | F46: 440 | H46: 442 | I46: ORD-1771626318026-930 | J46: Added 40 to stock (orderId:ORD-1771626318026-930) | K46: abdofwzy9@gmail.com
A47: 46074.018 | B47: Purchase | C47: حجر ريموت | D47: 40 | E47: 3.25 | F47: 130 | H47: 441 | J47: Added 40 to stock (orderId:) | K47: abdofwzy9@gmail.com
A48: 46073.872 | B48: Manufacturing-Output | C48: مقزم شجر | D48: 3 | E48: 15.166667 | H48: 45.5 | J48: manufactured | K48: مقزم-شجر | L48: Product manufactured | M48: abdofwzy9@gmail.com
A49: 46073.872 | B49: Manufacturing-Output | C49: بوت صغير | D49: 1 | E49: 19.5 | H49: 19.5 | J49: manufactured | K49: مقزم-شجر | L49: Product manufactured | M49: abdofwzy9@gmail.com
A50: 46073.872 | B50: Manufacturing-Input | C50: شجرة صغيرة 3d | D50: 1 | E50: 65 | H50: 65 | J50: ذكريا | K50: مقزم-شجر | L50: Used in manufacturing | M50: abdofwzy9@gmail.com
A51: 46172.911 | B51: Sale | C51: علبة مناديل كريستال | D51: 1 | E51: 178.75 | F51: 250 | G51: 250 | H51: 250 | I51: 71.25 | J51: شركة حسين علي | K51: 1370 | L51: Sold (saleId:SAL-1780167096062-770) | M51: abdofwzy9@gmail.com
A52: 46172.911 | B52: Sale | C52: شجرة مانغوليا 80 سم | D52: 1 | E52: 103.75 | F52: 200 | G52: 200 | H52: 200 | I52: 96.25 | J52: manufactured | K52: 1352 | L52: Sold (saleId:SAL-1780167096024-241) | M52: abdofwzy9@gmail.com
A53: 46172.911 | B53: Sale | C53: بوت بشريطة دهبي حسين علي | D53: 1 | E53: 100 | F53: 150 | G53: 150 | H53: 150 | I53: 50 | J53: شركة حسين علي | K53: 1127 | L53: Sold (saleId:SAL-1780167095988-611) | M53: abdofwzy9@gmail.com
A54: 46172.911 | B54: Sale | C54: ورد ديكور محمد رشدي | D54: 4 | E54: 103 | F54: 150 | G54: 150 | H54: 600 | I54: 188 | J54: سنتر محمد رشدي | K54: 1116 | L54: Sold (saleId:SAL-1780167095949-602) | M54: abdofwzy9@gmail.com
A55: 46172.911 | B55: Sale | C55: بخور ميسوس كيس | D55: 2 | E55: 11.25 | F55: 20 | G55: 20 | H55: 40 | I55: 17.5 | J55: سنتر محمد رشدي | K55: 1103 | L55: Sold (saleId:SAL-1780167095912-461) | M55: abdofwzy9@gmail.com
A56: 46172.911 | B56: Sale | C56: طقم دوناتس | D56: 1 | E56: 110 | F56: 220 | G56: 220 | H56: 220 | I56: 110 | J56: شركة حسين علي | K56: 1092 | L56: Sold (saleId:SAL-1780167095878-806) | M56: abdofwzy9@gmail.com
A57: 46172.911 | B57: Sale | C57: بوكيه بلاسيتك وورد احمر صغير | D57: 1 | E57: 110 | F57: 170 | G57: 170 | H57: 170 | I57: 60 | J57: ذكريا | K57: 321 | L57: Sold (saleId:SAL-1780167095835-176) | M57: abdofwzy9@gmail.com
A58: 46172.9 | B58: Sale | C58: طقم عربيات 6ق 575/1 | D58: 1 | E58: 65 | F58: 110 | G58: 110 | H58: 110 | I58: 45 | J58: سنتر محمد رشدي | K58: 1438 | L58: Sold (saleId:SAL-1780166130792-557) | M58: abdofwzy9@gmail.com
A59: 46172.9 | B59: Sale | C59: بندق 5 فرع زهرة sf-86 | D59: 0.6 | E59: 55 | F59: 50 | G59: 50 | H59: 30 | I59: -3 | J59: شركة الفرسان للاستيراد والتصدير | K59: 1437 | L59: Sold (saleId:SAL-1780166130772-785) | M59: abdofwzy9@gmail.com
A60: 46060.795 | B60: Purchase | C60: تابلوه دائري | D60: 5 | E60: 50 | F60: 250 | G60: سنتر محمد رشدي | H60: 381 | J60: Added 5 to stock (orderId:) | K60: abdofwzy9@gmail.com
A61: 46172.9 | B61: Sale | C61: مروحة يد 339/3 | D61: 1 | E61: 17.92 | F61: 30 | G61: 30 | H61: 30 | I61: 12.08 | J61: سنتر محمد رشدي | K61: 1436 | L61: Sold (saleId:SAL-1780166130752-605) | M61: abdofwzy9@gmail.com
A62: 46172.9 | B62: Sale | C62: بوت صغير فاضي | D62: 1 | E62: 20 | F62: 50 | G62: 50 | H62: 50 | I62: 30 | J62: شركة حسين علي | K62: 1435 | L62: Sold (saleId:SAL-1780166130727-591) | M62: abdofwzy9@gmail.com
A63: 46172.9 | B63: Sale | C63: 12 اواس علاء شاكر | D63: 1 | E63: 70 | F63: 150 | G63: 150 | H63: 150 | I63: 80 | J63: شركة علاء شاكر | K63: 1434 | L63: Sold (saleId:SAL-1780166130693-842) | M63: abdofwzy9@gmail.com
A64: 46172.9 | B64: Sale | C64: خضرة حشو 12 | D64: 0.16666667 | E64: 50 | F64: 90 | G64: 90 | H64: 15 | I64: 6.67 | J64: شركة حسين علي | K64: 1432 | L64: Sold (saleId:SAL-1780166130656-471) | M64: abdofwzy9@gmail.com
A65: 46172.9 | B65: Sale | C65: خضرة اللوان 18 | D65: 0.22222222 | E65: 110 | F65: 180 | G65: 180 | H65: 40 | I65: 15.56 | J65: شركة الفرسان | K65: 1431 | L65: Sold (saleId:SAL-1780166130634-293) | M65: abdofwzy9@gmail.com
A66: 46172.9 | B66: Sale | C66: بندق 5 فرع زهرة sf-86 | D66: 1 | E66: 55 | F66: 75 | G66: 75 | H66: 75 | I66: 20 | J66: شركة الفرسان للاستيراد والتصدير | K66: 1430 | L66: Sold (saleId:SAL-1780166130603-256) | M66: abdofwzy9@gmail.com
A67: 46058.82 | B67: Purchase | C67: بخور انسام ساعتين ونص | D67: 12 | E67: 34.166667 | F67: 410 | H67: 380 | I67: ORD-1770313281039-441 | J67: Added 12 to stock (orderId:ORD-1770313281039-441) | K67: abdofwzy9@gmail.com
A68: 46058.82 | B68: Purchase | C68: بخور انسام 5 ساعات | D68: 24 | E68: 53.333333 | F68: 1280 | H68: 379 | I68: ORD-1770313281024-204 | J68: Added 24 to stock (orderId:ORD-1770313281024-204) | K68: abdofwzy9@gmail.com
A69: 46058.82 | B69: Purchase | C69: علبة بخور المدينة | D69: 12 | E69: 23.333333 | F69: 280 | H69: 378 | I69: ORD-1770313280986-491 | J69: Added 12 to stock (orderId:ORD-1770313280986-491) | K69: abdofwzy9@gmail.com
A70: 46058.82 | B70: Purchase | C70: سيريا ستارة شخصيات وورم | D70: 3 | E70: 225 | F70: 675 | G70: سنتر محمد رشدي | H70: 377 | J70: Added 3 to stock (orderId:) | K70: abdofwzy9@gmail.com
A71: 46172.9 | B71: Sale | C71: بوت صغير فاضي | D71: 1 | E71: 20 | F71: 35 | G71: 35 | H71: 35 | I71: 15 | J71: شركة حسين علي | K71: 1429 | L71: Sold (saleId:SAL-1780166130551-171) | M71: abdofwzy9@gmail.com
A72: 46172.9 | B72: Sale | C72: بوكيه جيبس فيل | D72: 0.33333333 | E72: 65 | F72: 90 | G72: 90 | H72: 30 | I72: 8.33 | J72: شركة حسين علي | K72: 1428 | L72: Sold (saleId:SAL-1780166130516-454) | M72: abdofwzy9@gmail.com
A73: 46090.942 | B73: Manufacturing-Output | C73: مقزم شجر | D73: 6 | E73: 11.416667 | H73: 68.5 | J73: manufactured | K73: تصنيع-مقزم-شجر | L73: Product manufactured | M73: abdofwzy9@gmail.com
A74: 46090.942 | B74: Manufacturing-Input | C74: قصرية مقزمات 8سم | D74: 6 | E74: 6 | H74: 36 | J74: المهندس | K74: تصنيع-مقزم-شجر | L74: Used in manufacturing | M74: abdofwzy9@gmail.com
A75: 46090.942 | B75: Manufacturing-Input | C75: بنجمينا أخضر ساده | D75: 0.5 | E75: 65 | H75: 32.5 | J75: شركة الفرسان | K75: تصنيع-مقزم-شجر | L75: Used in manufacturing | M75: abdofwzy9@gmail.com
A76: 46090.939 | B76: Manufacturing-Output | C76: مقزم شجر | D76: 6 | E76: 5.4166667 | H76: 32.5 | J76: manufactured | K76: تصنيع-مزرعة | L76: Product manufactured | M76: abdofwzy9@gmail.com
A77: 46090.939 | B77: Manufacturing-Input | C77: بنجمينا أخضر ساده | D77: 0.5 | E77: 65 | H77: 32.5 | J77: شركة الفرسان | K77: تصنيع-مزرعة | L77: Used in manufacturing | M77: abdofwzy9@gmail.com
A78: 46172.9 | B78: Sale | C78: لليام 9 فرع | D78: 1 | E78: 125 | F78: 155 | G78: 155 | H78: 155 | I78: 30 | J78: شركة الفرسان | K78: 1427 | L78: Sold (saleId:SAL-1780166130479-183) | M78: abdofwzy9@gmail.com
A79: 46172.9 | B79: Sale | C79: دستة ورق بنجمينا | D79: 0.5 | E79: 75 | F79: 160 | G79: 160 | H79: 80 | I79: 42.5 | J79: شركة علاء شاكر | K79: 1426 | L79: Sold (saleId:SAL-1780166130443-421) | M79: abdofwzy9@gmail.com
A80: 46172.9 | B80: Sale | C80: بوت صغير فاضي | D80: 2 | E80: 20 | F80: 50 | G80: 50 | H80: 100 | I80: 60 | J80: شركة حسين علي | K80: 1425 | L80: Sold (saleId:SAL-1780166130409-570) | M80: abdofwzy9@gmail.com
A81: 46172.9 | B81: Sale | C81: مروحة يد 339/3 | D81: 2 | E81: 17.92 | F81: 30 | G81: 30 | H81: 60 | I81: 24.16 | J81: سنتر محمد رشدي | K81: 1424 | L81: Sold (saleId:SAL-1780166130372-878) | M81: abdofwzy9@gmail.com
A82: 46172.9 | B82: Sale | C82: بوت تركي كبير | D82: 1 | E82: 65 | F82: 75 | G82: 75 | H82: 75 | I82: 10 | J82: عبدالفتاح | K82: 1423 | L82: Sold (saleId:SAL-1780166130338-682) | M82: abdofwzy9@gmail.com
A83: 46172.9 | B83: Sale | C83: شجرة موزة جلد 9 ورقة فردي 40×10 اسم | D83: 1 | E83: 300 | F83: 375 | G83: 375 | H83: 375 | I83: 75 | J83: شركة الفرسان | K83: 1422 | L83: Sold (saleId:SAL-1780166130304-713) | M83: abdofwzy9@gmail.com
A84: 46172.9 | B84: Sale | C84: فرع زرع | D84: 4 | E84: 9.17 | F84: 20 | G84: 20 | H84: 80 | I84: 43.32 | J84: شركة الفرسان | K84: 1421 | L84: Sold (saleId:SAL-1780166130284-588) | M84: abdofwzy9@gmail.com
A85: 46172.9 | B85: Sale | C85: تقيلة زجاج 615/2 | D85: 1 | E85: 88 | F85: 135 | G85: 135 | H85: 135 | I85: 47 | J85: محمد رشدي | K85: 1420 | L85: Sold (saleId:SAL-1780166130259-308) | M85: abdofwzy9@gmail.com
A86: 46172.9 | B86: Sale | C86: اباجورة شكل 0 | D86: 1 | E86: 120 | F86: 170 | G86: 170 | H86: 170 | I86: 50 | J86: شركة البطل | K86: 1419 | L86: Sold (saleId:SAL-1780166130236-887) | M86: abdofwzy9@gmail.com
A87: 46172.9 | B87: Sale | C87: ديكور معدن 6450/1 | D87: 1 | E87: 290 | F87: 400 | G87: 400 | H87: 400 | I87: 110 | J87: سنتر محمد رشدي | K87: 1418 | L87: Sold (saleId:SAL-1780166130209-872) | M87: abdofwzy9@gmail.com
A88: 46172.9 | B88: Sale | C88: خضرة اللوان 18 | D88: 0.22222222 | E88: 110 | F88: 180 | G88: 180 | H88: 40 | I88: 15.56 | J88: شركة الفرسان | K88: 1417 | L88: Sold (saleId:SAL-1780166130175-866) | M88: abdofwzy9@gmail.com
A89: 46172.9 | B89: Sale | C89: ريشة دوناتس | D89: 4 | E89: 15 | F89: 20 | G89: 20 | H89: 80 | I89: 20 | J89: شركة حسين علي | K89: 1416 | L89: Sold (saleId:SAL-1780166130148-172) | M89: abdofwzy9@gmail.com
... A94: 46172.9 | B94: Sale | C94: ريشة دوناتس | D94: 4 | E94: 15 | F94: 20 | G94: 20 | H94: 80 | I94: 20 | J94: شركة حسين علي | K94: 1411 | L94: Sold (saleId:SAL-1780166130025-622) | M94: abdofwzy9@gmail.com
A95: 46053.702 | B95: Manufacturing-Output | C95: ريش | D95: 12 | E95: 7.0833333 | H95: 85 | J95: manufactured | K95: ريش-بورد | L95: Product manufactured | M95: abdofwzy9@gmail.com
A96: 46053.702 | B96: Manufacturing-Input | C96: ريش بورد | D96: 1 | E96: 85 | H96: 85 | J96: ذكريا | K96: ريش-بورد | L96: Used in manufacturing | M96: abdofwzy9@gmail.com
A97: 46172.9 | B97: Sale | C97: توليب 24 حسين علي | D97: 1 | E97: 150 | F97: 190 | G97: 190 | H97: 190 | I97: 40 | J97: شركة حسين علي | K97: 1410 | L97: Sold (saleId:SAL-1780166129997-747) | M97: abdofwzy9@gmail.com
A98: 46172.9 | B98: Sale | C98: فازة بورسلين | D98: 1 | E98: 195 | F98: 250 | G98: 250 | H98: 250 | I98: 55 | J98: ذكريا | K98: 1409 | L98: Sold (saleId:SAL-1780166129973-217) | M98: abdofwzy9@gmail.com
A99: 46172.9 | B99: Sale | C99: قصرية 25سم | D99: 3 | E99: 10 | F99: 25 | G99: 25 | H99: 75 | I99: 45 | J99: المهندس | K99: 1408 | L99: Sold (saleId:SAL-1780166129953-583) | M99: abdofwzy9@gmail.com
A100: 46172.9 | B100: Sale | C100: بوت صغير مقزمات حسين علي | D100: 1 | E100: 12.11 | F100: 30 | G100: 30 | H100: 30 | I100: 17.89 | J100: شركة حسين علي | K100: 1407 | L100: Sold (saleId:SAL-1780166129932-975) | M100: abdofwzy9@gmail.com
A101: 46172.9 | B101: Sale | C101: بوكية قرنفل | D101: 1 | E101: 30 | F101: 70 | G101: 70 | H101: 70 | I101: 40 | J101: شركة حسين علي | K101: 1406 | L101: Sold (saleId:SAL-1780166129905-860) | M101: abdofwzy9@gmail.com
A102: 46172.9 | B102: Sale | C102: بوت صغير فاضي | D102: 1 | E102: 20 | F102: 50 | G102: 50 | H102: 50 | I102: 30 | J102: شركة حسين علي | K102: 1405 | L102: Sold (saleId:SAL-1780166129877-474) | M102: abdofwzy9@gmail.com
A103: 46172.9 | B103: Sale | C103: شجرة جاهزة | D103: 1 | E103: 84 | F103: 100 | G103: 100 | H103: 100 | I103: 16 | J103: ذكريا | K103: 1404 | L103: Sold (saleId:SAL-1780166129856-652) | M103: abdofwzy9@gmail.com
A104: 46172.9 | B104: Sale | C104: بوت صغير مقزمات حسين علي | D104: 1 | E104: 12.11 | F104: 20 | G104: 20 | H104: 20 | I104: 7.89 | J104: شركة حسين علي | K104: 1403 | L104: Sold (saleId:SAL-1780166129834-601) | M104: abdofwzy9@gmail.com
A105: 46172.9 | B105: Sale | C105: بندق 5 فرع زهرة sf-86 | D105: 1 | E105: 55 | F105: 60 | G105: 60 | H105: 60 | I105: 5 | J105: شركة الفرسان للاستيراد والتصدير | K105: 1402 | L105: Sold (saleId:SAL-1780166129812-645) | M105: abdofwzy9@gmail.com
A106: 46172.9 | B106: Sale | C106: برواز ثلاثي شعبي | D106: 1 | E106: 90 | F106: 140 | G106: 140 | H106: 140 | I106: 50 | J106: شركة الفرسان للاستيراد والتصدير | K106: 1401 | L106: Sold (saleId:SAL-1780166129790-918) | M106: abdofwzy9@gmail.com
...

Sheet SystemStatus
A1: Date | B1: Process | C1: Message | D1: Count
A2: 45997.557 | B2: Orders | C2: Processed orders into stock | D2: 243
A3: 45997.577 | B3: Sales | C3: Processed sales | D3: 157
A4: 45997.577 | B4: Sales | C4: Warnings: Not enough stock for بوكيه بلاستيك ورد مقفول وورد صغير. Required: 1, Available: 0 (sale row: 18) | Not enough stock for فازة خزف وورد احمر صغير. Required: 2, Available: 0 (sale row: 19) | Not enough stock for بوكيه خزف مقسوم ورد شبه التاج. Required: 1, Available: 0 (sale row: 79) | Not enough stock for بوكيه ورد احمر صغير واخضر. Required: 1, Available: 0 (sale row: 108) | Not enough stock for بوكيه بلاستيك و ريش واخضر عرايس:). Required: 1, Available: 0 (sale row: 109) | D4: 12
A5: 45997.58 | B5: Sales | C5: Processed sales | D5: 0
A6: 45997.58 | B6: Sales | C6: Warnings: Not enough stock for بوكيه بلاستيك ورد مقفول وورد صغير. Required: 1, Available: 0 (sale row: 18) | Not enough stock for فازة خزف وورد احمر صغير. Required: 2, Available: 0 (sale row: 19) | Not enough stock for بوكيه خزف مقسوم ورد شبه التاج. Required: 1, Available: 0 (sale row: 79) | Not enough stock for بوكيه ورد احمر صغير واخضر. Required: 1, Available: 0 (sale row: 108) | Not enough stock for بوكيه بلاستيك و ريش واخضر عرايس:). Required: 1, Available: 0 (sale row: 109) | D6: 12
A7: 45997.583 | B7: Sales | C7: Processed sales | D7: 5
A8: 45997.583 | B8: Sales | C8: Warnings: Not enough stock for بوكيه بلاستيك ورد مقفول وورد صغير. Required: 1, Available: 0 (sale row: 18) | Not enough stock for فازة خزف وورد احمر صغير. Required: 2, Available: 0 (sale row: 19) | Not enough stock for بوكيه خزف مقسوم ورد شبه التاج. Required: 1, Available: 0 (sale row: 79) | Not enough stock for بوكيه ورد احمر صغير واخضر. Required: 1, Available: 0 (sale row: 108) | Not enough stock for بوكيه بلاستيك و ريش واخضر عرايس:). Required: 1, Available: 0 (sale row: 109) | D8: 7
A9: 45997.986 | B9: Orders | C9: Processed orders into stock | D9: 243
A10: 45997.987 | B10: Sales | C10: Processed sales | D10: 158
A11: 45997.987 | B11: Sales | C11: Warnings: Not enough stock for فازة خزف وورد احمر صغير. Required: 2, Available: 0 (sale row: 19) | No stock entry for شجرة ورق عريض قماش | | (sale row: 23) | No stock entry for شجرة تركيب 18 ورقة | | (sale row: 68) | Not enough stock for بوكيه خزف مقسوم ورد شبه التاج. Required: 1, Available: 0 (sale row: 79) | No stock entry for شجرة تركيب 18 ورقة | | (sale row: 89) | D11: 11
A12: 45997.99 | B12: Sales | C12: Processed sales | D12: 6
A13: 45997.99 | B13: Sales | C13: Warnings: Not enough stock for فازة خزف وورد احمر صغير. Required: 2, Available: 0 (sale row: 19) | No stock entry for شجرة ورق عريض قماش | | (sale row: 23) | No stock entry for شجرة تركيب 18 ورقة | | (sale row: 68) | Not enough stock for بوكيه خزف مقسوم ورد شبه التاج. Required: 1, Available: 0 (sale row: 79) | No stock entry for شجرة تركيب 18 ورقة | | (sale row: 89) | D13: 12
... A330: 46172.913 | B330: Sales | C330: Warnings: Not enough stock for فازة خزف وورد احمر صغير. Required: 2, Available: 0 (sale row: 19) | Not enough stock for بوكيه خزف مقسوم ورد شبه التاج. Required: 1, Available: 0 (sale row: 79) | Not enough stock for بوكيه ورد احمر صغير واخضر. Required: 1, Available: 0 (sale row: 108) | Not enough stock for بوكيه بلاستيك و ريش واخضر عرايس:). Required: 1, Available: 0 (sale row: 109) | Not enough stock for كريستالة ديكور. Required: 2, Available: 0 (sale row: 148) | D330: 12

Sheet Inventory_Report
A1: name | B1: supplier | C1: price | D1: totalQuantity | E1: count | F1: ignore
A2: XO وسط 1121 | B2: سنتر محمد رشدي | C2: 19 | D2: 1
A3: آلة حاسبة 656/120 (عرض) | B3: سنتر محمد رشدي | C3: 155 | D3: 1
A4: أباجورة USB تاتش - 359 | B4: سنتر محمد رشدي | C4: 155 | D4: 1
A5: أباجورة يو اس بي 77/34/2 | B5: سنتر محمد رشدي | C5: 125 | D5: 8
A6: اباجورة USB تاتش 734/26 | B6: سنتر محمد رشدي | C6: 130 | D6: 1
A7: اباجورة شكل 0 | B7: شركة البطل | C7: 140 | D7: 5
A8: اسبايدر مان 5396 | B8: محمد رشدي | C8: 115 | D8: 2
A9: اشكال السيرفرات | B9: ذكريا | C9: 120 | D9: 4
A10: اشكال سيلفرات اقل | B10: ذكريا | C10: 95 | D10: 2
A11: افرع طويلة | B11: ذكريا | C11: 75 | D11: 29
A12: افرع هيش | B12: ذكريا | C12: 50 | D12: 5
A13: بازل شكل 2 ق 100 – 069/1 | B13: سنتر محمد رشدي | C13: 82 | D13: 1
... A19: بالون مطبوع هابي 1507/12 | B19: محمد رشدي | C19: 6.67 | D19: 12
A20: بخور انسام 5 ساعات | C20: 53.33 | D20: 17.2
A21: بخور انسام ساعتين ونص | C21: 34.17 | D21: 12
A22: بخور فحم بالقطعة 0411/12 | B22: سنتر محمد رشدي | C22: 17.5 | D22: 20
A23: بخور ميسوس كيس | B23: سنتر محمد رشدي | C23: 11.25 | D23: 46
A24: برج إيفل 15CM | B24: سنتر محمد رشدي | C24: 29 | D24: 3
A25: برواز ثلاثي دهبي صغير | B25: شركة الفرسان | C25: 75 | D25: 4
A26: برواز ثلاثي شعبي ك | B26: شركة الفرسان | C26: 85 | D26: 4
A27: برواز ثلاثي وسط | B27: شركة الفرسان | C27: 75 | D27: 9
A28: برواز فردي | B28: شركة الفرسان | C28: 50 | D28: 12
A29: برواز ورد دهبي ثلاثي | B29: شركة الفرسان | C29: 175 | D29: 3
A30: بروبلين 10 سم | B30: شركة الفرسان | C30: 10 | D30: 3
A31: بروبلين 14 سم | B31: شركة الفرسان | C31: 20 | D31: 9
A32: بروبلين 5سم | B32: المهندس | C32: 5 | D32: 18
A33: بروبلين 5سم عبدالله | B33: شركة حسين علي | C33: 3.5 | D33: 195
... A52: بوت جامبو طويل | B52: عبدالفتاح | C52: 175 | D52: 10
A53: بوت صغير | C53: 20 | D53: 24
A54: بوت صغير | B54: manufactured | C54: 22.75 | D54: 3
A55: بوت صغير فاضي | B55: شركة حسين علي | C55: 20 | D55: 1
A56: بوت صغير مقزمات | C56: 10 | D56: 6
A57: بوت صغير مقزمات | B57: شركة حسين علي | C57: 11.82 | D57: 40
A58: بوت صغير هااند ميد و 2 بوكيه | B58: ذكريا | C58: 235 | D58: 1
A59: بوت طويل مستطيل فاضي | B59: ذكريا | C59: 85 | D59: 3
A60: بوت كبير عادي | B60: ذكريا | C60: 135 | D60: 21
A61: بوت مستطيل بكسر رخام | B61: ذكريا | C61: 160 | D61: 2
A62: بوت هاند ميد كبير | B62: ذكريا | C62: 425 | D62: 2
A63: بوت وسط | B63: ذكريا | C63: 89.07 | D63: 17
A64: بوت وسط فاضي | B64: عبدالفتاح | C64: 35 | D64: 126
A65: بوكية احمر قطيفة | B65: manufactured | C65: 168.33333 | D65: 1
A66: بوكية قرنفل | B66: شركة حسين علي | C66: 30 | D66: 0.14285714
A67: بوكية قرنفل | B67: شركة حسين علي | C67: 30 | D67: 24
A68: بوكيه ورد صغير | B68: ذكريا | C68: 115 | D68: 1
... A75: بوكيه بلاستيك وبوكيه اخضر | B75: ذكريا | C75: 140 | D75: 2
A76: بوكيه بلاستيك و ريش واخضر عرايس:) | C76: 290 | D76: 1
A77: بوكيه بلاستيك و ورد بني وصغير | B77: ذكريا | C77: 135 | D77: 1
A78: بوكيه بلاستيك واتنين صغيرين | B78: ذكريا | C78: 125 | D78: 1
A79: بوكيه بلاستيك وورد مقفول | B79: ذكريا | C79: 110 | D79: 2
A80: بوكيه بلاسيتك وورد مسك الليل | B80: ذكريا | C80: 112.5 | D80: 1
A81: بوكيه جلد | B81: ذكريا | C81: 75 | D81: 3.8
A82: بوكيه جيبس فل | B82: ذكريا | C82: 30 | D82: 6
A83: بوكيه جيبس فيل | B83: شركة حسين علي | C83: 65 | D83: 2
A84: بوكيه خزف | B84: ذكريا | C84: 140 | D84: 1
A85: بوكيه خزف صغير | B85: ذكريا | C85: 130 | D85: 2
A86: بوكيه دوار شمس | B86: ذكريا | C86: 105 | D86: 1
A87: بوكيه ريش حمام | B87: ذكريا | C87: 135 | D87: 2
A88: بوكيه زهرة الياسمين | B88: ذكريا | C88: 125 | D88: 1
... A125: جليتر بورنيطة 010444/53 | B125: محمد رشدي | C125: 18 | D125: 24
A126: حجر ريموت | C126: 3.25 | D126: 38
A127: حجر ساعة | C127: 11 | D127: 30
A128: حجر قلم جاز (عرض خاص) - 459/3 | B128: سنتر محمد رشدي | C128: 11 | D128: 35
A129: حجر قلم جاز (عرض خاص) - 459/3 | B129: محمد رشدي | C129: 12.5 | D129: 20
A130: حصان 5309 | B130: محمد رشدي | C130: 55 | D130: 5
A131: خضرا حشو | B131: المهندس | C131: 55 | D131: 1
A132: خضرة اللوان 18 | B132: شركة الفرسان | C132: 110 | D132: 3.5
A133: خضرة حشو 12 | B133: شركة حسين علي | C133: 50 | D133: 10.5
A134: خضره 24 كلة | B134: شركة الفرسان | C134: 125 | D134: 4
A135: خضره اشابيه 7 فرع | B135: شركة الفرسان | C135: 35 | D135: 12
A136: دابل فيس 12م | C136: 15 | D136: 8
A137: دابل فيس 14م | C137: 20 | D137: 10
A138: دابل فيس 18م | C138: 28 | D138: 10
A139: دبدوب 6135 | B139: محمد رشدي | C139: 60 | D139: 2
A140: دستة بلاستيك ماسك | B140: محمد رشدي | C140: 1.92 | D140: 84
A141: دستة مانجوليا الفرسان | B141: الفرسان | C141: 180 | D141: 4
A142: دستة ورق بنجمينا | B142: عبدالفتاح | C142: 65 | D142: 2
A143: دستة ورق بنجمينا ابيض | B143: شركة الفرسان | C143: 65 | D143: 2
A144: دستة ورق بنجمينا فلفل | B144: شركة الفرسان | C144: 225 | D144: 1
A145: دستة ورق خروع الوان | B145: شركة الفرسان | C145: 250 | D145: 1
A146: دستة ورق نعناع | B146: شركة الفرسان | C146: 250 | D146: 1
A147: دلاية صلي على النبي 336/09 | B147: محمد رشدي | C147: 8 | D147: 2
A148: دوناتس ثلاثي | B148: شركة حسين علي | C148: 120 | D148: 5
A149: دوناتس ثنائي | B149: شركة حسين علي | C149: 150 | D149: 6
A150: ديكور بالنور 60/8 | B150: سنتر محمد رشدي | C150: 110 | D150: 3
... A171: ريش | B171: manufactured | C171: 7.0833333 | D171: 3
A172: ريش ازرق | C172: 135 | D172: 1
A173: ريش بورد | B173: ذكريا | C173: 85 | D173: 3
A174: ريش دوناتس | B174: شركة حسين علي | C174: 15 | D174: 9
A175: ريش مكثف | B175: شركة حسين علي | C175: 17 | D175: 4
A176: ريشة دوناتس | B176: شركة حسين علي | C176: 15 | D176: 57
A177: زياتة | B177: شركة الهضبة | C177: 34 | D177: 11
A178: ساعة حائط 3400 | B178: سنتر محمد رشدي | C178: 112 | D178: 2
A179: سبورة معدن 2535 ع 72 | B179: سنتر محمد رشدي | C179: 60 | D179: 4
A180: ستارة خرز | B180: ذكريا | C180: 170 | D180: 2
A181: سحببة ورد نجمة | B181: شركة حسين علي | C181: 65 | D181: 8
A182: سحبة قرنفل ونجمة | B182: شركة حسين علي | C182: 135 | D182: 6
A183: سربا شريط ليد 8053 (5م) | B183: سنتر محمد رشدي | C183: 115 | D183: 3
A184: سرية وورم - 8044 | B184: سنتر محمد رشدي | C184: 242 | D184: 5
... A272: عروسة نضارة 6018 | B272: محمد رشدي | C272: 250 | D272: 3
...

Sheet  طلبيات
A1: اسم الصنف | B1: النوع | C1: السعر | D1: الكمية | E1: المجموع
A2: اشكال سيلفرات | B2: سيلفرات | C2: 120 | D2: 13 | E2: =' طلبيات'!$D2*' طلبيات'!$C2 -> 1560
A3: اشكال سيلفرات | B3: سيلفرات | C3: 95 | D3: 2 | E3: =' طلبيات'!$D3*' طلبيات'!$C3 -> 190
A4: كتاب ديكور | B4: كتب | C4: 17 | D4: 12 | E4: =' طلبيات'!$D4*' طلبيات'!$C4 -> 204
A5: اباجورة | B5: كهربائيات | C5: 165 | D5: 6 | E5: =' طلبيات'!$D5*' طلبيات'!$C5 -> 990
A6: فواحة | B6: كهربائيات | C6: 325 | D6: 2 | E6: =' طلبيات'!$D6*' طلبيات'!$C6 -> 650
A7: مبخرة | B7: خزف | C7: 60 | D7: 12 | E7: =' طلبيات'!$D7*' طلبيات'!$C7 -> 720
A8: شجرة مشمش اربع فروع | B8: شجر | C8: 275 | D8: 3 | E8: =' طلبيات'!$D8*' طلبيات'!$C8 -> 825
A9: شجرة مشمش خمس فروع | B9: شجر | C9: 325 | D9: 1 | E9: =' طلبيات'!$D9*' طلبيات'!$C9 -> 325
A10: بوت تركي | B10: بوتات | C10: 105 | D10: 4 | E10: =' طلبيات'!$D10*' طلبيات'!$C10 -> 420
A11: مكتبة | B11: بلاستيك | C11: 18 | D11: 24 | E11: =' طلبيات'!$D11*' طلبيات'!$C11 -> 432
E12: =' طلبيات'!$D12*' طلبيات'!$C12 -> 0
E13: =' طلبيات'!$D13*' طلبيات'!$C13 -> 0
E14: =' طلبيات'!$D14*' طلبيات'!$C14 -> 0
A15: Sum | B15: =SUBTOTAL(109,' طلبيات'!$B$2:$B$14) -> 0 | C15: =SUBTOTAL(109,' طلبيات'!$C$2:$C$14) -> 1505 | D15: =SUBTOTAL(109,' طلبيات'!$D$2:$D$14) -> 79 | E15: =SUBTOTAL(109,' طلبيات'!$E$2:$E$14) -> 6316
A18: اسم العنصر | B18: النوع | C18: سعر الشراء | D18: الكمية | E18: المجموع | F18: التاريخ
A19: فازة ازاز كبيره وبوكيه | B19: بوكيه | C19: 725 | D19: 1 | E19: =' طلبيات'!$D19*' طلبيات'!$C19 -> 725 | F19: 45832
A20: طقم زجاج ابيض وريش وورد صغير | B20: بوكيه | C20: 415 | D20: 1 | E20: =' طلبيات'!$D20*' طلبيات'!$C20 -> 415 | F20: 45832
A21: طقم زجاج ابيض وبوكيه اخضر | B21: بوكيه | C21: 325 | D21: 1 | E21: =' طلبيات'!$D21*' طلبيات'!$C21 -> 325 | F21: 45832
A22: طقم زجاج ابيض وريش بس | B22: بوكيه | C22: 300 | D22: 1 | E22: =' طلبيات'!$D22*' طلبيات'!$C22 -> 300 | F22: 45832
A23: فازة ازاز وبوكيه ورد غالي | B23: بوكيه زجاج | C23: 295 | D23: 2 | E23: =' طلبيات'!$D23*' طلبيات'!$C23 -> 590 | F23: 45832
A24: فازة ازاز وبوكيه ابيض وبيبي فلاور | B24: بوكيه زجاج | C24: 200 | D24: 1 | E24: =' طلبيات'!$D24*' طلبيات'!$C24 -> 200 | F24: 45832
A25: فازة خزف وبوكيه ابيض كبير | B25: بوكيه | C25: 185 | D25: 1 | E25: =' طلبيات'!$D25*' طلبيات'!$C25 -> 185 | F25: 45832
A26: فازة خزف وبوكيه ورد مقفول وورد صغير | B26: بوكيه | C26: 180 | D26: 2 | E26: =' طلبيات'!$D26*' طلبيات'!$C26 -> 360 | F26: 45832
A27: فازة ازاز وبوكيه | B27: بوكيه | C27: 180 | D27: 3 | E27: =' طلبيات'!$D27*' طلبيات'!$C27 -> 540 | F27: 45832
A28: بوكيه بلاستيك ورد كبير | B28: بوكيه | C28: 175 | D28: 1 | E28: =' طلبيات'!$D28*' طلبيات'!$C28 -> 175 | F28: 45832
A29: فازة خزف كبيره مشمش | B29: بوكيه | C29: 175 | D29: 4 | E29: =' طلبيات'!$D29*' طلبيات'!$C29 -> 700 | F29: 45832
A30: بوكيه بلاستيك | B30: بوكيه | C30: 160 | D30: 2 | E30: =' طلبيات'!$D30*' طلبيات'!$C30 -> 320 | F30: 45832
... A37: فازة خزف وبوكيه ورد مقفول | B37: بوكيه | C37: 125 | D37: 3 | E37: =' طلبيات'!$D37*' طلبيات'!$C37 -> 375 | F37: 45832
A38: بوكيه خزف مقسوم ورد شبه التاج | B38: بوكيه | C38: =225/2 -> 112.5 | D38: 2 | E38: =' طلبيات'!$D38*' طلبيات'!$C38 -> 225 | F38: 45832
A39: طقم زجاج ابيض فاضي | B39: زجاج ابيض | C39: 125 | D39: 1 | E39: =' طلبيات'!$D39*' طلبيات'!$C39 -> 125 | F39: 45832
A40: طقم دوناتس | B40: خزف | C40: 135 | D40: 3 | E40: =' طلبيات'!$D40*' طلبيات'!$C40 -> 405 | F40: 45832
A41: قطعة دوناتس | B41: خزف | C41: =135/3 -> 45 | D41: 2 | E41: =' طلبيات'!$D41*' طلبيات'!$C41 -> 90 | F41: 45832
A42: مزرعة بورسلين | B42: بوكيه | C42: 55 | D42: 1 | E42: =' طلبيات'!$D42*' طلبيات'!$C42 -> 55 | F42: 45832
A43: مزرعة بورسلين | B43: بوكيه | C43: 35 | D43: 9 | E43: =' طلبيات'!$D43*' طلبيات'!$C43 -> 315 | F43: 45832
A44: بوكيه اخضر | B44: ورد لوحده | C44: 175 | D44: 2 | E44: =' طلبيات'!$D44*' طلبيات'!$C44 -> 350 | F44: 45832
A45: طقم باسكت | B45: سيلفرات | C45: 755 | D45: 1 | E45: =' طلبيات'!$D45*' طلبيات'!$C45 -> 755 | F45: 45832
A46: شمعدان نخلة | B46: سيلفرات | C46: 625 | D46: 1 | E46: =' طلبيات'!$D46*' طلبيات'!$C46 -> 625 | F46: 45832
A47: شمعدان كريستال | B47: سيلفرات | C47: 595 | D47: 1 | E47: =' طلبيات'!$D47*' طلبيات'!$C47 -> 595 | F47: 45832
A48: شوكة كبيرة | B48: سيلفرات | C48: 220 | D48: 3 | E48: =' طلبيات'!$D48*' طلبيات'!$C48 -> 660 | F48: 45832
A49: شوكة وسط | B49: سيلفرات | C49: 155 | D49: 6 | E49: =' طلبيات'!$D49*' طلبيات'!$C49 -> 930 | F49: 45832
A50: شوكة صغيرة | B50: سيلفرات | C50: 130 | D50: 6 | E50: =' طلبيات'!$D50*' طلبيات'!$C50 -> 780 | F50: 45832
A51: شمعدان رفيع طويل عادي | B51: سيلفرات | C51: 205 | D51: 2 | E51: =' طلبيات'!$D51*' طلبيات'!$C51 -> 410 | F51: 45832
A52: شمعدان رفيع طويل اسود | B52: سيلفرات | C52: 215 | D52: 2 | E52: =' طلبيات'!$D52*' طلبيات'!$C52 -> 430 | F52: 45832
A53: كريستالة ديكور | B53: سيلفرات | C53: 175 | D53: 3 | E53: =' طلبيات'!$D53*' طلبيات'!$C53 -> 525 | F53: 45832
... A73: شجرة تركيب 18 ورقة | B73: شجر | C73: 145 | D73: 6 | E73: =' طلبيات'!$D73*' طلبيات'!$C73 -> 870 | F73: 45832
E74: =' طلبيات'!$D74*' طلبيات'!$C74 -> 0 | F74: 45832
E75: =' طلبيات'!$D75*' طلبيات'!$C75 -> 0 | F75: 45832
A76: Sum | B76: =SUBTOTAL(109,' طلبيات'!$B$19:$B$75) -> 0 | C76: =SUBTOTAL(109,' طلبيات'!$C$19:$C$75) -> 11852.5 | D76: =SUBTOTAL(109,' طلبيات'!$D$19:$D$75) -> 172 | E76: =SUBTOTAL(109,' طلبيات'!$E$19:$E$75) -> 24745
A79: اسم العنصر | B79: النوع | C79: سعر الشراء | D79: الكمية | E79: المجموع | F79: التاريخ
A80: شجرة مكثفة ورق | B80: شجر | C80: 310 | D80: 1 | E80: =' طلبيات'!$D80*' طلبيات'!$C80 -> 310 | F80: 45835
A81: شجرة مشمش خمس فروع | B81: شجر | C81: 325 | D81: 1 | E81: =' طلبيات'!$D81*' طلبيات'!$C81 -> 325 | F81: 45835
A82: شجرة مشمش 4 فروع | B82: شجر | C82: 275 | D82: 5 | E82: =' طلبيات'!$D82*' طلبيات'!$C82 -> 1375 | F82: 45835
A83: شجرة مشمش 3 فروع | B83: شجر | C83: 225 | D83: 1 | E83: =' طلبيات'!$D83*' طلبيات'!$C83 -> 225 | F83: 45835
A84: شجرة مشمش فرعين | B84: شجر | C84: 175 | D84: 6 | E84: =' طلبيات'!$D84*' طلبيات'!$C84 -> 1050 | F84: 45835
A85: شجرة ورق عريض جلد | B85: شجر | C85: 210 | D85: 3 | E85: =' طلبيات'!$D85*' طلبيات'!$C85 -> 630 | F85: 45835
A86: طقم دوناتس | B86: خزف | C86: 135 | D86: 2 | E86: =' طلبيات'!$D86*' طلبيات'!$C86 -> 270 | F86: 45835
A87: طقم دوناتس طويل | B87: خزف | C87: 165 | D87: 1 | E87: =' طلبيات'!$D87*' طلبيات'!$C87 -> 165 | F87: 45835
A88: فازة خزف متوسطة | B88: خزف | C88: 75 | D88: 11 | E88: =' طلبيات'!$D88*' طلبيات'!$C88 -> 825 | F88: 45835
A89: فازة خزف غالية | B89: خزف | C89: 95 | D89: 2 | E89: =' طلبيات'!$D89*' طلبيات'!$C89 -> 190 | F89: 45835
A90: فازة كريستال عسلي | B90: زجاج | C90: 365 | D90: 1 | E90: =' طلبيات'!$D90*' طلبيات'!$C90 -> 365 | F90: 45835
A91: شكل عاج صغير | B91: سيلفرات | C91: 210 | D91: 2 | E91: =' طلبيات'!$D91*' طلبيات'!$C91 -> 420 | F91: 45835
... A96: شمعدان بلياستر بالفازة | B96: سيلفرات | C96: 750 | D96: 1 | E96: =' طلبيات'!$D96*' طلبيات'!$C96 -> 750 | F96: 45835
A97: شكل صبارة خزف صغيرة | B97: خزف | C97: 32 | D97: 18 | E97: =' طلبيات'!$D97*' طلبيات'!$C97 -> 576 | F97: 45835 | I97: =220+30 -> 250
A98: بوكيه كريستال شفاف وبوكيه اخضر | B98: بوكيه | C98: 510 | D98: 1 | E98: =' طلبيات'!$D98*' طلبيات'!$C98 -> 510 | F98: 45835
A99: بوت وسط | B99: بوتات | C99: 95 | D99: 7 | E99: =' طلبيات'!$D99*' طلبيات'!$C99 -> 665 | F99: 45835
A100: بوكيه ورد صغير | B100: ورد لوحده | C100: 115 | D100: 2 | E100: =' طلبيات'!$D100*' طلبيات'!$C100 -> 230 | F100: 45835
A101: بوكيه ورد نوعين | B101: ورد لوحده | C101: 145 | D101: 2 | E101: =' طلبيات'!$D101*' طلبيات'!$C101 -> 290 | F101: 45835
A102: بوكيه ورد طويل | B102: ورد لوحده | C102: 195 | D102: 2 | E102: =' طلبيات'!$D102*' طلبيات'!$C102 -> 390 | F102: 45835
A103: بوكيه شبه التاج | B103: ورد لوحده | C103: 175 | D103: 3 | E103: =' طلبيات'!$D103*' طلبيات'!$C103 -> 525 | F103: 45835
A104: بوكيه فل | B104: ورد لوحده | C104: 110 | D104: 2 | E104: =' طلبيات'!$D104*' طلبيات'!$C104 -> 220 | F104: 45835
A105: افرع طويلة | B105: ورد لوحده | C105: 75 | D105: 20 | E105: =' طلبيات'!$D105*' طلبيات'!$C105 -> 1500 | F105: 45835
A106: افرع هيش | B106: ورد لوحده | C106: 50 | D106: 5 | E106: =' طلبيات'!$D106*' طلبيات'!$C106 -> 250 | F106: 45835
A107: بوكيه فازة بورسلين دهبي وورد شبه التاج | B107: بوكيه | C107: 385 | D107: 1 | E107: =' طلبيات'!$D107*' طلبيات'!$C107 -> 385 | F107: 45835
A108: بوكيه بلاستيك و ريش واخضر عرايس:) | B108: بوكيه | C108: 310 | D108: 1 | E108: =' طلبيات'!$D108*' طلبيات'!$C108 -> 310 | F108: 45835
A109: بوكيه خزف غالي وورد مجفف | B109: بوكيه | C109: 280 | D109: 3 | E109: =' طلبيات'!$D109*' طلبيات'!$C109 -> 840 | F109: 45835
... A134: مزرعة صغيرة اكليرك | B134: بوكيه | C134: 30 | D134: 16 | E134: =' طلبيات'!$D134*' طلبيات'!$C134 -> 480 | F134: 45835
A135: Sum | B135: 0 | C135: 11549.5 | D135: 190 | E135: 23146 | F135: 2520925
A137: اسم العنصر | B137: التفاصيل | C137: النوع | D137: سعر الشراء | E137: الكمية | F137: المجموع | G137: التاريخ | H137: المورد
A138: شجرة فانباخيا صغيرة | C138: شجر | D138: 235 | E138: 1 | F138: 235 | G138: 45856 | H138: ذكريا
A139: شجرة ورق عريض | C139: شجر | D139: 195 | E139: 4 | F139: 780 | G139: 45856 | H139: ذكريا
A140: شجرة اريكا صغيرة | C140: شجر | D140: 425 | E140: 1 | F140: 425 | G140: 45856 | H140: ذكريا
A141: شجرة اريكا وسط | C141: شجر | D141: 550 | E141: 1 | F141: 550 | G141: 45856 | H141: ذكريا
A142: بولا خزف وبوكيه ورد صغير | C142: بوكيه | D142: 80 | E142: 6 | F142: 480 | G142: 45856 | H142: ذكريا
A143: بوت صغير هااند ميد و 2 بوكيه | C143: بوكيه | D143: 235 | E143: 3 | F143: 705 | G143: 45856 | H143: ذكريا
A144: بوت تركي هاند ميد | C144: بوتات | D144: 275 | E144: 1 | F144: 275 | G144: 45856 | H144: ذكريا
A145: بوت هاند ميد كبير | C145: بوكيه | D145: 425 | E145: 2 | F145: 850 | G145: 45856 | H145: ذكريا
A146: بوت كبير | C146: بوتات | D146: 175 | E146: 10 | F146: 1750 | G146: 45856 | H146: ذكريا
A147: فرع مشمش جديد | C147: ورد لوحده | D147: 150 | E147: 2 | F147: 300 | G147: 45856 | H147: ذكريا
A148: بوكيه كله | C148: ورد لوحده | D148: 175 | E148: 1 | F148: 175 | G148: 45856 | H148: ذكريا
A149: بوكيه ورد كبير | C149: ورد لوحده | D149: 145 | E149: 1 | F149: 145 | G149: 45856 | H149: ذكريا
... A153: طقم باسكت | C153: سيلفرات | D153: 695 | E153: 1 | F153: 695 | G153: 45856 | H153: ذكريا
A154: موديل رقم 2043 | B154: طقم طبق فاكهة من قطعتين | C154: سيلفرات | D154: 1299 | E154: 1 | F154: 1299 | G154: 45856 | H154: ذكريا
A155: موديل رقم 2042 | B155: طقم طبق فاكهة من قطعتين | C155: سيلفرات | D155: 1299 | E155: 1 | F155: 1299 | G155: 45856 | H155: ذكريا
A156: موديل رقم 2051 | B156: طبق تسالي 4 عين | C156: سيلفرات | D156: 1399 | E156: 2 | F156: 2798 | G156: 45856 | H156: ذكريا
A157: موديل رقم 2001 | B157: طبق تسالي 5 عين | C157: سيلفرات | D157: 1250 | E157: 1 | F157: 1250 | G157: 45856 | H157: ذكريا
A158: موديل رقم 2003 | B158: طبق تسالي 4 عين | C158: سيلفرات | D158: 1100 | E158: 2 | F158: 2200 | G158: 45856 | H158: ذكريا
A159: موديل رقم 2058 | B159: شيالة 3 دور | C159: سيلفرات | D159: 1499 | E159: 1 | F159: 1499 | G159: 45856 | H159: ذكريا
A160: موديل رقم 2057 | B160: شيالة 3 دور | C160: سيلفرات | D160: 1499 | E160: 1 | F160: 1499 | G160: 45856 | H160: ذكريا
A161: موديل 935 | B161: شيالة 2 دور | C161: سيلفرات | D161: 999 | E161: 1 | F161: 999 | G161: 45856 | H161: ذكريا
...

Sheet Manufacturing
A1: ManufactureID | B1: ProductName | C1: ProductType | D1: QtyToProduce | E1: CostSharePercent | F1: Status | G1: Date | H1: Notes
A2: مقزم_خضرا _الوان | B2: مقزم خضرة الوان | C2: بوكيه | D2: 18 | E2: 100 | F2: done | G2: 46150 | H2: ✅ Success. Cost: 173.00

Sheet Manufacturing_Items
A1: ManufactureID | B1: MaterialName | C1: Type | D1: Supplier | E1: Qty/Unit | F1: TotalQty | G1: Price | H1: Total Price | I1: Available Quantity
A2: مقزم_خضرا _الوان | B2: خضرة اللوان 18 | C2: =IF(B2="","",IFERROR(VLOOKUP(B2, Stock_New!A:F, 2, FALSE),"")) -> ورد لوحدة | D2: =IF(C2="","",IFERROR(VLOOKUP(B2, Stock_New!A:G, 3, FALSE),"")) -> شركة الفرسان | E2: =1/18 -> 0.055555556 | F2: 1 | G2: =IF(B2="", "", IFERROR(VLOOKUP(B2, Stock_New!A:G, 4, FALSE), "")) -> 110 | H2: =G2*F2 -> 110 | I2: =IF(B2="","",IFERROR(VLOOKUP(B2, Stock_New!A:F, 5, FALSE),"")) -> 1.4444444
A3: مقزم_خضرا _الوان | B3: بروبلين 5سم عبدالله | C3: =IF(B3="","",IFERROR(VLOOKUP(B3, Stock_New!A:F, 2, FALSE),"")) -> بوت مقزمات | D3: =IF(C3="","",IFERROR(VLOOKUP(B3, Stock_New!A:G, 3, FALSE),"")) -> شركة حسين علي | E3: 1 | F3: 18 | G3: =IF(B3="", "", IFERROR(VLOOKUP(B3, Stock_New!A:G, 4, FALSE), "")) -> 3.5 | H3: =G3*F3 -> 63 | I3: =IF(B3="","",IFERROR(VLOOKUP(B3, Stock_New!A:F, 5, FALSE),"")) -> 142
C4: =IF(B4="","",IFERROR(VLOOKUP(B4, Stock_New!A:F, 2, FALSE),"")) | D4: =IF(C4="","",IFERROR(VLOOKUP(B4, Stock_New!A:G, 3, FALSE),"")) | G4: =IF(B4="", "", IFERROR(VLOOKUP(B4, Stock_New!A:G, 4, FALSE), "")) | H4: =G4*F4 -> 0 | I4: =IF(B4="","",IFERROR(VLOOKUP(B4, Stock_New!A:F, 5, FALSE),""))
G5: =IF(B5="", "", IFERROR(VLOOKUP(B5, Stock_New!A:G, 4, FALSE), "")) | H5: =G5*F5 -> 0 | I5: =IF(B5="","",IFERROR(VLOOKUP(B5, Stock_New!A:F, 5, FALSE),""))
G6: =IF(B6="", "", IFERROR(VLOOKUP(B6, Stock_New!A:G, 4, FALSE), "")) | H6: =G6*F6 -> 0 | I6: =IF(B6="","",IFERROR(VLOOKUP(B6, Stock_New!A:F, 5, FALSE),""))
C7: =IF(B7="","",IFERROR(VLOOKUP(B7, Stock_New!A:F, 2, FALSE),"")) | D7: =IF(C7="","",IFERROR(VLOOKUP(C7, Stock_New!B:G, 2, FALSE),"")) | G7: =IF(B7="", "", IFERROR(VLOOKUP(B7, Stock_New!A:G, 4, FALSE), "")) | H7: =G7*F7 -> 0 | I7: =IF(B7="","",IFERROR(VLOOKUP(B7, Stock_New!A:F, 5, FALSE),""))
